<?xml version="1.0" encoding="ISO-8859-1" standalone="yes"?>
<nite:root nite:id="Bmr012.C.segs" xmlns:nite="http://nite.sourceforge.net/">
   <segment nite:id="Bmr012.segment.43" starttime="76.743" endtime="77.773" participant="fe016" timing-provenance="dialogueact">
      <nite:child href="Bmr012.C.words.xml#id(Bmr012.w.444)..id(Bmr012.w.448)"/>
   </segment>
   <segment nite:id="Bmr012.segment.47" starttime="82.467" endtime="83.439" participant="fe016" timing-provenance="segment">
      <nite:child href="Bmr012.C.words.xml#id(Bmr012.w.475)..id(Bmr012.vocalsound.11)"/>
   </segment>
   <segment nite:id="Bmr012.segment.50" starttime="84.815" endtime="90.865" participant="fe016" timing-provenance="dialogueact">
      <nite:child href="Bmr012.C.words.xml#id(Bmr012.w.489)..id(Bmr012.w.514)"/>
   </segment>
   <segment nite:id="Bmr012.segment.59" starttime="92.891" endtime="93.211" participant="fe016" timing-provenance="dialogueact">
      <nite:child href="Bmr012.C.words.xml#id(Bmr012.w.564)..id(Bmr012.w.565)"/>
   </segment>
   <segment nite:id="Bmr012.segment.85" starttime="136.516" endtime="139.895" participant="fe016" timing-provenance="segment">
      <nite:child href="Bmr012.C.words.xml#id(Bmr012.w.740)..id(Bmr012.comment.2)"/>
   </segment>
   <segment nite:id="Bmr012.segment.91" starttime="140.182" endtime="142.817" participant="fe016" timing-provenance="segment">
      <nite:child href="Bmr012.C.words.xml#id(Bmr012.w.774)..id(Bmr012.comment.3)"/>
   </segment>
   <segment nite:id="Bmr012.segment.96" starttime="146.471" endtime="147.191" participant="fe016" timing-provenance="dialogueact">
      <nite:child href="Bmr012.C.words.xml#id(Bmr012.w.837)..id(Bmr012.w.839)"/>
   </segment>
   <segment nite:id="Bmr012.segment.97" starttime="147.505" endtime="153.863" participant="fe016" timing-provenance="segment">
      <nite:child href="Bmr012.C.words.xml#id(Bmr012.w.840)..id(Bmr012.comment.4)"/>
   </segment>
   <segment nite:id="Bmr012.segment.104" starttime="157.97" endtime="161.104" participant="fe016" timing-provenance="segment">
      <nite:child href="Bmr012.C.words.xml#id(Bmr012.w.891)..id(Bmr012.comment.5)"/>
   </segment>
   <segment nite:id="Bmr012.segment.136" starttime="231.954" endtime="233.714" participant="fe016" timing-provenance="dialogueact">
      <nite:child href="Bmr012.C.words.xml#id(Bmr012.w.1114)..id(Bmr012.w.1123)"/>
   </segment>
   <segment nite:id="Bmr012.segment.137" starttime="234.154" endtime="234.774" participant="fe016" timing-provenance="dialogueact">
      <nite:child href="Bmr012.C.words.xml#id(Bmr012.w.1124)..id(Bmr012.w.1126)"/>
   </segment>
   <segment nite:id="Bmr012.segment.140" starttime="235.414" endtime="236.604" participant="fe016" timing-provenance="dialogueact">
      <nite:child href="Bmr012.C.words.xml#id(Bmr012.w.1136)..id(Bmr012.w.1139)"/>
   </segment>
   <segment nite:id="Bmr012.segment.143" starttime="238.479" endtime="239.689" participant="fe016" timing-provenance="dialogueact">
      <nite:child href="Bmr012.C.words.xml#id(Bmr012.w.1147)"/>
   </segment>
   <segment nite:id="Bmr012.segment.144" starttime="241.18" endtime="243.14" participant="fe016" timing-provenance="dialogueact">
      <nite:child href="Bmr012.C.words.xml#id(Bmr012.w.1148)..id(Bmr012.w.1155)"/>
   </segment>
   <segment nite:id="Bmr012.segment.145" starttime="243.14" endtime="245.21" participant="fe016" timing-provenance="dialogueact">
      <nite:child href="Bmr012.C.words.xml#id(Bmr012.w.1156)..id(Bmr012.w.1160)"/>
   </segment>
   <segment nite:id="Bmr012.segment.146" starttime="246.27" endtime="247.39" participant="fe016" timing-provenance="dialogueact">
      <nite:child href="Bmr012.C.words.xml#id(Bmr012.w.1161)"/>
   </segment>
   <segment nite:id="Bmr012.segment.147" starttime="247.45" endtime="252.32" participant="fe016" timing-provenance="dialogueact">
      <nite:child href="Bmr012.C.words.xml#id(Bmr012.w.1162)..id(Bmr012.w.1178)"/>
   </segment>
   <segment nite:id="Bmr012.segment.148" starttime="252.91" endtime="258.5" participant="fe016" timing-provenance="dialogueact">
      <nite:child href="Bmr012.C.words.xml#id(Bmr012.w.1179)..id(Bmr012.w.1197)"/>
   </segment>
   <segment nite:id="Bmr012.segment.150" starttime="258.93" endtime="261.76" participant="fe016" timing-provenance="dialogueact">
      <nite:child href="Bmr012.C.words.xml#id(Bmr012.w.1198)..id(Bmr012.w.1208)"/>
   </segment>
   <segment nite:id="Bmr012.segment.151" starttime="262.61" endtime="263.0" participant="fe016" timing-provenance="dialogueact">
      <nite:child href="Bmr012.C.words.xml#id(Bmr012.w.1209)"/>
   </segment>
   <segment nite:id="Bmr012.segment.152" starttime="264.103" endtime="266.823" participant="fe016" timing-provenance="dialogueact">
      <nite:child href="Bmr012.C.words.xml#id(Bmr012.w.1210)..id(Bmr012.w.1219)"/>
   </segment>
   <segment nite:id="Bmr012.segment.153" starttime="267.353" endtime="270.193" participant="fe016" timing-provenance="dialogueact">
      <nite:child href="Bmr012.C.words.xml#id(Bmr012.w.1220)..id(Bmr012.w.1226)"/>
   </segment>
   <segment nite:id="Bmr012.segment.154" starttime="270.583" endtime="277.183" participant="fe016" timing-provenance="dialogueact">
      <nite:child href="Bmr012.C.words.xml#id(Bmr012.w.1227)..id(Bmr012.w.1246)"/>
   </segment>
   <segment nite:id="Bmr012.segment.155" starttime="277.52" endtime="279.952" participant="fe016" timing-provenance="segment">
      <nite:child href="Bmr012.C.words.xml#id(Bmr012.w.1247)..id(Bmr012.disfmarker.38)"/>
   </segment>
   <segment nite:id="Bmr012.segment.156" starttime="280.093" endtime="280.883" participant="fe016" timing-provenance="dialogueact">
      <nite:child href="Bmr012.C.words.xml#id(Bmr012.w.1253)..id(Bmr012.w.1255)"/>
   </segment>
   <segment nite:id="Bmr012.segment.157" starttime="281.723" endtime="289.103" participant="fe016" timing-provenance="dialogueact">
      <nite:child href="Bmr012.C.words.xml#id(Bmr012.w.1256)..id(Bmr012.w.1288)"/>
   </segment>
   <segment nite:id="Bmr012.segment.158" starttime="289.963" endtime="296.403" participant="fe016" timing-provenance="dialogueact">
      <nite:child href="Bmr012.C.words.xml#id(Bmr012.w.1289)..id(Bmr012.w.1317)"/>
   </segment>
   <segment nite:id="Bmr012.segment.161" starttime="296.753" endtime="300.883" participant="fe016" timing-provenance="dialogueact">
      <nite:child href="Bmr012.C.words.xml#id(Bmr012.w.1321)..id(Bmr012.w.1341)"/>
   </segment>
   <segment nite:id="Bmr012.segment.162" starttime="301.303" endtime="304.323" participant="fe016" timing-provenance="dialogueact">
      <nite:child href="Bmr012.C.words.xml#id(Bmr012.w.1342)..id(Bmr012.w.1351)"/>
   </segment>
   <segment nite:id="Bmr012.segment.168" starttime="309.721" endtime="310.92" participant="fe016" timing-provenance="segment">
      <nite:child href="Bmr012.C.words.xml#id(Bmr012.w.1389)..id(Bmr012.disfmarker.47)"/>
   </segment>
   <segment nite:id="Bmr012.segment.169" starttime="310.931" endtime="313.071" participant="fe016" timing-provenance="dialogueact">
      <nite:child href="Bmr012.C.words.xml#id(Bmr012.w.1394)..id(Bmr012.w.1399)"/>
   </segment>
   <segment nite:id="Bmr012.segment.172" starttime="313.221" endtime="315.521" participant="fe016" timing-provenance="dialogueact">
      <nite:child href="Bmr012.C.words.xml#id(Bmr012.w.1413)..id(Bmr012.w.1422)"/>
   </segment>
   <segment nite:id="Bmr012.segment.185" starttime="330.528" endtime="331.359" participant="fe016" timing-provenance="segment">
      <nite:child href="Bmr012.C.words.xml#id(Bmr012.w.1520)..id(Bmr012.w.1521)"/>
   </segment>
   <segment nite:id="Bmr012.segment.189" starttime="333.401" endtime="335.243" participant="fe016" timing-provenance="segment">
      <nite:child href="Bmr012.C.words.xml#id(Bmr012.w.1533)..id(Bmr012.disfmarker.57)"/>
   </segment>
   <segment nite:id="Bmr012.segment.191" starttime="335.251" endtime="340.531" participant="fe016" timing-provenance="dialogueact">
      <nite:child href="Bmr012.C.words.xml#id(Bmr012.w.1539)..id(Bmr012.w.1557)"/>
   </segment>
   <segment nite:id="Bmr012.segment.195" starttime="341.121" endtime="341.541" participant="fe016" timing-provenance="dialogueact">
      <nite:child href="Bmr012.C.words.xml#id(Bmr012.w.1580)"/>
   </segment>
   <segment nite:id="Bmr012.segment.196" starttime="342.845" endtime="349.039" participant="fe016" timing-provenance="segment">
      <nite:child href="Bmr012.C.words.xml#id(Bmr012.w.1581)..id(Bmr012.vocalsound.39)"/>
   </segment>
   <segment nite:id="Bmr012.segment.206" starttime="349.848" endtime="350.988" participant="fe016" timing-provenance="dialogueact">
      <nite:child href="Bmr012.C.words.xml#id(Bmr012.w.1637)..id(Bmr012.w.1641)"/>
   </segment>
   <segment nite:id="Bmr012.segment.207" starttime="351.547" endtime="351.897" participant="fe016" timing-provenance="dialogueact">
      <nite:child href="Bmr012.C.words.xml#id(Bmr012.w.1642)..id(Bmr012.w.1643)"/>
   </segment>
   <segment nite:id="Bmr012.segment.212" starttime="352.924" endtime="356.064" participant="fe016" timing-provenance="dialogueact">
      <nite:child href="Bmr012.C.words.xml#id(Bmr012.w.1662)..id(Bmr012.w.1671)"/>
   </segment>
   <segment nite:id="Bmr012.segment.216" starttime="356.284" endtime="360.328" participant="fe016" timing-provenance="segment">
      <nite:child href="Bmr012.C.words.xml#id(Bmr012.w.1710)..id(Bmr012.disfmarker.71)"/>
   </segment>
   <segment nite:id="Bmr012.segment.220" starttime="362.506" endtime="362.866" participant="fe016" timing-provenance="dialogueact">
      <nite:child href="Bmr012.C.words.xml#id(Bmr012.w.1737)..id(Bmr012.w.1738)"/>
   </segment>
   <segment nite:id="Bmr012.segment.222" starttime="365.305" endtime="365.685" participant="fe016" timing-provenance="dialogueact">
      <nite:child href="Bmr012.C.words.xml#id(Bmr012.w.1741)..id(Bmr012.w.1742)"/>
   </segment>
   <segment nite:id="Bmr012.segment.229" starttime="381.623" endtime="383.323" participant="fe016" timing-provenance="dialogueact">
      <nite:child href="Bmr012.C.words.xml#id(Bmr012.w.1809)..id(Bmr012.w.1817)"/>
   </segment>
   <segment nite:id="Bmr012.segment.234" starttime="383.873" endtime="384.143" participant="fe016" timing-provenance="dialogueact">
      <nite:child href="Bmr012.C.words.xml#id(Bmr012.w.1828)..id(Bmr012.w.1829)"/>
   </segment>
   <segment nite:id="Bmr012.segment.235" starttime="384.523" endtime="388.273" participant="fe016" timing-provenance="dialogueact">
      <nite:child href="Bmr012.C.words.xml#id(Bmr012.w.1830)..id(Bmr012.w.1845)"/>
   </segment>
   <segment nite:id="Bmr012.segment.242" starttime="388.753" endtime="389.983" participant="fe016" timing-provenance="dialogueact">
      <nite:child href="Bmr012.C.words.xml#id(Bmr012.w.1863)..id(Bmr012.w.1867)"/>
   </segment>
   <segment nite:id="Bmr012.segment.247" starttime="391.594" endtime="394.769" participant="fe016" timing-provenance="segment">
      <nite:child href="Bmr012.C.words.xml#id(Bmr012.w.1880)..id(Bmr012.disfmarker.84)"/>
   </segment>
   <segment nite:id="Bmr012.segment.252" starttime="395.141" endtime="401.701" participant="fe016" timing-provenance="dialogueact">
      <nite:child href="Bmr012.C.words.xml#id(Bmr012.w.1889)..id(Bmr012.w.1917)"/>
   </segment>
   <segment nite:id="Bmr012.segment.261" starttime="404.931" endtime="405.551" participant="fe016" timing-provenance="dialogueact">
      <nite:child href="Bmr012.C.words.xml#id(Bmr012.w.1996)..id(Bmr012.w.1997)"/>
   </segment>
   <segment nite:id="Bmr012.segment.269" starttime="416.652" endtime="424.152" participant="fe016" timing-provenance="dialogueact">
      <nite:child href="Bmr012.C.words.xml#id(Bmr012.w.2035)..id(Bmr012.w.2066)"/>
   </segment>
   <segment nite:id="Bmr012.segment.278" starttime="425.224" endtime="432.044" participant="fe016" timing-provenance="dialogueact">
      <nite:child href="Bmr012.C.words.xml#id(Bmr012.w.2094)..id(Bmr012.w.2124)"/>
   </segment>
   <segment nite:id="Bmr012.segment.283" starttime="432.454" endtime="436.714" participant="fe016" timing-provenance="dialogueact">
      <nite:child href="Bmr012.C.words.xml#id(Bmr012.w.2139)..id(Bmr012.w.2157)"/>
   </segment>
   <segment nite:id="Bmr012.segment.285" starttime="437.018" endtime="438.409" participant="fe016" timing-provenance="segment">
      <nite:child href="Bmr012.C.words.xml#id(Bmr012.w.2162)..id(Bmr012.disfmarker.103)"/>
   </segment>
   <segment nite:id="Bmr012.segment.290" starttime="444.989" endtime="446.849" participant="fe016" timing-provenance="dialogueact">
      <nite:child href="Bmr012.C.words.xml#id(Bmr012.w.2208)..id(Bmr012.w.2217)"/>
   </segment>
   <segment nite:id="Bmr012.segment.295" starttime="449.9" endtime="455.31" participant="fe016" timing-provenance="dialogueact">
      <nite:child href="Bmr012.C.words.xml#id(Bmr012.w.2242)..id(Bmr012.w.2262)"/>
   </segment>
   <segment nite:id="Bmr012.segment.297" starttime="455.98" endtime="457.37" participant="fe016" timing-provenance="dialogueact">
      <nite:child href="Bmr012.C.words.xml#id(Bmr012.w.2265)..id(Bmr012.w.2268)"/>
   </segment>
   <segment nite:id="Bmr012.segment.300" starttime="457.907" endtime="459.333" participant="fe016" timing-provenance="segment">
      <nite:child href="Bmr012.C.words.xml#id(Bmr012.w.2271)..id(Bmr012.disfmarker.106)"/>
   </segment>
   <segment nite:id="Bmr012.segment.302" starttime="459.61" endtime="463.06" participant="fe016" timing-provenance="dialogueact">
      <nite:child href="Bmr012.C.words.xml#id(Bmr012.w.2281)..id(Bmr012.w.2294)"/>
   </segment>
   <segment nite:id="Bmr012.segment.307" starttime="463.34" endtime="467.07" participant="fe016" timing-provenance="dialogueact">
      <nite:child href="Bmr012.C.words.xml#id(Bmr012.w.2301)..id(Bmr012.w.2316)"/>
   </segment>
   <segment nite:id="Bmr012.segment.310" starttime="467.48" endtime="476.13" participant="fe016" timing-provenance="dialogueact">
      <nite:child href="Bmr012.C.words.xml#id(Bmr012.w.2320)..id(Bmr012.w.2355)"/>
   </segment>
   <segment nite:id="Bmr012.segment.316" starttime="476.13" endtime="478.91" participant="fe016" timing-provenance="dialogueact">
      <nite:child href="Bmr012.C.words.xml#id(Bmr012.w.2362)..id(Bmr012.w.2373)"/>
   </segment>
   <segment nite:id="Bmr012.segment.320" starttime="479.5" endtime="480.44" participant="fe016" timing-provenance="dialogueact">
      <nite:child href="Bmr012.C.words.xml#id(Bmr012.w.2408)..id(Bmr012.w.2413)"/>
   </segment>
   <segment nite:id="Bmr012.segment.321" starttime="484.87" endtime="486.87" participant="fe016" timing-provenance="dialogueact">
      <nite:child href="Bmr012.C.words.xml#id(Bmr012.w.2414)..id(Bmr012.w.2420)"/>
   </segment>
   <segment nite:id="Bmr012.segment.325" starttime="487.64" endtime="488.51" participant="fe016" timing-provenance="dialogueact">
      <nite:child href="Bmr012.C.words.xml#id(Bmr012.w.2454)"/>
   </segment>
   <segment nite:id="Bmr012.segment.328" starttime="494.275" endtime="495.346" participant="fe016" timing-provenance="segment">
      <nite:child href="Bmr012.C.words.xml#id(Bmr012.w.2487)..id(Bmr012.disfmarker.112)"/>
   </segment>
   <segment nite:id="Bmr012.segment.329" starttime="497.072" endtime="498.292" participant="fe016" timing-provenance="dialogueact">
      <nite:child href="Bmr012.C.words.xml#id(Bmr012.w.2489)..id(Bmr012.w.2492)"/>
   </segment>
   <segment nite:id="Bmr012.segment.332" starttime="498.762" endtime="505.662" participant="fe016" timing-provenance="dialogueact">
      <nite:child href="Bmr012.C.words.xml#id(Bmr012.w.2502)..id(Bmr012.w.2531)"/>
   </segment>
   <segment nite:id="Bmr012.segment.336" starttime="506.042" endtime="507.742" participant="fe016" timing-provenance="dialogueact">
      <nite:child href="Bmr012.C.words.xml#id(Bmr012.w.2542)..id(Bmr012.w.2548)"/>
   </segment>
   <segment nite:id="Bmr012.segment.338" starttime="508.242" endtime="509.292" participant="fe016" timing-provenance="dialogueact">
      <nite:child href="Bmr012.C.words.xml#id(Bmr012.w.2554)..id(Bmr012.w.2555)"/>
   </segment>
   <segment nite:id="Bmr012.segment.340" starttime="510.572" endtime="512.751" participant="fe016" timing-provenance="segment">
      <nite:child href="Bmr012.C.words.xml#id(Bmr012.w.2566)..id(Bmr012.disfmarker.113)"/>
   </segment>
   <segment nite:id="Bmr012.segment.346" starttime="517.307" endtime="519.877" participant="fe016" timing-provenance="dialogueact">
      <nite:child href="Bmr012.C.words.xml#id(Bmr012.w.2596)..id(Bmr012.w.2607)"/>
   </segment>
   <segment nite:id="Bmr012.segment.350" starttime="520.247" endtime="520.707" participant="fe016" timing-provenance="dialogueact">
      <nite:child href="Bmr012.C.words.xml#id(Bmr012.w.2616)..id(Bmr012.w.2617)"/>
   </segment>
   <segment nite:id="Bmr012.segment.351" starttime="521.389" endtime="523.15" participant="fe016" timing-provenance="segment">
      <nite:child href="Bmr012.C.words.xml#id(Bmr012.w.2618)..id(Bmr012.disfmarker.116)"/>
   </segment>
   <segment nite:id="Bmr012.segment.354" starttime="522.317" endtime="526.247" participant="fe016" timing-provenance="dialogueact">
      <nite:child href="Bmr012.C.words.xml#id(Bmr012.w.2633)..id(Bmr012.w.2639)"/>
   </segment>
   <segment nite:id="Bmr012.segment.358" starttime="526.457" endtime="529.497" participant="fe016" timing-provenance="dialogueact">
      <nite:child href="Bmr012.C.words.xml#id(Bmr012.w.2646)..id(Bmr012.w.2663)"/>
   </segment>
   <segment nite:id="Bmr012.segment.359" starttime="530.097" endtime="530.557" participant="fe016" timing-provenance="dialogueact">
      <nite:child href="Bmr012.C.words.xml#id(Bmr012.w.2664)"/>
   </segment>
   <segment nite:id="Bmr012.segment.360" starttime="530.977" endtime="531.877" participant="fe016" timing-provenance="dialogueact">
      <nite:child href="Bmr012.C.words.xml#id(Bmr012.w.2665)..id(Bmr012.w.2667)"/>
   </segment>
   <segment nite:id="Bmr012.segment.361" starttime="532.241" endtime="536.88" participant="fe016" timing-provenance="segment">
      <nite:child href="Bmr012.C.words.xml#id(Bmr012.w.2668)..id(Bmr012.disfmarker.117)"/>
   </segment>
   <segment nite:id="Bmr012.segment.363" starttime="537.157" endtime="541.897" participant="fe016" timing-provenance="dialogueact">
      <nite:child href="Bmr012.C.words.xml#id(Bmr012.w.2681)..id(Bmr012.w.2696)"/>
   </segment>
   <segment nite:id="Bmr012.segment.364" starttime="542.174" endtime="548.169" participant="fe016" timing-provenance="segment">
      <nite:child href="Bmr012.C.words.xml#id(Bmr012.w.2697)..id(Bmr012.disfmarker.119)"/>
   </segment>
   <segment nite:id="Bmr012.segment.367" starttime="548.177" endtime="550.347" participant="fe016" timing-provenance="dialogueact">
      <nite:child href="Bmr012.C.words.xml#id(Bmr012.w.2720)..id(Bmr012.w.2727)"/>
   </segment>
   <segment nite:id="Bmr012.segment.368" starttime="550.747" endtime="557.017" participant="fe016" timing-provenance="dialogueact">
      <nite:child href="Bmr012.C.words.xml#id(Bmr012.w.2728)..id(Bmr012.w.2756)"/>
   </segment>
   <segment nite:id="Bmr012.segment.371" starttime="557.697" endtime="558.077" participant="fe016" timing-provenance="dialogueact">
      <nite:child href="Bmr012.C.words.xml#id(Bmr012.w.2779)"/>
   </segment>
   <segment nite:id="Bmr012.segment.375" starttime="563.908" endtime="567.268" participant="fe016" timing-provenance="dialogueact">
      <nite:child href="Bmr012.C.words.xml#id(Bmr012.w.2796)..id(Bmr012.w.2814)"/>
   </segment>
   <segment nite:id="Bmr012.segment.383" starttime="567.598" endtime="568.418" participant="fe016" timing-provenance="dialogueact">
      <nite:child href="Bmr012.C.words.xml#id(Bmr012.w.2837)..id(Bmr012.w.2838)"/>
   </segment>
   <segment nite:id="Bmr012.segment.384" starttime="569.918" endtime="570.378" participant="fe016" timing-provenance="dialogueact">
      <nite:child href="Bmr012.C.words.xml#id(Bmr012.w.2839)"/>
   </segment>
   <segment nite:id="Bmr012.segment.387" starttime="572.19" endtime="573.873" participant="fe016" timing-provenance="segment">
      <nite:child href="Bmr012.C.words.xml#id(Bmr012.vocalsound.74)"/>
   </segment>
   <segment nite:id="Bmr012.segment.390" starttime="574.063" endtime="576.663" participant="fe016" timing-provenance="dialogueact">
      <nite:child href="Bmr012.C.words.xml#id(Bmr012.w.2859)..id(Bmr012.w.2868)"/>
   </segment>
   <segment nite:id="Bmr012.segment.395" starttime="577.073" endtime="580.543" participant="fe016" timing-provenance="dialogueact">
      <nite:child href="Bmr012.C.words.xml#id(Bmr012.w.2881)..id(Bmr012.w.2897)"/>
   </segment>
   <segment nite:id="Bmr012.segment.396" starttime="581.053" endtime="584.973" participant="fe016" timing-provenance="dialogueact">
      <nite:child href="Bmr012.C.words.xml#id(Bmr012.w.2898)..id(Bmr012.w.2912)"/>
   </segment>
   <segment nite:id="Bmr012.segment.397" starttime="585.313" endtime="587.403" participant="fe016" timing-provenance="dialogueact">
      <nite:child href="Bmr012.C.words.xml#id(Bmr012.w.2913)..id(Bmr012.w.2920)"/>
   </segment>
   <segment nite:id="Bmr012.segment.398" starttime="587.653" endtime="588.753" participant="fe016" timing-provenance="dialogueact">
      <nite:child href="Bmr012.C.words.xml#id(Bmr012.w.2921)..id(Bmr012.w.2923)"/>
   </segment>
   <segment nite:id="Bmr012.segment.399" starttime="589.603" endtime="593.403" participant="fe016" timing-provenance="dialogueact">
      <nite:child href="Bmr012.C.words.xml#id(Bmr012.w.2924)..id(Bmr012.w.2935)"/>
   </segment>
   <segment nite:id="Bmr012.segment.400" starttime="593.713" endtime="596.193" participant="fe016" timing-provenance="dialogueact">
      <nite:child href="Bmr012.C.words.xml#id(Bmr012.w.2936)..id(Bmr012.w.2952)"/>
   </segment>
   <segment nite:id="Bmr012.segment.401" starttime="596.57" endtime="599.085" participant="fe016" timing-provenance="segment">
      <nite:child href="Bmr012.C.words.xml#id(Bmr012.w.2953)..id(Bmr012.disfmarker.126)"/>
   </segment>
   <segment nite:id="Bmr012.segment.406" starttime="606.168" endtime="606.528" participant="fe016" timing-provenance="dialogueact">
      <nite:child href="Bmr012.C.words.xml#id(Bmr012.w.2990)..id(Bmr012.w.2991)"/>
   </segment>
   <segment nite:id="Bmr012.segment.410" starttime="608.491" endtime="608.701" participant="fe016" timing-provenance="dialogueact">
      <nite:child href="Bmr012.C.words.xml#id(Bmr012.w.3017)..id(Bmr012.w.3018)"/>
   </segment>
   <segment nite:id="Bmr012.segment.411" starttime="609.411" endtime="613.601" participant="fe016" timing-provenance="dialogueact">
      <nite:child href="Bmr012.C.words.xml#id(Bmr012.w.3019)..id(Bmr012.w.3028)"/>
   </segment>
   <segment nite:id="Bmr012.segment.414" starttime="613.971" endtime="614.601" participant="fe016" timing-provenance="dialogueact">
      <nite:child href="Bmr012.C.words.xml#id(Bmr012.w.3041)..id(Bmr012.w.3043)"/>
   </segment>
   <segment nite:id="Bmr012.segment.417" starttime="615.121" endtime="621.911" participant="fe016" timing-provenance="dialogueact">
      <nite:child href="Bmr012.C.words.xml#id(Bmr012.w.3060)..id(Bmr012.w.3089)"/>
   </segment>
   <segment nite:id="Bmr012.segment.420" starttime="622.461" endtime="623.971" participant="fe016" timing-provenance="dialogueact">
      <nite:child href="Bmr012.C.words.xml#id(Bmr012.w.3094)..id(Bmr012.w.3102)"/>
   </segment>
   <segment nite:id="Bmr012.segment.421" starttime="624.541" endtime="631.131" participant="fe016" timing-provenance="dialogueact">
      <nite:child href="Bmr012.C.words.xml#id(Bmr012.w.3103)..id(Bmr012.w.3133)"/>
   </segment>
   <segment nite:id="Bmr012.segment.424" starttime="632.343" endtime="632.683" participant="fe016" timing-provenance="dialogueact">
      <nite:child href="Bmr012.C.words.xml#id(Bmr012.w.3150)..id(Bmr012.w.3151)"/>
   </segment>
   <segment nite:id="Bmr012.segment.427" starttime="635.641" endtime="637.641" participant="fe016" timing-provenance="dialogueact">
      <nite:child href="Bmr012.C.words.xml#id(Bmr012.w.3162)..id(Bmr012.w.3169)"/>
   </segment>
   <segment nite:id="Bmr012.segment.430" starttime="640.862" endtime="642.282" participant="fe016" timing-provenance="dialogueact">
      <nite:child href="Bmr012.C.words.xml#id(Bmr012.w.3197)..id(Bmr012.w.3205)"/>
   </segment>
   <segment nite:id="Bmr012.segment.437" starttime="651.889" endtime="651.969" participant="fe016" timing-provenance="dialogueact">
      <nite:child href="Bmr012.C.words.xml#id(Bmr012.w.3248)..id(Bmr012.w.3249)"/>
   </segment>
   <segment nite:id="Bmr012.segment.439" starttime="652.729" endtime="656.839" participant="fe016" timing-provenance="dialogueact">
      <nite:child href="Bmr012.C.words.xml#id(Bmr012.w.3254)..id(Bmr012.w.3267)"/>
   </segment>
   <segment nite:id="Bmr012.segment.452" starttime="669.951" endtime="671.211" participant="fe016" timing-provenance="segment">
      <nite:child href="Bmr012.C.words.xml#id(Bmr012.vocalsound.84)"/>
   </segment>
   <segment nite:id="Bmr012.segment.453" starttime="671.211" endtime="673.982" participant="fe016" timing-provenance="segment">
      <nite:child href="Bmr012.C.words.xml#id(Bmr012.w.3348)..id(Bmr012.vocalsound.85)"/>
   </segment>
   <segment nite:id="Bmr012.segment.460" starttime="674.362" endtime="674.592" participant="fe016" timing-provenance="dialogueact">
      <nite:child href="Bmr012.C.words.xml#id(Bmr012.w.3367)"/>
   </segment>
   <segment nite:id="Bmr012.segment.461" starttime="675.022" endtime="679.842" participant="fe016" timing-provenance="dialogueact">
      <nite:child href="Bmr012.C.words.xml#id(Bmr012.w.3368)..id(Bmr012.w.3381)"/>
   </segment>
   <segment nite:id="Bmr012.segment.464" starttime="680.562" endtime="684.372" participant="fe016" timing-provenance="dialogueact">
      <nite:child href="Bmr012.C.words.xml#id(Bmr012.w.3382)..id(Bmr012.w.3396)"/>
   </segment>
   <segment nite:id="Bmr012.segment.466" starttime="684.562" endtime="687.382" participant="fe016" timing-provenance="dialogueact">
      <nite:child href="Bmr012.C.words.xml#id(Bmr012.w.3397)..id(Bmr012.w.3406)"/>
   </segment>
   <segment nite:id="Bmr012.segment.467" starttime="687.742" endtime="692.532" participant="fe016" timing-provenance="dialogueact">
      <nite:child href="Bmr012.C.words.xml#id(Bmr012.w.3407)..id(Bmr012.w.3429)"/>
   </segment>
   <segment nite:id="Bmr012.segment.468" starttime="692.952" endtime="693.992" participant="fe016" timing-provenance="dialogueact">
      <nite:child href="Bmr012.C.words.xml#id(Bmr012.w.3430)..id(Bmr012.w.3433)"/>
   </segment>
   <segment nite:id="Bmr012.segment.472" starttime="694.655" endtime="698.894" participant="fe016" timing-provenance="segment">
      <nite:child href="Bmr012.C.words.xml#id(Bmr012.w.3447)..id(Bmr012.disfmarker.142)"/>
   </segment>
   <segment nite:id="Bmr012.segment.475" starttime="698.972" endtime="701.812" participant="fe016" timing-provenance="dialogueact">
      <nite:child href="Bmr012.C.words.xml#id(Bmr012.w.3497)..id(Bmr012.w.3507)"/>
   </segment>
   <segment nite:id="Bmr012.segment.477" starttime="706.856" endtime="710.566" participant="fe016" timing-provenance="dialogueact">
      <nite:child href="Bmr012.C.words.xml#id(Bmr012.w.3510)..id(Bmr012.w.3532)"/>
   </segment>
   <segment nite:id="Bmr012.segment.481" starttime="711.266" endtime="712.006" participant="fe016" timing-provenance="dialogueact">
      <nite:child href="Bmr012.C.words.xml#id(Bmr012.w.3542)..id(Bmr012.w.3545)"/>
   </segment>
   <segment nite:id="Bmr012.segment.483" starttime="712.356" endtime="713.036" participant="fe016" timing-provenance="dialogueact">
      <nite:child href="Bmr012.C.words.xml#id(Bmr012.w.3552)..id(Bmr012.w.3554)"/>
   </segment>
   <segment nite:id="Bmr012.segment.485" starttime="713.696" endtime="714.916" participant="fe016" timing-provenance="dialogueact">
      <nite:child href="Bmr012.C.words.xml#id(Bmr012.w.3557)..id(Bmr012.w.3559)"/>
   </segment>
   <segment nite:id="Bmr012.segment.487" starttime="715.366" endtime="716.796" participant="fe016" timing-provenance="dialogueact">
      <nite:child href="Bmr012.C.words.xml#id(Bmr012.w.3564)..id(Bmr012.w.3571)"/>
   </segment>
   <segment nite:id="Bmr012.segment.488" starttime="717.166" endtime="718.676" participant="fe016" timing-provenance="dialogueact">
      <nite:child href="Bmr012.C.words.xml#id(Bmr012.w.3572)..id(Bmr012.w.3577)"/>
   </segment>
   <segment nite:id="Bmr012.segment.489" starttime="719.136" endtime="722.876" participant="fe016" timing-provenance="dialogueact">
      <nite:child href="Bmr012.C.words.xml#id(Bmr012.w.3578)..id(Bmr012.w.3595)"/>
   </segment>
   <segment nite:id="Bmr012.segment.490" starttime="722.876" endtime="725.916" participant="fe016" timing-provenance="dialogueact">
      <nite:child href="Bmr012.C.words.xml#id(Bmr012.w.3596)..id(Bmr012.w.3607)"/>
   </segment>
   <segment nite:id="Bmr012.segment.491" starttime="726.436" endtime="732.506" participant="fe016" timing-provenance="dialogueact">
      <nite:child href="Bmr012.C.words.xml#id(Bmr012.w.3608)..id(Bmr012.w.3630)"/>
   </segment>
   <segment nite:id="Bmr012.segment.493" starttime="733.016" endtime="733.886" participant="fe016" timing-provenance="dialogueact">
      <nite:child href="Bmr012.C.words.xml#id(Bmr012.w.3645)..id(Bmr012.w.3648)"/>
   </segment>
   <segment nite:id="Bmr012.segment.496" starttime="743.468" endtime="743.798" participant="fe016" timing-provenance="dialogueact">
      <nite:child href="Bmr012.C.words.xml#id(Bmr012.w.3666)..id(Bmr012.w.3667)"/>
   </segment>
   <segment nite:id="Bmr012.segment.499" starttime="744.738" endtime="747.068" participant="fe016" timing-provenance="dialogueact">
      <nite:child href="Bmr012.C.words.xml#id(Bmr012.w.3673)..id(Bmr012.w.3679)"/>
   </segment>
   <segment nite:id="Bmr012.segment.500" starttime="748.068" endtime="749.198" participant="fe016" timing-provenance="dialogueact">
      <nite:child href="Bmr012.C.words.xml#id(Bmr012.w.3680)..id(Bmr012.w.3683)"/>
   </segment>
   <segment nite:id="Bmr012.segment.502" starttime="752.803" endtime="753.103" participant="fe016" timing-provenance="dialogueact">
      <nite:child href="Bmr012.C.words.xml#id(Bmr012.w.3699)..id(Bmr012.w.3700)"/>
   </segment>
   <segment nite:id="Bmr012.segment.504" starttime="753.763" endtime="755.313" participant="fe016" timing-provenance="dialogueact">
      <nite:child href="Bmr012.C.words.xml#id(Bmr012.w.3704)..id(Bmr012.w.3708)"/>
   </segment>
   <segment nite:id="Bmr012.segment.506" starttime="755.863" endtime="756.283" participant="fe016" timing-provenance="dialogueact">
      <nite:child href="Bmr012.C.words.xml#id(Bmr012.w.3717)..id(Bmr012.w.3718)"/>
   </segment>
   <segment nite:id="Bmr012.segment.508" starttime="758.163" endtime="759.733" participant="fe016" timing-provenance="dialogueact">
      <nite:child href="Bmr012.C.words.xml#id(Bmr012.w.3732)..id(Bmr012.w.3738)"/>
   </segment>
   <segment nite:id="Bmr012.segment.509" starttime="760.053" endtime="766.743" participant="fe016" timing-provenance="dialogueact">
      <nite:child href="Bmr012.C.words.xml#id(Bmr012.w.3739)..id(Bmr012.w.3771)"/>
   </segment>
   <segment nite:id="Bmr012.segment.512" starttime="766.993" endtime="768.543" participant="fe016" timing-provenance="dialogueact">
      <nite:child href="Bmr012.C.words.xml#id(Bmr012.w.3772)..id(Bmr012.w.3775)"/>
   </segment>
   <segment nite:id="Bmr012.segment.513" starttime="769.023" endtime="770.993" participant="fe016" timing-provenance="dialogueact">
      <nite:child href="Bmr012.C.words.xml#id(Bmr012.w.3776)..id(Bmr012.w.3785)"/>
   </segment>
   <segment nite:id="Bmr012.segment.514" starttime="771.653" endtime="775.663" participant="fe016" timing-provenance="dialogueact">
      <nite:child href="Bmr012.C.words.xml#id(Bmr012.w.3786)..id(Bmr012.w.3803)"/>
   </segment>
   <segment nite:id="Bmr012.segment.515" starttime="775.964" endtime="779.864" participant="fe016" timing-provenance="segment">
      <nite:child href="Bmr012.C.words.xml#id(Bmr012.w.3804)..id(Bmr012.disfmarker.158)"/>
   </segment>
   <segment nite:id="Bmr012.segment.516" starttime="780.483" endtime="789.373" participant="fe016" timing-provenance="dialogueact">
      <nite:child href="Bmr012.C.words.xml#id(Bmr012.w.3817)..id(Bmr012.w.3857)"/>
   </segment>
   <segment nite:id="Bmr012.segment.517" starttime="790.013" endtime="797.483" participant="fe016" timing-provenance="dialogueact">
      <nite:child href="Bmr012.C.words.xml#id(Bmr012.w.3858)..id(Bmr012.w.3877)"/>
   </segment>
   <segment nite:id="Bmr012.segment.518" starttime="798.513" endtime="800.213" participant="fe016" timing-provenance="dialogueact">
      <nite:child href="Bmr012.C.words.xml#id(Bmr012.w.3878)..id(Bmr012.w.3884)"/>
   </segment>
   <segment nite:id="Bmr012.segment.520" starttime="800.923" endtime="803.283" participant="fe016" timing-provenance="dialogueact">
      <nite:child href="Bmr012.C.words.xml#id(Bmr012.w.3885)..id(Bmr012.w.3892)"/>
   </segment>
   <segment nite:id="Bmr012.segment.521" starttime="803.573" endtime="808.933" participant="fe016" timing-provenance="dialogueact">
      <nite:child href="Bmr012.C.words.xml#id(Bmr012.w.3893)..id(Bmr012.w.3916)"/>
   </segment>
   <segment nite:id="Bmr012.segment.523" starttime="809.453" endtime="811.383" participant="fe016" timing-provenance="dialogueact">
      <nite:child href="Bmr012.C.words.xml#id(Bmr012.w.3917)..id(Bmr012.w.3927)"/>
   </segment>
   <segment nite:id="Bmr012.segment.526" starttime="813.648" endtime="814.798" participant="fe016" timing-provenance="dialogueact">
      <nite:child href="Bmr012.C.words.xml#id(Bmr012.w.3940)..id(Bmr012.w.3943)"/>
   </segment>
   <segment nite:id="Bmr012.segment.528" starttime="816.993" endtime="817.763" participant="fe016" timing-provenance="dialogueact">
      <nite:child href="Bmr012.C.words.xml#id(Bmr012.w.3967)..id(Bmr012.w.3970)"/>
   </segment>
   <segment nite:id="Bmr012.segment.529" starttime="818.423" endtime="818.863" participant="fe016" timing-provenance="dialogueact">
      <nite:child href="Bmr012.C.words.xml#id(Bmr012.w.3971)..id(Bmr012.w.3972)"/>
   </segment>
   <segment nite:id="Bmr012.segment.530" starttime="819.273" endtime="821.423" participant="fe016" timing-provenance="dialogueact">
      <nite:child href="Bmr012.C.words.xml#id(Bmr012.w.3973)..id(Bmr012.w.3982)"/>
   </segment>
   <segment nite:id="Bmr012.segment.531" starttime="822.013" endtime="826.983" participant="fe016" timing-provenance="dialogueact">
      <nite:child href="Bmr012.C.words.xml#id(Bmr012.w.3983)..id(Bmr012.w.3999)"/>
   </segment>
   <segment nite:id="Bmr012.segment.532" starttime="827.284" endtime="832.4" participant="fe016" timing-provenance="segment">
      <nite:child href="Bmr012.C.words.xml#id(Bmr012.w.4000)..id(Bmr012.disfmarker.161)"/>
   </segment>
   <segment nite:id="Bmr012.segment.536" starttime="838.062" endtime="842.722" participant="fe016" timing-provenance="dialogueact">
      <nite:child href="Bmr012.C.words.xml#id(Bmr012.w.4040)..id(Bmr012.w.4055)"/>
   </segment>
   <segment nite:id="Bmr012.segment.537" starttime="843.292" endtime="843.672" participant="fe016" timing-provenance="dialogueact">
      <nite:child href="Bmr012.C.words.xml#id(Bmr012.w.4056)"/>
   </segment>
   <segment nite:id="Bmr012.segment.538" starttime="844.432" endtime="846.912" participant="fe016" timing-provenance="dialogueact">
      <nite:child href="Bmr012.C.words.xml#id(Bmr012.w.4057)..id(Bmr012.w.4070)"/>
   </segment>
   <segment nite:id="Bmr012.segment.540" starttime="847.512" endtime="851.862" participant="fe016" timing-provenance="dialogueact">
      <nite:child href="Bmr012.C.words.xml#id(Bmr012.w.4073)..id(Bmr012.w.4093)"/>
   </segment>
   <segment nite:id="Bmr012.segment.542" starttime="851.952" endtime="856.532" participant="fe016" timing-provenance="dialogueact">
      <nite:child href="Bmr012.C.words.xml#id(Bmr012.w.4098)..id(Bmr012.w.4118)"/>
   </segment>
   <segment nite:id="Bmr012.segment.543" starttime="856.952" endtime="859.352" participant="fe016" timing-provenance="dialogueact">
      <nite:child href="Bmr012.C.words.xml#id(Bmr012.w.4119)..id(Bmr012.w.4126)"/>
   </segment>
   <segment nite:id="Bmr012.segment.544" starttime="859.842" endtime="860.892" participant="fe016" timing-provenance="dialogueact">
      <nite:child href="Bmr012.C.words.xml#id(Bmr012.w.4127)..id(Bmr012.w.4133)"/>
   </segment>
   <segment nite:id="Bmr012.segment.545" starttime="861.182" endtime="861.552" participant="fe016" timing-provenance="dialogueact">
      <nite:child href="Bmr012.C.words.xml#id(Bmr012.w.4134)"/>
   </segment>
   <segment nite:id="Bmr012.segment.546" starttime="862.342" endtime="862.892" participant="fe016" timing-provenance="dialogueact">
      <nite:child href="Bmr012.C.words.xml#id(Bmr012.w.4135)..id(Bmr012.w.4139)"/>
   </segment>
   <segment nite:id="Bmr012.segment.554" starttime="868.47" endtime="871.709" participant="fe016" timing-provenance="segment">
      <nite:child href="Bmr012.C.words.xml#id(Bmr012.vocalsound.98)"/>
   </segment>
   <segment nite:id="Bmr012.segment.562" starttime="880.042" endtime="882.242" participant="fe016" timing-provenance="dialogueact">
      <nite:child href="Bmr012.C.words.xml#id(Bmr012.w.4271)..id(Bmr012.w.4280)"/>
   </segment>
   <segment nite:id="Bmr012.segment.570" starttime="902.58" endtime="902.92" participant="fe016" timing-provenance="dialogueact">
      <nite:child href="Bmr012.C.words.xml#id(Bmr012.w.4375)..id(Bmr012.w.4376)"/>
   </segment>
   <segment nite:id="Bmr012.segment.574" starttime="917.48" endtime="930.83" participant="fe016" timing-provenance="dialogueact">
      <nite:child href="Bmr012.C.words.xml#id(Bmr012.w.4443)..id(Bmr012.w.4496)"/>
   </segment>
   <segment nite:id="Bmr012.segment.576" starttime="931.53" endtime="933.9" participant="fe016" timing-provenance="dialogueact">
      <nite:child href="Bmr012.C.words.xml#id(Bmr012.w.4498)..id(Bmr012.w.4508)"/>
   </segment>
   <segment nite:id="Bmr012.segment.577" starttime="934.49" endtime="936.82" participant="fe016" timing-provenance="dialogueact">
      <nite:child href="Bmr012.C.words.xml#id(Bmr012.w.4509)..id(Bmr012.w.4515)"/>
   </segment>
   <segment nite:id="Bmr012.segment.578" starttime="937.17" endtime="939.66" participant="fe016" timing-provenance="dialogueact">
      <nite:child href="Bmr012.C.words.xml#id(Bmr012.w.4516)..id(Bmr012.w.4529)"/>
   </segment>
   <segment nite:id="Bmr012.segment.579" starttime="940.02" endtime="941.06" participant="fe016" timing-provenance="dialogueact">
      <nite:child href="Bmr012.C.words.xml#id(Bmr012.w.4530)..id(Bmr012.w.4533)"/>
   </segment>
   <segment nite:id="Bmr012.segment.580" starttime="941.65" endtime="945.83" participant="fe016" timing-provenance="dialogueact">
      <nite:child href="Bmr012.C.words.xml#id(Bmr012.w.4534)..id(Bmr012.w.4551)"/>
   </segment>
   <segment nite:id="Bmr012.segment.581" starttime="946.45" endtime="947.11" participant="fe016" timing-provenance="dialogueact">
      <nite:child href="Bmr012.C.words.xml#id(Bmr012.w.4552)..id(Bmr012.w.4556)"/>
   </segment>
   <segment nite:id="Bmr012.segment.582" starttime="947.8" endtime="948.28" participant="fe016" timing-provenance="dialogueact">
      <nite:child href="Bmr012.C.words.xml#id(Bmr012.w.4557)..id(Bmr012.w.4558)"/>
   </segment>
   <segment nite:id="Bmr012.segment.583" starttime="948.68" endtime="950.289" participant="fe016" timing-provenance="segment">
      <nite:child href="Bmr012.C.words.xml#id(Bmr012.w.4559)..id(Bmr012.disfmarker.173)"/>
   </segment>
   <segment nite:id="Bmr012.segment.584" starttime="951.066" endtime="953.246" participant="fe016" timing-provenance="dialogueact">
      <nite:child href="Bmr012.C.words.xml#id(Bmr012.w.4570)..id(Bmr012.w.4575)"/>
   </segment>
   <segment nite:id="Bmr012.segment.585" starttime="954.403" endtime="955.447" participant="fe016" timing-provenance="segment">
      <nite:child href="Bmr012.C.words.xml#id(Bmr012.vocalsound.100)"/>
   </segment>
   <segment nite:id="Bmr012.segment.586" starttime="956.086" endtime="958.54" participant="fe016" timing-provenance="segment">
      <nite:child href="Bmr012.C.words.xml#id(Bmr012.w.4576)..id(Bmr012.vocalsound.101)"/>
   </segment>
   <segment nite:id="Bmr012.segment.587" starttime="959.994" endtime="971.774" participant="fe016" timing-provenance="dialogueact">
      <nite:child href="Bmr012.C.words.xml#id(Bmr012.w.4580)..id(Bmr012.w.4619)"/>
   </segment>
   <segment nite:id="Bmr012.segment.592" starttime="972.324" endtime="976.324" participant="fe016" timing-provenance="dialogueact">
      <nite:child href="Bmr012.C.words.xml#id(Bmr012.w.4634)..id(Bmr012.w.4647)"/>
   </segment>
   <segment nite:id="Bmr012.segment.593" starttime="977.184" endtime="977.564" participant="fe016" timing-provenance="dialogueact">
      <nite:child href="Bmr012.C.words.xml#id(Bmr012.w.4648)"/>
   </segment>
   <segment nite:id="Bmr012.segment.616" starttime="1025.56" endtime="1027.0" participant="fe016" timing-provenance="dialogueact">
      <nite:child href="Bmr012.C.words.xml#id(Bmr012.w.4797)..id(Bmr012.w.4801)"/>
   </segment>
   <segment nite:id="Bmr012.segment.621" starttime="1032.85" endtime="1036.74" participant="fe016" timing-provenance="dialogueact">
      <nite:child href="Bmr012.C.words.xml#id(Bmr012.w.4830)..id(Bmr012.w.4840)"/>
   </segment>
   <segment nite:id="Bmr012.segment.622" starttime="1037.57" endtime="1038.97" participant="fe016" timing-provenance="dialogueact">
      <nite:child href="Bmr012.C.words.xml#id(Bmr012.w.4841)..id(Bmr012.w.4844)"/>
   </segment>
   <segment nite:id="Bmr012.segment.624" starttime="1038.97" endtime="1040.64" participant="fe016" timing-provenance="dialogueact">
      <nite:child href="Bmr012.C.words.xml#id(Bmr012.w.4866)..id(Bmr012.w.4870)"/>
   </segment>
   <segment nite:id="Bmr012.segment.627" starttime="1042.59" endtime="1051.27" participant="fe016" timing-provenance="dialogueact">
      <nite:child href="Bmr012.C.words.xml#id(Bmr012.w.4880)..id(Bmr012.w.4914)"/>
   </segment>
   <segment nite:id="Bmr012.segment.631" starttime="1052.75" endtime="1053.41" participant="fe016" timing-provenance="dialogueact">
      <nite:child href="Bmr012.C.words.xml#id(Bmr012.w.4941)..id(Bmr012.w.4943)"/>
   </segment>
   <segment nite:id="Bmr012.segment.633" starttime="1054.89" endtime="1055.52" participant="fe016" timing-provenance="dialogueact">
      <nite:child href="Bmr012.C.words.xml#id(Bmr012.w.4976)..id(Bmr012.w.4978)"/>
   </segment>
   <segment nite:id="Bmr012.segment.638" starttime="1078.16" endtime="1078.82" participant="fe016" timing-provenance="dialogueact">
      <nite:child href="Bmr012.C.words.xml#id(Bmr012.w.5086)..id(Bmr012.w.5089)"/>
   </segment>
   <segment nite:id="Bmr012.segment.648" starttime="1106.5" endtime="1109.6" participant="fe016" timing-provenance="dialogueact">
      <nite:child href="Bmr012.C.words.xml#id(Bmr012.w.5193)..id(Bmr012.w.5203)"/>
   </segment>
   <segment nite:id="Bmr012.segment.651" starttime="1114.37" endtime="1115.04" participant="fe016" timing-provenance="dialogueact">
      <nite:child href="Bmr012.C.words.xml#id(Bmr012.w.5245)..id(Bmr012.w.5248)"/>
   </segment>
   <segment nite:id="Bmr012.segment.672" starttime="1157.32" endtime="1159.02" participant="fe016" timing-provenance="dialogueact">
      <nite:child href="Bmr012.C.words.xml#id(Bmr012.w.5393)..id(Bmr012.w.5398)"/>
   </segment>
   <segment nite:id="Bmr012.segment.677" starttime="1162.28" endtime="1163.18" participant="fe016" timing-provenance="dialogueact">
      <nite:child href="Bmr012.C.words.xml#id(Bmr012.w.5419)..id(Bmr012.w.5423)"/>
   </segment>
   <segment nite:id="Bmr012.segment.680" starttime="1163.701" endtime="1167.7" participant="fe016" timing-provenance="segment">
      <nite:child href="Bmr012.C.words.xml#id(Bmr012.w.5436)..id(Bmr012.comment.13)"/>
   </segment>
   <segment nite:id="Bmr012.segment.683" starttime="1173.04" endtime="1174.92" participant="fe016" timing-provenance="dialogueact">
      <nite:child href="Bmr012.C.words.xml#id(Bmr012.w.5485)..id(Bmr012.w.5493)"/>
   </segment>
   <segment nite:id="Bmr012.segment.686" starttime="1175.77" endtime="1176.33" participant="fe016" timing-provenance="dialogueact">
      <nite:child href="Bmr012.C.words.xml#id(Bmr012.w.5521)"/>
   </segment>
   <segment nite:id="Bmr012.segment.687" starttime="1177.48" endtime="1177.71" participant="fe016" timing-provenance="dialogueact">
      <nite:child href="Bmr012.C.words.xml#id(Bmr012.w.5522)..id(Bmr012.w.5523)"/>
   </segment>
   <segment nite:id="Bmr012.segment.690" starttime="1183.07" endtime="1185.71" participant="fe016" timing-provenance="dialogueact">
      <nite:child href="Bmr012.C.words.xml#id(Bmr012.w.5536)..id(Bmr012.w.5549)"/>
   </segment>
   <segment nite:id="Bmr012.segment.693" starttime="1186.46" endtime="1186.84" participant="fe016" timing-provenance="dialogueact">
      <nite:child href="Bmr012.C.words.xml#id(Bmr012.w.5568)"/>
   </segment>
   <segment nite:id="Bmr012.segment.697" starttime="1191.84" endtime="1195.38" participant="fe016" timing-provenance="dialogueact">
      <nite:child href="Bmr012.C.words.xml#id(Bmr012.w.5586)..id(Bmr012.w.5602)"/>
   </segment>
   <segment nite:id="Bmr012.segment.702" starttime="1196.87" endtime="1197.34" participant="fe016" timing-provenance="segment">
      <nite:child href="Bmr012.C.words.xml#id(Bmr012.vocalsound.112)"/>
   </segment>
   <segment nite:id="Bmr012.segment.704" starttime="1197.34" endtime="1202.031" participant="fe016" timing-provenance="segment">
      <nite:child href="Bmr012.C.words.xml#id(Bmr012.w.5617)..id(Bmr012.disfmarker.220)"/>
   </segment>
   <segment nite:id="Bmr012.segment.707" starttime="1204.02" endtime="1204.3" participant="fe016" timing-provenance="dialogueact">
      <nite:child href="Bmr012.C.words.xml#id(Bmr012.w.5681)..id(Bmr012.w.5682)"/>
   </segment>
   <segment nite:id="Bmr012.segment.708" starttime="1205.3" endtime="1206.03" participant="fe016" timing-provenance="dialogueact">
      <nite:child href="Bmr012.C.words.xml#id(Bmr012.w.5683)..id(Bmr012.w.5687)"/>
   </segment>
   <segment nite:id="Bmr012.segment.718" starttime="1220.01" endtime="1223.17" participant="fe016" timing-provenance="segment">
      <nite:child href="Bmr012.C.words.xml#id(Bmr012.w.5737)..id(Bmr012.disfmarker.228)"/>
   </segment>
   <segment nite:id="Bmr012.segment.727" starttime="1237.2" endtime="1242.38" participant="fe016" timing-provenance="dialogueact">
      <nite:child href="Bmr012.C.words.xml#id(Bmr012.w.5826)..id(Bmr012.w.5847)"/>
   </segment>
   <segment nite:id="Bmr012.segment.737" starttime="1265.27" endtime="1272.31" participant="fe016" timing-provenance="dialogueact">
      <nite:child href="Bmr012.C.words.xml#id(Bmr012.w.5934)..id(Bmr012.w.5960)"/>
   </segment>
   <segment nite:id="Bmr012.segment.746" starttime="1282.61" endtime="1284.78" participant="fe016" timing-provenance="dialogueact">
      <nite:child href="Bmr012.C.words.xml#id(Bmr012.w.5985)..id(Bmr012.w.5992)"/>
   </segment>
   <segment nite:id="Bmr012.segment.750" starttime="1285.73" endtime="1286.46" participant="fe016" timing-provenance="dialogueact">
      <nite:child href="Bmr012.C.words.xml#id(Bmr012.w.6024)"/>
   </segment>
   <segment nite:id="Bmr012.segment.758" starttime="1303.19" endtime="1311.15" participant="fe016" timing-provenance="dialogueact">
      <nite:child href="Bmr012.C.words.xml#id(Bmr012.w.6084)..id(Bmr012.w.6118)"/>
   </segment>
   <segment nite:id="Bmr012.segment.761" starttime="1312.216" endtime="1315.225" participant="fe016" timing-provenance="segment">
      <nite:child href="Bmr012.C.words.xml#id(Bmr012.vocalsound.124)"/>
   </segment>
   <segment nite:id="Bmr012.segment.767" starttime="1323.25" endtime="1323.56" participant="fe016" timing-provenance="dialogueact">
      <nite:child href="Bmr012.C.words.xml#id(Bmr012.w.6226)..id(Bmr012.w.6227)"/>
   </segment>
   <segment nite:id="Bmr012.segment.771" starttime="1328.19" endtime="1328.42" participant="fe016" timing-provenance="dialogueact">
      <nite:child href="Bmr012.C.words.xml#id(Bmr012.w.6234)..id(Bmr012.w.6235)"/>
   </segment>
   <segment nite:id="Bmr012.segment.772" starttime="1329.27" endtime="1329.61" participant="fe016" timing-provenance="dialogueact">
      <nite:child href="Bmr012.C.words.xml#id(Bmr012.w.6236)..id(Bmr012.w.6237)"/>
   </segment>
   <segment nite:id="Bmr012.segment.775" starttime="1332.14" endtime="1338.18" participant="fe016" timing-provenance="segment">
      <nite:child href="Bmr012.C.words.xml#id(Bmr012.w.6242)..id(Bmr012.disfmarker.246)"/>
   </segment>
   <segment nite:id="Bmr012.segment.776" starttime="1338.99" endtime="1341.06" participant="fe016" timing-provenance="dialogueact">
      <nite:child href="Bmr012.C.words.xml#id(Bmr012.w.6266)..id(Bmr012.w.6273)"/>
   </segment>
   <segment nite:id="Bmr012.segment.794" starttime="1360.11" endtime="1366.47" participant="fe016" timing-provenance="dialogueact">
      <nite:child href="Bmr012.C.words.xml#id(Bmr012.w.6376)..id(Bmr012.w.6402)"/>
   </segment>
   <segment nite:id="Bmr012.segment.800" starttime="1367.6" endtime="1367.94" participant="fe016" timing-provenance="dialogueact">
      <nite:child href="Bmr012.C.words.xml#id(Bmr012.w.6439)..id(Bmr012.w.6440)"/>
   </segment>
   <segment nite:id="Bmr012.segment.803" starttime="1368.96" endtime="1370.99" participant="fe016" timing-provenance="dialogueact">
      <nite:child href="Bmr012.C.words.xml#id(Bmr012.w.6443)..id(Bmr012.w.6451)"/>
   </segment>
   <segment nite:id="Bmr012.segment.825" starttime="1394.42" endtime="1397.46" participant="fe016" timing-provenance="segment">
      <nite:child href="Bmr012.C.words.xml#id(Bmr012.w.6582)..id(Bmr012.disfmarker.261)"/>
   </segment>
   <segment nite:id="Bmr012.segment.826" starttime="1398.11" endtime="1401.57" participant="fe016" timing-provenance="dialogueact">
      <nite:child href="Bmr012.C.words.xml#id(Bmr012.w.6590)..id(Bmr012.w.6602)"/>
   </segment>
   <segment nite:id="Bmr012.segment.827" starttime="1402.87" endtime="1404.83" participant="fe016" timing-provenance="dialogueact">
      <nite:child href="Bmr012.C.words.xml#id(Bmr012.w.6603)..id(Bmr012.w.6612)"/>
   </segment>
   <segment nite:id="Bmr012.segment.830" starttime="1406.16" endtime="1407.62" participant="fe016" timing-provenance="dialogueact">
      <nite:child href="Bmr012.C.words.xml#id(Bmr012.w.6621)..id(Bmr012.w.6630)"/>
   </segment>
   <segment nite:id="Bmr012.segment.834" starttime="1415.39" endtime="1417.86" participant="fe016" timing-provenance="segment">
      <nite:child href="Bmr012.C.words.xml#id(Bmr012.w.6687)..id(Bmr012.vocalsound.132)"/>
   </segment>
   <segment nite:id="Bmr012.segment.837" starttime="1418.73" endtime="1419.01" participant="fe016" timing-provenance="dialogueact">
      <nite:child href="Bmr012.C.words.xml#id(Bmr012.w.6713)..id(Bmr012.w.6714)"/>
   </segment>
   <segment nite:id="Bmr012.segment.838" starttime="1420.72" endtime="1420.95" participant="fe016" timing-provenance="dialogueact">
      <nite:child href="Bmr012.C.words.xml#id(Bmr012.w.6715)..id(Bmr012.w.6716)"/>
   </segment>
   <segment nite:id="Bmr012.segment.841" starttime="1422.95" endtime="1427.67" participant="fe016" timing-provenance="dialogueact">
      <nite:child href="Bmr012.C.words.xml#id(Bmr012.w.6722)..id(Bmr012.w.6743)"/>
   </segment>
   <segment nite:id="Bmr012.segment.842" starttime="1428.38" endtime="1429.07" participant="fe016" timing-provenance="segment">
      <nite:child href="Bmr012.C.words.xml#id(Bmr012.w.6744)..id(Bmr012.disfmarker.268)"/>
   </segment>
   <segment nite:id="Bmr012.segment.843" starttime="1429.84" endtime="1432.53" participant="fe016" timing-provenance="dialogueact">
      <nite:child href="Bmr012.C.words.xml#id(Bmr012.w.6745)..id(Bmr012.w.6755)"/>
   </segment>
   <segment nite:id="Bmr012.segment.844" starttime="1432.99" endtime="1440.51" participant="fe016" timing-provenance="dialogueact">
      <nite:child href="Bmr012.C.words.xml#id(Bmr012.w.6756)..id(Bmr012.w.6785)"/>
   </segment>
   <segment nite:id="Bmr012.segment.845" starttime="1441.22" endtime="1445.77" participant="fe016" timing-provenance="dialogueact">
      <nite:child href="Bmr012.C.words.xml#id(Bmr012.w.6786)..id(Bmr012.w.6797)"/>
   </segment>
   <segment nite:id="Bmr012.segment.849" starttime="1446.81" endtime="1457.53" participant="fe016" timing-provenance="segment">
      <nite:child href="Bmr012.C.words.xml#id(Bmr012.vocalsound.135)..id(Bmr012.w.6840)"/>
   </segment>
   <segment nite:id="Bmr012.segment.853" starttime="1457.99" endtime="1462.56" participant="fe016" timing-provenance="dialogueact">
      <nite:child href="Bmr012.C.words.xml#id(Bmr012.w.6844)..id(Bmr012.w.6862)"/>
   </segment>
   <segment nite:id="Bmr012.segment.854" starttime="1463.23" endtime="1466.71" participant="fe016" timing-provenance="dialogueact">
      <nite:child href="Bmr012.C.words.xml#id(Bmr012.w.6863)..id(Bmr012.w.6876)"/>
   </segment>
   <segment nite:id="Bmr012.segment.855" starttime="1467.29" endtime="1473.74" participant="fe016" timing-provenance="dialogueact">
      <nite:child href="Bmr012.C.words.xml#id(Bmr012.w.6877)..id(Bmr012.w.6895)"/>
   </segment>
   <segment nite:id="Bmr012.segment.856" starttime="1474.24" endtime="1475.82" participant="fe016" timing-provenance="segment">
      <nite:child href="Bmr012.C.words.xml#id(Bmr012.w.6896)..id(Bmr012.vocalsound.139)"/>
   </segment>
   <segment nite:id="Bmr012.segment.857" starttime="1476.07" endtime="1477.37" participant="fe016" timing-provenance="dialogueact">
      <nite:child href="Bmr012.C.words.xml#id(Bmr012.w.6900)..id(Bmr012.w.6904)"/>
   </segment>
   <segment nite:id="Bmr012.segment.858" starttime="1477.96" endtime="1482.4" participant="fe016" timing-provenance="dialogueact">
      <nite:child href="Bmr012.C.words.xml#id(Bmr012.w.6905)..id(Bmr012.w.6923)"/>
   </segment>
   <segment nite:id="Bmr012.segment.859" starttime="1483.48" endtime="1486.18" participant="fe016" timing-provenance="dialogueact">
      <nite:child href="Bmr012.C.words.xml#id(Bmr012.w.6924)..id(Bmr012.w.6936)"/>
   </segment>
   <segment nite:id="Bmr012.segment.861" starttime="1486.94" endtime="1488.55" participant="fe016" timing-provenance="dialogueact">
      <nite:child href="Bmr012.C.words.xml#id(Bmr012.w.6940)..id(Bmr012.w.6944)"/>
   </segment>
   <segment nite:id="Bmr012.segment.865" starttime="1491.37" endtime="1498.04" participant="fe016" timing-provenance="dialogueact">
      <nite:child href="Bmr012.C.words.xml#id(Bmr012.w.6969)..id(Bmr012.w.6994)"/>
   </segment>
   <segment nite:id="Bmr012.segment.866" starttime="1498.379" endtime="1515.02" participant="fe016" timing-provenance="segment">
      <nite:child href="Bmr012.C.words.xml#id(Bmr012.w.6995)..id(Bmr012.disfmarker.278)"/>
   </segment>
   <segment nite:id="Bmr012.segment.871" starttime="1517.99" endtime="1518.68" participant="fe016" timing-provenance="dialogueact">
      <nite:child href="Bmr012.C.words.xml#id(Bmr012.w.7098)..id(Bmr012.w.7102)"/>
   </segment>
   <segment nite:id="Bmr012.segment.872" starttime="1519.3" endtime="1519.75" participant="fe016" timing-provenance="dialogueact">
      <nite:child href="Bmr012.C.words.xml#id(Bmr012.w.7103)..id(Bmr012.w.7106)"/>
   </segment>
   <segment nite:id="Bmr012.segment.914" starttime="1619.97" endtime="1623.3" participant="fe016" timing-provenance="dialogueact">
      <nite:child href="Bmr012.C.words.xml#id(Bmr012.w.7543)..id(Bmr012.w.7556)"/>
   </segment>
   <segment nite:id="Bmr012.segment.917" starttime="1623.96" endtime="1624.38" participant="fe016" timing-provenance="dialogueact">
      <nite:child href="Bmr012.C.words.xml#id(Bmr012.w.7562)..id(Bmr012.w.7563)"/>
   </segment>
   <segment nite:id="Bmr012.segment.962" starttime="1725.48" endtime="1726.22" participant="fe016" timing-provenance="dialogueact">
      <nite:child href="Bmr012.C.words.xml#id(Bmr012.w.7951)..id(Bmr012.w.7952)"/>
   </segment>
   <segment nite:id="Bmr012.segment.965" starttime="1728.42" endtime="1731.87" participant="fe016" timing-provenance="dialogueact">
      <nite:child href="Bmr012.C.words.xml#id(Bmr012.w.7957)..id(Bmr012.w.7970)"/>
   </segment>
   <segment nite:id="Bmr012.segment.968" starttime="1734.4" endtime="1736.24" participant="fe016" timing-provenance="dialogueact">
      <nite:child href="Bmr012.C.words.xml#id(Bmr012.w.7985)..id(Bmr012.w.7990)"/>
   </segment>
   <segment nite:id="Bmr012.segment.975" starttime="1743.973" endtime="1744.999" participant="fe016" timing-provenance="segment">
      <nite:child href="Bmr012.C.words.xml#id(Bmr012.vocalsound.146)"/>
   </segment>
   <segment nite:id="Bmr012.segment.977" starttime="1744.999" endtime="1749.359" participant="fe016" timing-provenance="segment">
      <nite:child href="Bmr012.C.words.xml#id(Bmr012.w.8072)..id(Bmr012.vocalsound.147)"/>
   </segment>
   <segment nite:id="Bmr012.segment.982" starttime="1752.69" endtime="1753.05" participant="fe016" timing-provenance="segment">
      <nite:child href="Bmr012.C.words.xml#id(Bmr012.vocalsound.148)"/>
   </segment>
   <segment nite:id="Bmr012.segment.987" starttime="1765.51" endtime="1766.74" participant="fe016" timing-provenance="dialogueact">
      <nite:child href="Bmr012.C.words.xml#id(Bmr012.w.8157)..id(Bmr012.w.8164)"/>
   </segment>
   <segment nite:id="Bmr012.segment.990" starttime="1767.17" endtime="1773.7" participant="fe016" timing-provenance="dialogueact">
      <nite:child href="Bmr012.C.words.xml#id(Bmr012.w.8169)..id(Bmr012.w.8191)"/>
   </segment>
   <segment nite:id="Bmr012.segment.991" starttime="1774.71" endtime="1777.15" participant="fe016" timing-provenance="dialogueact">
      <nite:child href="Bmr012.C.words.xml#id(Bmr012.w.8192)..id(Bmr012.w.8202)"/>
   </segment>
   <segment nite:id="Bmr012.segment.992" starttime="1778.257" endtime="1778.946" participant="fe016" timing-provenance="segment">
      <nite:child href="Bmr012.C.words.xml#id(Bmr012.w.8203)..id(Bmr012.disfmarker.315)"/>
   </segment>
   <segment nite:id="Bmr012.segment.993" starttime="1778.946" endtime="1780.025" participant="fe016" timing-provenance="segment">
      <nite:child href="Bmr012.C.words.xml#id(Bmr012.w.8204)..id(Bmr012.disfmarker.316)"/>
   </segment>
   <segment nite:id="Bmr012.segment.996" starttime="1782.89" endtime="1784.419" participant="fe016" timing-provenance="segment">
      <nite:child href="Bmr012.C.words.xml#id(Bmr012.w.8227)..id(Bmr012.disfmarker.317)"/>
   </segment>
   <segment nite:id="Bmr012.segment.1001" starttime="1784.946" endtime="1786.51" participant="fe016" timing-provenance="segment">
      <nite:child href="Bmr012.C.words.xml#id(Bmr012.w.8264)..id(Bmr012.disfmarker.318)"/>
   </segment>
   <segment nite:id="Bmr012.segment.1003" starttime="1786.48" endtime="1790.08" participant="fe016" timing-provenance="dialogueact">
      <nite:child href="Bmr012.C.words.xml#id(Bmr012.w.8269)..id(Bmr012.w.8285)"/>
   </segment>
   <segment nite:id="Bmr012.segment.1005" starttime="1790.81" endtime="1791.31" participant="fe016" timing-provenance="dialogueact">
      <nite:child href="Bmr012.C.words.xml#id(Bmr012.w.8292)"/>
   </segment>
   <segment nite:id="Bmr012.segment.1006" starttime="1791.6" endtime="1797.76" participant="fe016" timing-provenance="segment">
      <nite:child href="Bmr012.C.words.xml#id(Bmr012.w.8293)..id(Bmr012.comment.20)"/>
   </segment>
   <segment nite:id="Bmr012.segment.1014" starttime="1798.94" endtime="1802.4" participant="fe016" timing-provenance="dialogueact">
      <nite:child href="Bmr012.C.words.xml#id(Bmr012.w.8354)..id(Bmr012.w.8366)"/>
   </segment>
   <segment nite:id="Bmr012.segment.1024" starttime="1814.66" endtime="1817.02" participant="fe016" timing-provenance="dialogueact">
      <nite:child href="Bmr012.C.words.xml#id(Bmr012.w.8418)..id(Bmr012.w.8427)"/>
   </segment>
   <segment nite:id="Bmr012.segment.1029" starttime="1820.28" endtime="1821.28" participant="fe016" timing-provenance="dialogueact">
      <nite:child href="Bmr012.C.words.xml#id(Bmr012.w.8454)..id(Bmr012.w.8458)"/>
   </segment>
   <segment nite:id="Bmr012.segment.1035" starttime="1825.33" endtime="1828.48" participant="fe016" timing-provenance="dialogueact">
      <nite:child href="Bmr012.C.words.xml#id(Bmr012.w.8484)..id(Bmr012.w.8497)"/>
   </segment>
   <segment nite:id="Bmr012.segment.1043" starttime="1839.98" endtime="1840.36" participant="fe016" timing-provenance="dialogueact">
      <nite:child href="Bmr012.C.words.xml#id(Bmr012.w.8562)..id(Bmr012.w.8563)"/>
   </segment>
   <segment nite:id="Bmr012.segment.1044" starttime="1841.2" endtime="1844.45" participant="fe016" timing-provenance="dialogueact">
      <nite:child href="Bmr012.C.words.xml#id(Bmr012.w.8564)..id(Bmr012.w.8577)"/>
   </segment>
   <segment nite:id="Bmr012.segment.1057" starttime="1860.48" endtime="1862.15" participant="fe016" timing-provenance="dialogueact">
      <nite:child href="Bmr012.C.words.xml#id(Bmr012.w.8681)..id(Bmr012.w.8686)"/>
   </segment>
   <segment nite:id="Bmr012.segment.1059" starttime="1862.88" endtime="1864.69" participant="fe016" timing-provenance="dialogueact">
      <nite:child href="Bmr012.C.words.xml#id(Bmr012.w.8689)..id(Bmr012.w.8695)"/>
   </segment>
   <segment nite:id="Bmr012.segment.1067" starttime="1874.38" endtime="1874.66" participant="fe016" timing-provenance="dialogueact">
      <nite:child href="Bmr012.C.words.xml#id(Bmr012.w.8765)..id(Bmr012.w.8766)"/>
   </segment>
   <segment nite:id="Bmr012.segment.1075" starttime="1891.56" endtime="1896.93" participant="fe016" timing-provenance="dialogueact">
      <nite:child href="Bmr012.C.words.xml#id(Bmr012.w.8871)..id(Bmr012.w.8893)"/>
   </segment>
   <segment nite:id="Bmr012.segment.1077" starttime="1897.7" endtime="1899.18" participant="fe016" timing-provenance="dialogueact">
      <nite:child href="Bmr012.C.words.xml#id(Bmr012.w.8897)..id(Bmr012.w.8902)"/>
   </segment>
   <segment nite:id="Bmr012.segment.1079" starttime="1899.85" endtime="1904.43" participant="fe016" timing-provenance="dialogueact">
      <nite:child href="Bmr012.C.words.xml#id(Bmr012.w.8907)..id(Bmr012.w.8925)"/>
   </segment>
   <segment nite:id="Bmr012.segment.1093" starttime="1933.81" endtime="1939.12" participant="fe016" timing-provenance="dialogueact">
      <nite:child href="Bmr012.C.words.xml#id(Bmr012.w.9049)..id(Bmr012.w.9075)"/>
   </segment>
   <segment nite:id="Bmr012.segment.1099" starttime="1940.21" endtime="1940.75" participant="fe016" timing-provenance="dialogueact">
      <nite:child href="Bmr012.C.words.xml#id(Bmr012.w.9098)..id(Bmr012.w.9102)"/>
   </segment>
   <segment nite:id="Bmr012.segment.1104" starttime="1948.02" endtime="1949.15" participant="fe016" timing-provenance="dialogueact">
      <nite:child href="Bmr012.C.words.xml#id(Bmr012.w.9137)..id(Bmr012.w.9142)"/>
   </segment>
   <segment nite:id="Bmr012.segment.1108" starttime="1949.59" endtime="1954.6" participant="fe016" timing-provenance="dialogueact">
      <nite:child href="Bmr012.C.words.xml#id(Bmr012.w.9167)..id(Bmr012.w.9196)"/>
   </segment>
   <segment nite:id="Bmr012.segment.1114" starttime="1956.551" endtime="1958.329" participant="fe016" timing-provenance="segment">
      <nite:child href="Bmr012.C.words.xml#id(Bmr012.vocalsound.170)"/>
   </segment>
   <segment nite:id="Bmr012.segment.1117" starttime="1959.301" endtime="1961.459" participant="fe016" timing-provenance="segment">
      <nite:child href="Bmr012.C.words.xml#id(Bmr012.vocalsound.172)"/>
   </segment>
   <segment nite:id="Bmr012.segment.1118" starttime="1963.03" endtime="1964.91" participant="fe016" timing-provenance="dialogueact">
      <nite:child href="Bmr012.C.words.xml#id(Bmr012.w.9254)..id(Bmr012.w.9261)"/>
   </segment>
   <segment nite:id="Bmr012.segment.1121" starttime="1965.54" endtime="1966.16" participant="fe016" timing-provenance="dialogueact">
      <nite:child href="Bmr012.C.words.xml#id(Bmr012.w.9279)..id(Bmr012.w.9280)"/>
   </segment>
   <segment nite:id="Bmr012.segment.1124" starttime="1967.38" endtime="1968.64" participant="fe016" timing-provenance="dialogueact">
      <nite:child href="Bmr012.C.words.xml#id(Bmr012.w.9289)..id(Bmr012.w.9293)"/>
   </segment>
   <segment nite:id="Bmr012.segment.1128" starttime="1980.4" endtime="1981.22" participant="fe016" timing-provenance="dialogueact">
      <nite:child href="Bmr012.C.words.xml#id(Bmr012.w.9367)..id(Bmr012.w.9372)"/>
   </segment>
   <segment nite:id="Bmr012.segment.1131" starttime="1982.45" endtime="1982.87" participant="fe016" timing-provenance="dialogueact">
      <nite:child href="Bmr012.C.words.xml#id(Bmr012.w.9387)..id(Bmr012.w.9389)"/>
   </segment>
   <segment nite:id="Bmr012.segment.1138" starttime="1993.86" endtime="1994.22" participant="fe016" timing-provenance="dialogueact">
      <nite:child href="Bmr012.C.words.xml#id(Bmr012.w.9448)..id(Bmr012.w.9449)"/>
   </segment>
   <segment nite:id="Bmr012.segment.1145" starttime="1995.78" endtime="2003.215" participant="fe016" timing-provenance="segment">
      <nite:child href="Bmr012.C.words.xml#id(Bmr012.vocalsound.177)..id(Bmr012.w.9488)"/>
   </segment>
   <segment nite:id="Bmr012.segment.1152" starttime="2003.79" endtime="2006.58" participant="fe016" timing-provenance="dialogueact">
      <nite:child href="Bmr012.C.words.xml#id(Bmr012.w.9510)..id(Bmr012.w.9524)"/>
   </segment>
   <segment nite:id="Bmr012.segment.1155" starttime="2007.2" endtime="2008.48" participant="fe016" timing-provenance="dialogueact">
      <nite:child href="Bmr012.C.words.xml#id(Bmr012.w.9529)..id(Bmr012.w.9536)"/>
   </segment>
   <segment nite:id="Bmr012.segment.1157" starttime="2008.89" endtime="2009.538" participant="fe016" timing-provenance="segment">
      <nite:child href="Bmr012.C.words.xml#id(Bmr012.comment.25)"/>
   </segment>
</nite:root>