<?xml version="1.0" encoding="ISO-8859-1" standalone="yes"?>
<nite:root nite:id="Bmr008.F.dialogue-acts" xmlns:nite="http://nite.sourceforge.net/">
   <dialogueact nite:id="Bmr008.F.dialogueact7" starttime="6.567" endtime="8.667" type="z" original-type="z" channel="c8" participant="fe008">
      <nite:child href="Bmr008.F.words.xml#id(Bmr008.w.53)..id(Bmr008.w.66)"/>
   </dialogueact>
   <dialogueact nite:id="Bmr008.F.dialogueact9" starttime="8.667" endtime="12.157" type="z" adjacency="2a" original-type="z" channel="c8" participant="fe008">
      <nite:child href="Bmr008.F.words.xml#id(Bmr008.w.67)..id(Bmr008.w.81)"/>
   </dialogueact>
   <dialogueact nite:id="Bmr008.F.dialogueact19" starttime="18.43" endtime="18.58" type="b" original-type="b" channel="c8" participant="fe008">
      <nite:child href="Bmr008.F.words.xml#id(Bmr008.w.127)..id(Bmr008.w.128)"/>
   </dialogueact>
   <dialogueact nite:id="Bmr008.F.dialogueact35" starttime="69.634" endtime="69.834" type="s" adjacency="5b.6a" original-type="s" channel="c8" participant="fe008">
      <nite:child href="Bmr008.F.words.xml#id(Bmr008.w.280)..id(Bmr008.w.283)"/>
   </dialogueact>
   <dialogueact nite:id="Bmr008.F.dialogueact59" starttime="143.593" endtime="145.083" type="fg|s^e" adjacency="8b.9a" original-type="fg|s^e" channel="c8" participant="fe008">
      <nite:child href="Bmr008.F.words.xml#id(Bmr008.w.613)..id(Bmr008.w.621)"/>
   </dialogueact>
   <dialogueact nite:id="Bmr008.F.dialogueact60" starttime="145.293" endtime="146.083" comment="FBH" type="s^cc" original-type="s^cc" channel="c8" participant="fe008">
      <nite:child href="Bmr008.F.words.xml#id(Bmr008.w.622)..id(Bmr008.w.628)"/>
   </dialogueact>
   <dialogueact nite:id="Bmr008.F.dialogueact65" starttime="149.752" endtime="152.142" type="s" adjacency="10b.11a" original-type="s" channel="c8" participant="fe008">
      <nite:child href="Bmr008.F.words.xml#id(Bmr008.w.649)..id(Bmr008.w.657)"/>
   </dialogueact>
   <dialogueact nite:id="Bmr008.F.dialogueact66" starttime="152.522" endtime="153.382" type="s^co" original-type="s^co" channel="c8" participant="fe008">
      <nite:child href="Bmr008.F.words.xml#id(Bmr008.w.658)..id(Bmr008.w.662)"/>
   </dialogueact>
   <dialogueact nite:id="Bmr008.F.dialogueact68" starttime="153.532" endtime="153.802" type="%-" original-type="%-" channel="c8" participant="fe008">
      <nite:child href="Bmr008.F.words.xml#id(Bmr008.w.673)..id(Bmr008.disfmarker.12)"/>
   </dialogueact>
   <dialogueact nite:id="Bmr008.F.dialogueact69" starttime="153.912" endtime="154.352" type="s^bk" adjacency="12b" original-type="s^bk" channel="c8" participant="fe008">
      <nite:child href="Bmr008.F.words.xml#id(Bmr008.w.674)..id(Bmr008.w.679)"/>
   </dialogueact>
   <dialogueact nite:id="Bmr008.F.dialogueact71" starttime="155.841" endtime="156.291" type="s^2^t1" adjacency="1b" original-type="s^2^t1" channel="c8" participant="fe008">
      <nite:child href="Bmr008.F.words.xml#id(Bmr008.w.687)..id(Bmr008.w.688)"/>
   </dialogueact>
   <dialogueact nite:id="Bmr008.F.dialogueact80" starttime="185.894" endtime="188.444" type="s^nd" adjacency="4b" original-type="s^nd" channel="c8" participant="fe008">
      <nite:child href="Bmr008.F.words.xml#id(Bmr008.w.801)..id(Bmr008.w.807)"/>
   </dialogueact>
   <dialogueact nite:id="Bmr008.F.dialogueact92" starttime="218.096" endtime="218.156" type="b.%" original-type="b.%" channel="c8" participant="fe008">
      <nite:child href="Bmr008.F.words.xml#id(Bmr008.w.936)..id(Bmr008.w.937)"/>
   </dialogueact>
   <dialogueact nite:id="Bmr008.F.dialogueact93" starttime="218.337" endtime="218.877" type="s.%--" original-type="s.%--" channel="c8" participant="fe008">
      <nite:child href="Bmr008.F.words.xml#id(Bmr008.w.938)..id(Bmr008.disfmarker.19)"/>
   </dialogueact>
   <dialogueact nite:id="Bmr008.F.dialogueact94" starttime="219.027" endtime="223.197" type="qy^rt" adjacency="9a" original-type="qy^rt" channel="c8" participant="fe008">
      <nite:child href="Bmr008.F.words.xml#id(Bmr008.w.941)..id(Bmr008.w.957)"/>
   </dialogueact>
   <dialogueact nite:id="Bmr008.F.dialogueact98" starttime="223.78" endtime="224.15" type="qy^bu^m^rt" adjacency="10b" original-type="qy^bu^m^rt" channel="c8" participant="fe008">
      <nite:child href="Bmr008.F.words.xml#id(Bmr008.w.966)..id(Bmr008.w.967)"/>
   </dialogueact>
   <dialogueact nite:id="Bmr008.F.dialogueact99" starttime="224.15" endtime="225.92" type="qw" adjacency="1a" original-type="qw" channel="c8" participant="fe008">
      <nite:child href="Bmr008.F.words.xml#id(Bmr008.w.968)..id(Bmr008.w.977)"/>
   </dialogueact>
   <dialogueact nite:id="Bmr008.F.dialogueact103" starttime="241.917" endtime="243.289" type="s^aa^rt" adjacency="2b.3a.4a" original-type="s^aa^rt" channel="c8" participant="fe008">
      <nite:child href="Bmr008.F.words.xml#id(Bmr008.w.1,035)..id(Bmr008.w.1,042)"/>
   </dialogueact>
   <dialogueact nite:id="Bmr008.F.dialogueact105" starttime="243.935" endtime="257.255" type="s^df" adjacency="3b" original-type="s^df" channel="c8" participant="fe008">
      <nite:child href="Bmr008.F.words.xml#id(Bmr008.w.1,043)..id(Bmr008.w.1,100)"/>
   </dialogueact>
   <dialogueact nite:id="Bmr008.F.dialogueact107" starttime="257.395" endtime="262.565" type="s^e" original-type="s^e" channel="c8" participant="fe008">
      <nite:child href="Bmr008.F.words.xml#id(Bmr008.w.1,101)..id(Bmr008.w.1,124)"/>
   </dialogueact>
   <dialogueact nite:id="Bmr008.F.dialogueact108" starttime="263.045" endtime="267.205" type="s" original-type="s" channel="c8" participant="fe008">
      <nite:child href="Bmr008.F.words.xml#id(Bmr008.w.1,125)..id(Bmr008.w.1,146)"/>
   </dialogueact>
   <dialogueact nite:id="Bmr008.F.dialogueact109" starttime="267.205" endtime="275.826" type="s.%--" original-type="s.%--" channel="c8" participant="fe008">
      <nite:child href="Bmr008.F.words.xml#id(Bmr008.w.1,147)..id(Bmr008.disfmarker.30)"/>
   </dialogueact>
   <dialogueact nite:id="Bmr008.F.dialogueact110" starttime="275.826" endtime="282.762" type="s" adjacency="5a" original-type="sj" channel="c8" participant="fe008">
      <nite:child href="Bmr008.F.words.xml#id(Bmr008.w.1,177)..id(Bmr008.w.1,201)"/>
   </dialogueact>
   <dialogueact nite:id="Bmr008.F.dialogueact112" starttime="282.952" endtime="287.942" type="s" original-type="sj" channel="c8" participant="fe008">
      <nite:child href="Bmr008.F.words.xml#id(Bmr008.w.1,202)..id(Bmr008.w.1,218)"/>
   </dialogueact>
   <dialogueact nite:id="Bmr008.F.dialogueact114" starttime="287.992" endtime="290.112" type="s" adjacency="6a" original-type="sj" channel="c8" participant="fe008">
      <nite:child href="Bmr008.F.words.xml#id(Bmr008.w.1,219)..id(Bmr008.w.1,232)"/>
   </dialogueact>
   <dialogueact nite:id="Bmr008.F.dialogueact116" starttime="290.949" endtime="293.329" type="s^df.%--" original-type="s^df.%--" channel="c8" participant="fe008">
      <nite:child href="Bmr008.F.words.xml#id(Bmr008.w.1,235)..id(Bmr008.disfmarker.31)"/>
   </dialogueact>
   <dialogueact nite:id="Bmr008.F.dialogueact118" starttime="297.137" endtime="298.057" type="s" adjacency="7b-1" original-type="s" channel="c8" participant="fe008">
      <nite:child href="Bmr008.F.words.xml#id(Bmr008.w.1,267)..id(Bmr008.w.1,271)"/>
   </dialogueact>
   <dialogueact nite:id="Bmr008.F.dialogueact119" starttime="298.147" endtime="299.187" type="s^r" adjacency="7b-1+" original-type="s^r" channel="c8" participant="fe008">
      <nite:child href="Bmr008.F.words.xml#id(Bmr008.w.1,272)..id(Bmr008.w.1,278)"/>
   </dialogueact>
   <dialogueact nite:id="Bmr008.F.dialogueact121" starttime="299.317" endtime="300.977" type="s^aap" original-type="s^aap" channel="c8" participant="fe008">
      <nite:child href="Bmr008.F.words.xml#id(Bmr008.w.1,288)..id(Bmr008.w.1,294)"/>
   </dialogueact>
   <dialogueact nite:id="Bmr008.F.dialogueact124" starttime="307.754" endtime="308.084" type="b" original-type="b" channel="c8" participant="fe008">
      <nite:child href="Bmr008.F.words.xml#id(Bmr008.w.1,331)..id(Bmr008.w.1,334)"/>
   </dialogueact>
   <dialogueact nite:id="Bmr008.F.dialogueact128" starttime="319.091" endtime="319.401" type="b" original-type="b" channel="c8" participant="fe008">
      <nite:child href="Bmr008.F.words.xml#id(Bmr008.w.1,393)..id(Bmr008.w.1,396)"/>
   </dialogueact>
   <dialogueact nite:id="Bmr008.F.dialogueact129" starttime="321.477" endtime="322.387" type="s" adjacency="8b-1.9a" original-type="s" channel="c8" participant="fe008">
      <nite:child href="Bmr008.F.words.xml#id(Bmr008.w.1,397)..id(Bmr008.w.1,403)"/>
   </dialogueact>
   <dialogueact nite:id="Bmr008.F.dialogueact130" starttime="322.447" endtime="326.367" type="s^e.%-" adjacency="9b" original-type="s^e.%-" channel="c8" participant="fe008">
      <nite:child href="Bmr008.F.words.xml#id(Bmr008.w.1,404)..id(Bmr008.disfmarker.38)"/>
   </dialogueact>
   <dialogueact nite:id="Bmr008.F.dialogueact136" starttime="336.22" endtime="336.99" type="s^df^nd" adjacency="11b" original-type="s^df^nd" channel="c8" participant="fe008">
      <nite:child href="Bmr008.F.words.xml#id(Bmr008.w.1,474)..id(Bmr008.w.1,482)"/>
   </dialogueact>
   <dialogueact nite:id="Bmr008.F.dialogueact137" starttime="337.1" endtime="337.26" type="%--" original-type="%--" channel="c8" participant="fe008">
      <nite:child href="Bmr008.F.words.xml#id(Bmr008.w.1,483)..id(Bmr008.disfmarker.40)"/>
   </dialogueact>
   <dialogueact nite:id="Bmr008.F.dialogueact138" starttime="337.46" endtime="337.61" type="b" original-type="b" channel="c8" participant="fe008">
      <nite:child href="Bmr008.F.words.xml#id(Bmr008.w.1,484)..id(Bmr008.w.1,485)"/>
   </dialogueact>
   <dialogueact nite:id="Bmr008.F.dialogueact139" starttime="337.61" endtime="345.92" type="s" adjacency="1a" original-type="s" channel="c8" participant="fe008">
      <nite:child href="Bmr008.F.words.xml#id(Bmr008.w.1,493)..id(Bmr008.w.1,527)"/>
   </dialogueact>
   <dialogueact nite:id="Bmr008.F.dialogueact153" starttime="367.184" endtime="374.274" type="s" adjacency="3a" original-type="s" channel="c8" participant="fe008">
      <nite:child href="Bmr008.F.words.xml#id(Bmr008.w.1,637)..id(Bmr008.w.1,669)"/>
   </dialogueact>
   <dialogueact nite:id="Bmr008.F.dialogueact157" starttime="374.964" endtime="376.264" type="s.%--" adjacency="4b" original-type="s.%--" channel="c8" participant="fe008">
      <nite:child href="Bmr008.F.words.xml#id(Bmr008.w.1,672)..id(Bmr008.w.1,679)"/>
   </dialogueact>
   <dialogueact nite:id="Bmr008.F.dialogueact158" starttime="376.264" endtime="377.424" type="qy^d^rt" adjacency="4b.5a" original-type="qy^d^rt" channel="c8" participant="fe008">
      <nite:child href="Bmr008.F.words.xml#id(Bmr008.w.1,680)..id(Bmr008.w.1,686)"/>
   </dialogueact>
   <dialogueact nite:id="Bmr008.F.dialogueact159" starttime="377.584" endtime="383.654" type="s" adjacency="6a" original-type="s" channel="c8" participant="fe008">
      <nite:child href="Bmr008.F.words.xml#id(Bmr008.w.1,689)..id(Bmr008.w.1,721)"/>
   </dialogueact>
   <dialogueact nite:id="Bmr008.F.dialogueact165" starttime="383.654" endtime="383.784" type="b" original-type="b" channel="c8" participant="fe008">
      <nite:child href="Bmr008.F.words.xml#id(Bmr008.w.1,722)..id(Bmr008.w.1,723)"/>
   </dialogueact>
   <dialogueact nite:id="Bmr008.F.dialogueact182" starttime="416.907" endtime="422.965" comment="This might be a &lt;bd&gt; of her and Adam's proposal." type="s" adjacency="3b-2" original-type="s" channel="c8" participant="fe008">
      <nite:child href="Bmr008.F.words.xml#id(Bmr008.w.1,878)..id(Bmr008.w.1,908)"/>
   </dialogueact>
   <dialogueact nite:id="Bmr008.F.dialogueact184" starttime="422.965" endtime="424.295" type="s" original-type="s" channel="c8" participant="fe008">
      <nite:child href="Bmr008.F.words.xml#id(Bmr008.w.1,909)..id(Bmr008.w.1,915)"/>
   </dialogueact>
   <dialogueact nite:id="Bmr008.F.dialogueact185" starttime="424.765" endtime="425.765" type="%-" original-type="%-" channel="c8" participant="fe008">
      <nite:child href="Bmr008.F.words.xml#id(Bmr008.w.1,917)..id(Bmr008.disfmarker.62)"/>
   </dialogueact>
   <dialogueact nite:id="Bmr008.F.dialogueact211" starttime="459.778" endtime="464.038" comment="said at 7:40" type="qy^rt" adjacency="7b-2.8a" original-type="qy^rt" channel="c8" participant="fe008">
      <nite:child href="Bmr008.F.words.xml#id(Bmr008.w.2,139)..id(Bmr008.w.2,157)"/>
   </dialogueact>
   <dialogueact nite:id="Bmr008.F.dialogueact244" starttime="531.538" endtime="531.748" type="b" original-type="b" channel="c8" participant="fe008">
      <nite:child href="Bmr008.F.words.xml#id(Bmr008.w.2,520)..id(Bmr008.w.2,523)"/>
   </dialogueact>
   <dialogueact nite:id="Bmr008.F.dialogueact246" starttime="531.748" endtime="532.288" type="s^aa" adjacency="2b" original-type="s^aa" channel="c8" participant="fe008">
      <nite:child href="Bmr008.F.words.xml#id(Bmr008.w.2,524)..id(Bmr008.w.2,527)"/>
   </dialogueact>
   <dialogueact nite:id="Bmr008.F.dialogueact250" starttime="539.87" endtime="540.71" type="s" adjacency="4b-3" original-type="s" channel="c8" participant="fe008">
      <nite:child href="Bmr008.F.words.xml#id(Bmr008.w.2,548)..id(Bmr008.w.2,553)"/>
   </dialogueact>
   <dialogueact nite:id="Bmr008.F.dialogueact254" starttime="541.127" endtime="607.417" comment="said at 10:08" type="s^aa" adjacency="8b-1" original-type="s^aa" channel="c8" participant="fe008">
      <nite:child href="Bmr008.F.words.xml#id(Bmr008.w.2,577)..id(Bmr008.w.2,852)"/>
   </dialogueact>
   <dialogueact nite:id="Bmr008.F.dialogueact283" starttime="620.02" endtime="623.65" type="qy^d" adjacency="2a" original-type="qy^d" channel="c8" participant="fe008">
      <nite:child href="Bmr008.F.words.xml#id(Bmr008.w.2,922)..id(Bmr008.w.2,944)"/>
   </dialogueact>
   <dialogueact nite:id="Bmr008.F.dialogueact285" starttime="624.157" endtime="624.577" type="s^bk" adjacency="3b" original-type="s^bk" channel="c8" participant="fe008">
      <nite:child href="Bmr008.F.words.xml#id(Bmr008.w.2,947)..id(Bmr008.w.2,950)"/>
   </dialogueact>
   <dialogueact nite:id="Bmr008.F.dialogueact287" starttime="625.228" endtime="625.468" type="%" original-type="%" channel="c8" participant="fe008">
      <nite:child href="Bmr008.F.words.xml#id(Bmr008.w.2,960)..id(Bmr008.w.2,961)"/>
   </dialogueact>
   <dialogueact nite:id="Bmr008.F.dialogueact289" starttime="632.314" endtime="632.614" type="b" original-type="b" channel="c8" participant="fe008">
      <nite:child href="Bmr008.F.words.xml#id(Bmr008.w.3,001)..id(Bmr008.w.3,004)"/>
   </dialogueact>
   <dialogueact nite:id="Bmr008.F.dialogueact290" starttime="634.541" endtime="634.841" comment="FBH" type="b" original-type="b" channel="c8" participant="fe008">
      <nite:child href="Bmr008.F.words.xml#id(Bmr008.w.3,005)..id(Bmr008.w.3,008)"/>
   </dialogueact>
   <dialogueact nite:id="Bmr008.F.dialogueact292" starttime="635.211" endtime="635.521" type="b" original-type="b" channel="c8" participant="fe008">
      <nite:child href="Bmr008.F.words.xml#id(Bmr008.w.3,011)..id(Bmr008.w.3,014)"/>
   </dialogueact>
   <dialogueact nite:id="Bmr008.F.dialogueact300" starttime="653.489" endtime="653.819" type="b" original-type="b" channel="c8" participant="fe008">
      <nite:child href="Bmr008.F.words.xml#id(Bmr008.w.3,117)..id(Bmr008.w.3,120)"/>
   </dialogueact>
   <dialogueact nite:id="Bmr008.F.dialogueact325" starttime="702.377" endtime="702.627" type="b" original-type="b" channel="c8" participant="fe008">
      <nite:child href="Bmr008.F.words.xml#id(Bmr008.w.3,370)..id(Bmr008.w.3,371)"/>
   </dialogueact>
   <dialogueact nite:id="Bmr008.F.dialogueact333" starttime="717.206" endtime="717.406" type="%-" original-type="%-" channel="c8" participant="fe008">
      <nite:child href="Bmr008.F.words.xml#id(Bmr008.w.3,452)..id(Bmr008.disfmarker.124)"/>
   </dialogueact>
   <dialogueact nite:id="Bmr008.F.dialogueact345" starttime="730.05" endtime="734.95" type="s" adjacency="3b" original-type="s" channel="c8" participant="fe008">
      <nite:child href="Bmr008.F.words.xml#id(Bmr008.w.3,535)..id(Bmr008.w.3,556)"/>
   </dialogueact>
   <dialogueact nite:id="Bmr008.F.dialogueact347" starttime="734.95" endtime="741.04" comment="quotes: &quot;middle 12:15 start time for this utterance. thirties&quot;" type="s" adjacency="4a" original-type="s" channel="c8" participant="fe008">
      <nite:child href="Bmr008.F.words.xml#id(Bmr008.w.3,557)..id(Bmr008.w.3,573)"/>
   </dialogueact>
   <dialogueact nite:id="Bmr008.F.dialogueact349" starttime="741.04" endtime="744.54" type="s.%-" original-type="s.%-" channel="c8" participant="fe008">
      <nite:child href="Bmr008.F.words.xml#id(Bmr008.w.3,574)..id(Bmr008.disfmarker.136)"/>
   </dialogueact>
   <dialogueact nite:id="Bmr008.F.dialogueact352" starttime="751.668" endtime="751.928" type="b" original-type="b" channel="c8" participant="fe008">
      <nite:child href="Bmr008.F.words.xml#id(Bmr008.w.3,627)..id(Bmr008.w.3,628)"/>
   </dialogueact>
   <dialogueact nite:id="Bmr008.F.dialogueact353" starttime="752.078" endtime="753.718" type="s^2^aa.%-" adjacency="5b-2" original-type="s^2^aa.%-" channel="c8" participant="fe008">
      <nite:child href="Bmr008.F.words.xml#id(Bmr008.w.3,629)..id(Bmr008.w.3,635)"/>
   </dialogueact>
   <dialogueact nite:id="Bmr008.F.dialogueact356" starttime="756.518" endtime="756.808" type="b" original-type="b" channel="c8" participant="fe008">
      <nite:child href="Bmr008.F.words.xml#id(Bmr008.w.3,669)..id(Bmr008.w.3,670)"/>
   </dialogueact>
   <dialogueact nite:id="Bmr008.F.dialogueact358" starttime="757.456" endtime="759.206" type="s^2^e" adjacency="6b-2" original-type="s^2^e" channel="c8" participant="fe008">
      <nite:child href="Bmr008.F.words.xml#id(Bmr008.w.3,673)..id(Bmr008.w.3,682)"/>
   </dialogueact>
   <dialogueact nite:id="Bmr008.F.dialogueact361" starttime="759.206" endtime="761.566" type="s^df.%-" original-type="s^df.%-" channel="c8" participant="fe008">
      <nite:child href="Bmr008.F.words.xml#id(Bmr008.w.3,683)..id(Bmr008.disfmarker.141)"/>
   </dialogueact>
   <dialogueact nite:id="Bmr008.F.dialogueact363" starttime="764.235" endtime="764.945" comment="quotes maybe: whole utt" type="s^fe^j" adjacency="7b" original-type="s^fe^j" channel="c8" participant="fe008">
      <nite:child href="Bmr008.F.words.xml#id(Bmr008.w.3,712)..id(Bmr008.w.3,715)"/>
   </dialogueact>
   <dialogueact nite:id="Bmr008.F.dialogueact367" starttime="768.588" endtime="769.808" type="qw^br^rt" adjacency="8b" original-type="qw^br^rt" channel="c8" participant="fe008">
      <nite:child href="Bmr008.F.words.xml#id(Bmr008.w.3,735)..id(Bmr008.w.3,740)"/>
   </dialogueact>
   <dialogueact nite:id="Bmr008.F.dialogueact370" starttime="775.401" endtime="775.951" type="s^bk" original-type="s^bk" channel="c8" participant="fe008">
      <nite:child href="Bmr008.F.words.xml#id(Bmr008.w.3,759)..id(Bmr008.w.3,762)"/>
   </dialogueact>
   <dialogueact nite:id="Bmr008.F.dialogueact409" starttime="839.548" endtime="848.478" type="s" adjacency="1a" original-type="s" channel="c8" participant="fe008">
      <nite:child href="Bmr008.F.words.xml#id(Bmr008.w.4,132)..id(Bmr008.w.4,169)"/>
   </dialogueact>
   <dialogueact nite:id="Bmr008.F.dialogueact411" starttime="848.518" endtime="850.248" type="s" adjacency="2b" original-type="s" channel="c8" participant="fe008">
      <nite:child href="Bmr008.F.words.xml#id(Bmr008.w.4,174)..id(Bmr008.w.4,188)"/>
   </dialogueact>
   <dialogueact nite:id="Bmr008.F.dialogueact413" starttime="850.718" endtime="855.03" comment="quotes: &quot;optional&quot;" type="s.%--" original-type="s.%--" channel="c8" participant="fe008">
      <nite:child href="Bmr008.F.words.xml#id(Bmr008.w.4,191)..id(Bmr008.disfmarker.161)"/>
   </dialogueact>
   <dialogueact nite:id="Bmr008.F.dialogueact414" starttime="855.03" endtime="862.076" type="s" original-type="s" channel="c8" participant="fe008">
      <nite:child href="Bmr008.F.words.xml#id(Bmr008.w.4,210)..id(Bmr008.w.4,239)"/>
   </dialogueact>
   <dialogueact nite:id="Bmr008.F.dialogueact428" starttime="871.38" endtime="871.75" type="s^ba" original-type="sj^ba" channel="c8" participant="fe008">
      <nite:child href="Bmr008.F.words.xml#id(Bmr008.w.4,325)..id(Bmr008.w.4,328)"/>
   </dialogueact>
   <dialogueact nite:id="Bmr008.F.dialogueact429" starttime="871.75" endtime="872.62" type="s^ba^e" original-type="sj^ba^e" channel="c8" participant="fe008">
      <nite:child href="Bmr008.F.words.xml#id(Bmr008.w.4,329)..id(Bmr008.w.4,334)"/>
   </dialogueact>
   <dialogueact nite:id="Bmr008.F.dialogueact437" starttime="882.41" endtime="882.68" type="b" original-type="b" channel="c8" participant="fe008">
      <nite:child href="Bmr008.F.words.xml#id(Bmr008.w.4,391)..id(Bmr008.w.4,392)"/>
   </dialogueact>
   <dialogueact nite:id="Bmr008.F.dialogueact441" starttime="889.68" endtime="890.03" type="s^t1.%" original-type="s^t1.%" channel="c8" participant="fe008">
      <nite:child href="Bmr008.F.words.xml#id(Bmr008.w.4,436)..id(Bmr008.w.4,439)"/>
   </dialogueact>
   <dialogueact nite:id="Bmr008.F.dialogueact442" starttime="890.51" endtime="891.37" type="s" adjacency="8b-2.9a-2.11a" original-type="s" channel="c8" participant="fe008">
      <nite:child href="Bmr008.F.words.xml#id(Bmr008.w.4,451)..id(Bmr008.w.4,457)"/>
   </dialogueact>
   <dialogueact nite:id="Bmr008.F.dialogueact443" starttime="891.47" endtime="891.99" type="s^r" adjacency="11b" original-type="s^r" channel="c8" participant="fe008">
      <nite:child href="Bmr008.F.words.xml#id(Bmr008.w.4,458)..id(Bmr008.w.4,463)"/>
   </dialogueact>
   <dialogueact nite:id="Bmr008.F.dialogueact459" starttime="936.828" endtime="940.028" type="s" original-type="s" channel="c8" participant="fe008">
      <nite:child href="Bmr008.F.words.xml#id(Bmr008.w.4,638)..id(Bmr008.w.4,656)"/>
   </dialogueact>
   <dialogueact nite:id="Bmr008.F.dialogueact461" starttime="941.12" endtime="945.32" type="s" original-type="s" channel="c8" participant="fe008">
      <nite:child href="Bmr008.F.words.xml#id(Bmr008.w.4,657)..id(Bmr008.w.4,675)"/>
   </dialogueact>
   <dialogueact nite:id="Bmr008.F.dialogueact462" starttime="945.4" endtime="949.07" type="s" original-type="s" channel="c8" participant="fe008">
      <nite:child href="Bmr008.F.words.xml#id(Bmr008.w.4,676)..id(Bmr008.w.4,689)"/>
   </dialogueact>
   <dialogueact nite:id="Bmr008.F.dialogueact463" starttime="949.07" endtime="951.68" type="s" original-type="s" channel="c8" participant="fe008">
      <nite:child href="Bmr008.F.words.xml#id(Bmr008.w.4,690)..id(Bmr008.w.4,701)"/>
   </dialogueact>
   <dialogueact nite:id="Bmr008.F.dialogueact464" starttime="951.73" endtime="955.5" comment="quotes: where did you live during your you know childhoold and adolescence?&quot;" type="s^e:qw" original-type="s^e:qw" channel="c8" participant="fe008">
      <nite:child href="Bmr008.F.words.xml#id(Bmr008.w.4,702)..id(Bmr008.w.4,719)"/>
   </dialogueact>
   <dialogueact nite:id="Bmr008.F.dialogueact467" starttime="955.93" endtime="956.49" type="s.%-" adjacency="4a" original-type="s.%-" channel="c8" participant="fe008">
      <nite:child href="Bmr008.F.words.xml#id(Bmr008.w.4,726)..id(Bmr008.disfmarker.183)"/>
   </dialogueact>
   <dialogueact nite:id="Bmr008.F.dialogueact469" starttime="961.518" endtime="962.678" type="s^aa" adjacency="5b" original-type="s^aa" channel="c8" participant="fe008">
      <nite:child href="Bmr008.F.words.xml#id(Bmr008.w.4,747)..id(Bmr008.w.4,752)"/>
   </dialogueact>
   <dialogueact nite:id="Bmr008.F.dialogueact470" starttime="962.678" endtime="965.96" type="s" adjacency="6a" original-type="s" channel="c8" participant="fe008">
      <nite:child href="Bmr008.F.words.xml#id(Bmr008.w.4,753)..id(Bmr008.w.4,779)"/>
   </dialogueact>
   <dialogueact nite:id="Bmr008.F.dialogueact473" starttime="965.96" endtime="966.18" type="fh" original-type="fh" channel="c8" participant="fe008">
      <nite:child href="Bmr008.F.words.xml#id(Bmr008.w.4,780)..id(Bmr008.disfmarker.186)"/>
   </dialogueact>
   <dialogueact nite:id="Bmr008.F.dialogueact474" starttime="969.908" endtime="970.298" type="b" original-type="b" channel="c8" participant="fe008">
      <nite:child href="Bmr008.F.words.xml#id(Bmr008.w.4,813)..id(Bmr008.w.4,816)"/>
   </dialogueact>
   <dialogueact nite:id="Bmr008.F.dialogueact477" starttime="972.85" endtime="973.16" type="b" original-type="b" channel="c8" participant="fe008">
      <nite:child href="Bmr008.F.words.xml#id(Bmr008.w.4,835)..id(Bmr008.w.4,838)"/>
   </dialogueact>
   <dialogueact nite:id="Bmr008.F.dialogueact479" starttime="974.855" endtime="975.285" type="b" original-type="b" channel="c8" participant="fe008">
      <nite:child href="Bmr008.F.words.xml#id(Bmr008.w.4,848)..id(Bmr008.w.4,851)"/>
   </dialogueact>
   <dialogueact nite:id="Bmr008.F.dialogueact483" starttime="983.82" endtime="984.75" type="s.%-" original-type="s.%-" channel="c8" participant="fe008">
      <nite:child href="Bmr008.F.words.xml#id(Bmr008.w.4,880)..id(Bmr008.disfmarker.191)"/>
   </dialogueact>
   <dialogueact nite:id="Bmr008.F.dialogueact485" starttime="984.75" endtime="984.83" type="b" original-type="b" channel="c8" participant="fe008">
      <nite:child href="Bmr008.F.words.xml#id(Bmr008.w.4,887)..id(Bmr008.w.4,888)"/>
   </dialogueact>
   <dialogueact nite:id="Bmr008.F.dialogueact486" starttime="989.498" endtime="990.028" type="b" original-type="b" channel="c8" participant="fe008">
      <nite:child href="Bmr008.F.words.xml#id(Bmr008.w.4,906)..id(Bmr008.w.4,909)"/>
   </dialogueact>
   <dialogueact nite:id="Bmr008.F.dialogueact494" starttime="999.522" endtime="1005.26" type="s" adjacency="1b" original-type="s" channel="c8" participant="fe008">
      <nite:child href="Bmr008.F.words.xml#id(Bmr008.w.4,968)..id(Bmr008.w.5,010)"/>
   </dialogueact>
   <dialogueact nite:id="Bmr008.F.dialogueact499" starttime="1006.5" endtime="1009.97" type="s" adjacency="2b-2" original-type="s" channel="c8" participant="fe008">
      <nite:child href="Bmr008.F.words.xml#id(Bmr008.w.5,034)..id(Bmr008.w.5,049)"/>
   </dialogueact>
   <dialogueact nite:id="Bmr008.F.dialogueact510" starttime="1032.17" endtime="1032.47" type="b" original-type="b" channel="c8" participant="fe008">
      <nite:child href="Bmr008.F.words.xml#id(Bmr008.w.5,157)..id(Bmr008.w.5,160)"/>
   </dialogueact>
   <dialogueact nite:id="Bmr008.F.dialogueact512" starttime="1035.11" endtime="1035.7" type="fg" original-type="fg" channel="c8" participant="fe008">
      <nite:child href="Bmr008.F.words.xml#id(Bmr008.w.5,187)..id(Bmr008.disfmarker.207)"/>
   </dialogueact>
   <dialogueact nite:id="Bmr008.F.dialogueact523" starttime="1054.51" endtime="1054.85" type="fg" original-type="fg" channel="c8" participant="fe008">
      <nite:child href="Bmr008.F.words.xml#id(Bmr008.w.5,292)..id(Bmr008.disfmarker.211)"/>
   </dialogueact>
   <dialogueact nite:id="Bmr008.F.dialogueact528" starttime="1063.33" endtime="1064.85" type="s" original-type="s" channel="c8" participant="fe008">
      <nite:child href="Bmr008.F.words.xml#id(Bmr008.w.5,323)..id(Bmr008.w.5,332)"/>
   </dialogueact>
   <dialogueact nite:id="Bmr008.F.dialogueact530" starttime="1064.96" endtime="1067.13" type="qy.%--" adjacency="1a" original-type="qy.%--" channel="c8" participant="fe008">
      <nite:child href="Bmr008.F.words.xml#id(Bmr008.w.5,337)..id(Bmr008.disfmarker.216)"/>
   </dialogueact>
   <dialogueact nite:id="Bmr008.F.dialogueact533" starttime="1069.03" endtime="1069.44" type="s^bk" adjacency="2b" original-type="s^bk" channel="c8" participant="fe008">
      <nite:child href="Bmr008.F.words.xml#id(Bmr008.w.5,371)..id(Bmr008.w.5,373)"/>
   </dialogueact>
   <dialogueact nite:id="Bmr008.F.dialogueact535" starttime="1070.19" endtime="1070.42" type="b.%" original-type="b.%" channel="c8" participant="fe008">
      <nite:child href="Bmr008.F.words.xml#id(Bmr008.w.5,374)..id(Bmr008.w.5,375)"/>
   </dialogueact>
   <dialogueact nite:id="Bmr008.F.dialogueact538" starttime="1071.78" endtime="1072.67" type="s^ba" adjacency="3b" original-type="sj^ba" channel="c8" participant="fe008">
      <nite:child href="Bmr008.F.words.xml#id(Bmr008.w.5,386)..id(Bmr008.w.5,392)"/>
   </dialogueact>
   <dialogueact nite:id="Bmr008.F.dialogueact539" starttime="1072.67" endtime="1072.95" type="b" original-type="b" channel="c8" participant="fe008">
      <nite:child href="Bmr008.F.words.xml#id(Bmr008.w.5,393)..id(Bmr008.w.5,394)"/>
   </dialogueact>
   <dialogueact nite:id="Bmr008.F.dialogueact542" starttime="1074.64" endtime="1074.83" type="%-" original-type="%-" channel="c8" participant="fe008">
      <nite:child href="Bmr008.F.words.xml#id(Bmr008.w.5,414)..id(Bmr008.disfmarker.218)"/>
   </dialogueact>
   <dialogueact nite:id="Bmr008.F.dialogueact546" starttime="1076.89" endtime="1077.58" type="s^ba" adjacency="5b-1" original-type="sj^ba" channel="c8" participant="fe008">
      <nite:child href="Bmr008.F.words.xml#id(Bmr008.w.5,423)..id(Bmr008.w.5,426)"/>
   </dialogueact>
   <dialogueact nite:id="Bmr008.F.dialogueact547" starttime="1078.11" endtime="1080.45" type="s" adjacency="6a" original-type="s" channel="c8" participant="fe008">
      <nite:child href="Bmr008.F.words.xml#id(Bmr008.w.5,427)..id(Bmr008.w.5,440)"/>
   </dialogueact>
   <dialogueact nite:id="Bmr008.F.dialogueact548" starttime="1080.45" endtime="1084.14" type="s" adjacency="6a+" original-type="s" channel="c8" participant="fe008">
      <nite:child href="Bmr008.F.words.xml#id(Bmr008.w.5,441)..id(Bmr008.w.5,458)"/>
   </dialogueact>
   <dialogueact nite:id="Bmr008.F.dialogueact550" starttime="1084.14" endtime="1085.11" type="s.%-" original-type="s.%-" channel="c8" participant="fe008">
      <nite:child href="Bmr008.F.words.xml#id(Bmr008.w.5,459)..id(Bmr008.w.5,461)"/>
   </dialogueact>
   <dialogueact nite:id="Bmr008.F.dialogueact551" starttime="1087.04" endtime="1087.61" type="s^aa" adjacency="7b-1" original-type="s^aa" channel="c8" participant="fe008">
      <nite:child href="Bmr008.F.words.xml#id(Bmr008.w.5,478)..id(Bmr008.w.5,483)"/>
   </dialogueact>
   <dialogueact nite:id="Bmr008.F.dialogueact553" starttime="1087.61" endtime="1089.37" type="s.%--" adjacency="8a" original-type="s.%--" channel="c8" participant="fe008">
      <nite:child href="Bmr008.F.words.xml#id(Bmr008.w.5,484)..id(Bmr008.w.5,492)"/>
   </dialogueact>
   <dialogueact nite:id="Bmr008.F.dialogueact556" starttime="1090.32" endtime="1090.56" type="qw.%-" original-type="qw.%-" channel="c8" participant="fe008">
      <nite:child href="Bmr008.F.words.xml#id(Bmr008.w.5,510)"/>
   </dialogueact>
   <dialogueact nite:id="Bmr008.F.dialogueact562" starttime="1111.67" endtime="1112.66" type="s^ba" adjacency="11b" original-type="sj^ba" channel="c8" participant="fe008">
      <nite:child href="Bmr008.F.words.xml#id(Bmr008.w.5,599)..id(Bmr008.w.5,604)"/>
   </dialogueact>
   <dialogueact nite:id="Bmr008.F.dialogueact567" starttime="1125.82" endtime="1127.24" type="s" adjacency="10b-1" original-type="s" channel="c8" participant="fe008">
      <nite:child href="Bmr008.F.words.xml#id(Bmr008.w.5,655)..id(Bmr008.w.5,661)"/>
   </dialogueact>
   <dialogueact nite:id="Bmr008.F.dialogueact571" starttime="1128.14" endtime="1130.32" type="s" original-type="s" channel="c8" participant="fe008">
      <nite:child href="Bmr008.F.words.xml#id(Bmr008.w.5,690)..id(Bmr008.w.5,702)"/>
   </dialogueact>
   <dialogueact nite:id="Bmr008.F.dialogueact589" starttime="1148.41" endtime="1148.81" type="s.%-" original-type="s.%-" channel="c8" participant="fe008">
      <nite:child href="Bmr008.F.words.xml#id(Bmr008.w.5,804)..id(Bmr008.w.5,808)"/>
   </dialogueact>
   <dialogueact nite:id="Bmr008.F.dialogueact606" starttime="1186.97" endtime="1187.94" type="s" original-type="s" channel="c8" participant="fe008">
      <nite:child href="Bmr008.F.words.xml#id(Bmr008.w.5,981)..id(Bmr008.w.5,985)"/>
   </dialogueact>
   <dialogueact nite:id="Bmr008.F.dialogueact617" starttime="1230.67" endtime="1231.12" type="b" original-type="b" channel="c8" participant="fe008">
      <nite:child href="Bmr008.F.words.xml#id(Bmr008.w.6,151)..id(Bmr008.w.6,154)"/>
   </dialogueact>
   <dialogueact nite:id="Bmr008.F.dialogueact618" starttime="1234.81" endtime="1234.93" type="b" original-type="b" channel="c8" participant="fe008">
      <nite:child href="Bmr008.F.words.xml#id(Bmr008.w.6,167)..id(Bmr008.w.6,168)"/>
   </dialogueact>
   <dialogueact nite:id="Bmr008.F.dialogueact619" starttime="1235.35" endtime="1240.86" type="s^e^na" adjacency="2b.3a.4a" original-type="s^e^na" channel="c8" participant="fe008">
      <nite:child href="Bmr008.F.words.xml#id(Bmr008.w.6,169)..id(Bmr008.w.6,193)"/>
   </dialogueact>
   <dialogueact nite:id="Bmr008.F.dialogueact624" starttime="1244.92" endtime="1246.16" type="s.%--" adjacency="6b" original-type="s.%--" channel="c8" participant="fe008">
      <nite:child href="Bmr008.F.words.xml#id(Bmr008.w.6,226)..id(Bmr008.disfmarker.264)"/>
   </dialogueact>
   <dialogueact nite:id="Bmr008.F.dialogueact625" starttime="1246.16" endtime="1248.03" comment="quote: &quot;native speaker category&quot; and the other categories" type="s" original-type="s" channel="c8" participant="fe008">
      <nite:child href="Bmr008.F.words.xml#id(Bmr008.w.6,233)..id(Bmr008.w.6,241)"/>
   </dialogueact>
   <dialogueact nite:id="Bmr008.F.dialogueact626" starttime="1248.32" endtime="1252.36" type="s" adjacency="7a" original-type="s" channel="c8" participant="fe008">
      <nite:child href="Bmr008.F.words.xml#id(Bmr008.w.6,242)..id(Bmr008.w.6,259)"/>
   </dialogueact>
   <dialogueact nite:id="Bmr008.F.dialogueact627" starttime="1252.66" endtime="1257.53" type="s" adjacency="7a+" original-type="s" channel="c8" participant="fe008">
      <nite:child href="Bmr008.F.words.xml#id(Bmr008.w.6,260)..id(Bmr008.w.6,277)"/>
   </dialogueact>
   <dialogueact nite:id="Bmr008.F.dialogueact629" starttime="1257.84" endtime="1263.83" type="s" original-type="s" channel="c8" participant="fe008">
      <nite:child href="Bmr008.F.words.xml#id(Bmr008.w.6,285)..id(Bmr008.w.6,314)"/>
   </dialogueact>
   <dialogueact nite:id="Bmr008.F.dialogueact631" starttime="1263.83" endtime="1269.34" type="s^rt" original-type="s^rt" channel="c8" participant="fe008">
      <nite:child href="Bmr008.F.words.xml#id(Bmr008.w.6,319)..id(Bmr008.w.6,341)"/>
   </dialogueact>
   <dialogueact nite:id="Bmr008.F.dialogueact632" starttime="1269.69" endtime="1272.14" type="s^rt" original-type="s^rt" channel="c8" participant="fe008">
      <nite:child href="Bmr008.F.words.xml#id(Bmr008.w.6,342)..id(Bmr008.w.6,354)"/>
   </dialogueact>
   <dialogueact nite:id="Bmr008.F.dialogueact633" starttime="1272.14" endtime="1280.16" type="s" original-type="s" channel="c8" participant="fe008">
      <nite:child href="Bmr008.F.words.xml#id(Bmr008.w.6,355)..id(Bmr008.w.6,394)"/>
   </dialogueact>
   <dialogueact nite:id="Bmr008.F.dialogueact638" starttime="1294.4" endtime="1299.04" type="s^ng" adjacency="8b" original-type="s^ng" channel="c8" participant="fe008">
      <nite:child href="Bmr008.F.words.xml#id(Bmr008.w.6,452)..id(Bmr008.w.6,489)"/>
   </dialogueact>
   <dialogueact nite:id="Bmr008.F.dialogueact641" starttime="1299.04" endtime="1301.92" type="s^df" original-type="s^df" channel="c8" participant="fe008">
      <nite:child href="Bmr008.F.words.xml#id(Bmr008.w.6,490)..id(Bmr008.w.6,498)"/>
   </dialogueact>
   <dialogueact nite:id="Bmr008.F.dialogueact643" starttime="1302.18" endtime="1311.08" type="s^df" adjacency="9a" original-type="s^df" channel="c8" participant="fe008">
      <nite:child href="Bmr008.F.words.xml#id(Bmr008.w.6,503)..id(Bmr008.w.6,541)"/>
   </dialogueact>
   <dialogueact nite:id="Bmr008.F.dialogueact644" starttime="1311.08" endtime="1314.85" type="s.%--" adjacency="9a+" original-type="s.%--" channel="c8" participant="fe008">
      <nite:child href="Bmr008.F.words.xml#id(Bmr008.w.6,542)..id(Bmr008.disfmarker.274)"/>
   </dialogueact>
   <dialogueact nite:id="Bmr008.F.dialogueact648" starttime="1317.91" endtime="1318.27" type="b" original-type="b" channel="c8" participant="fe008">
      <nite:child href="Bmr008.F.words.xml#id(Bmr008.w.6,598)..id(Bmr008.w.6,601)"/>
   </dialogueact>
   <dialogueact nite:id="Bmr008.F.dialogueact650" starttime="1322.14" endtime="1322.46" type="s^aa" adjacency="10b" original-type="s^aa" channel="c8" participant="fe008">
      <nite:child href="Bmr008.F.words.xml#id(Bmr008.w.6,602)..id(Bmr008.w.6,605)"/>
   </dialogueact>
   <dialogueact nite:id="Bmr008.F.dialogueact660" starttime="1368.26" endtime="1373.76" type="s" adjacency="1b" original-type="s" channel="c8" participant="fe008">
      <nite:child href="Bmr008.F.words.xml#id(Bmr008.w.6,779)..id(Bmr008.w.6,807)"/>
   </dialogueact>
   <dialogueact nite:id="Bmr008.F.dialogueact661" starttime="1373.76" endtime="1375.94" comment="start 22:54" type="s" original-type="s" channel="c8" participant="fe008">
      <nite:child href="Bmr008.F.words.xml#id(Bmr008.w.6,808)..id(Bmr008.w.6,821)"/>
   </dialogueact>
   <dialogueact nite:id="Bmr008.F.dialogueact662" starttime="1375.94" endtime="1384.3" type="s^cs" adjacency="2a" original-type="s^cs" channel="c8" participant="fe008">
      <nite:child href="Bmr008.F.words.xml#id(Bmr008.w.6,822)..id(Bmr008.w.6,853)"/>
   </dialogueact>
   <dialogueact nite:id="Bmr008.F.dialogueact663" starttime="1384.87" endtime="1388.77" type="s^cs" original-type="s^cs" channel="c8" participant="fe008">
      <nite:child href="Bmr008.F.words.xml#id(Bmr008.w.6,854)..id(Bmr008.w.6,882)"/>
   </dialogueact>
   <dialogueact nite:id="Bmr008.F.dialogueact666" starttime="1388.77" endtime="1390.53" type="s" original-type="s" channel="c8" participant="fe008">
      <nite:child href="Bmr008.F.words.xml#id(Bmr008.w.6,883)..id(Bmr008.w.6,896)"/>
   </dialogueact>
   <dialogueact nite:id="Bmr008.F.dialogueact667" starttime="1390.53" endtime="1391.53" type="s" original-type="s" channel="c8" participant="fe008">
      <nite:child href="Bmr008.F.words.xml#id(Bmr008.w.6,897)..id(Bmr008.w.6,903)"/>
   </dialogueact>
   <dialogueact nite:id="Bmr008.F.dialogueact668" starttime="1391.6" endtime="1393.52" type="s" original-type="s" channel="c8" participant="fe008">
      <nite:child href="Bmr008.F.words.xml#id(Bmr008.w.6,904)..id(Bmr008.w.6,913)"/>
   </dialogueact>
   <dialogueact nite:id="Bmr008.F.dialogueact670" starttime="1393.52" endtime="1396.84" type="s^cs^rt" original-type="s^cs^rt" channel="c8" participant="fe008">
      <nite:child href="Bmr008.F.words.xml#id(Bmr008.w.6,916)..id(Bmr008.w.6,931)"/>
   </dialogueact>
   <dialogueact nite:id="Bmr008.F.dialogueact671" starttime="1397.26" endtime="1399.29" type="s" original-type="s" channel="c8" participant="fe008">
      <nite:child href="Bmr008.F.words.xml#id(Bmr008.w.6,932)..id(Bmr008.w.6,939)"/>
   </dialogueact>
   <dialogueact nite:id="Bmr008.F.dialogueact672" starttime="1399.29" endtime="1401.27" type="s^no" original-type="s^no" channel="c8" participant="fe008">
      <nite:child href="Bmr008.F.words.xml#id(Bmr008.w.6,940)..id(Bmr008.w.6,952)"/>
   </dialogueact>
   <dialogueact nite:id="Bmr008.F.dialogueact674" starttime="1401.76" endtime="1407.83" type="s" original-type="s" channel="c8" participant="fe008">
      <nite:child href="Bmr008.F.words.xml#id(Bmr008.w.6,957)..id(Bmr008.w.6,982)"/>
   </dialogueact>
   <dialogueact nite:id="Bmr008.F.dialogueact682" starttime="1428.53" endtime="1428.92" type="s^ba" original-type="sj^ba" channel="c8" participant="fe008">
      <nite:child href="Bmr008.F.words.xml#id(Bmr008.w.7,082)..id(Bmr008.w.7,087)"/>
   </dialogueact>
   <dialogueact nite:id="Bmr008.F.dialogueact687" starttime="1442.44" endtime="1443.17" type="s^e" adjacency="6b.7a" original-type="s^e" channel="c8" participant="fe008">
      <nite:child href="Bmr008.F.words.xml#id(Bmr008.w.7,141)..id(Bmr008.w.7,144)"/>
   </dialogueact>
   <dialogueact nite:id="Bmr008.F.dialogueact690" starttime="1446.8" endtime="1447.68" type="s" original-type="s" channel="c8" participant="fe008">
      <nite:child href="Bmr008.F.words.xml#id(Bmr008.w.7,161)..id(Bmr008.w.7,166)"/>
   </dialogueact>
   <dialogueact nite:id="Bmr008.F.dialogueact693" starttime="1451.12" endtime="1453.46" type="s^nd" adjacency="8b" original-type="s^nd" channel="c8" participant="fe008">
      <nite:child href="Bmr008.F.words.xml#id(Bmr008.w.7,190)..id(Bmr008.w.7,203)"/>
   </dialogueact>
   <dialogueact nite:id="Bmr008.F.dialogueact695" starttime="1453.46" endtime="1454.87" type="s^ba" original-type="sj^ba" channel="c8" participant="fe008">
      <nite:child href="Bmr008.F.words.xml#id(Bmr008.w.7,204)..id(Bmr008.w.7,215)"/>
   </dialogueact>
   <dialogueact nite:id="Bmr008.F.dialogueact696" starttime="1454.87" endtime="1455.95" type="s^cs" original-type="s^cs" channel="c8" participant="fe008">
      <nite:child href="Bmr008.F.words.xml#id(Bmr008.w.7,216)..id(Bmr008.w.7,223)"/>
   </dialogueact>
   <dialogueact nite:id="Bmr008.F.dialogueact697" starttime="1455.95" endtime="1457.83" comment="quotes: &quot;among your peers&quot;" type="s^cs" original-type="s^cs" channel="c8" participant="fe008">
      <nite:child href="Bmr008.F.words.xml#id(Bmr008.w.7,224)..id(Bmr008.w.7,234)"/>
   </dialogueact>
   <dialogueact nite:id="Bmr008.F.dialogueact698" starttime="1458.02" endtime="1458.24" type="s^f" original-type="s^f" channel="c8" participant="fe008">
      <nite:child href="Bmr008.F.words.xml#id(Bmr008.w.7,235)..id(Bmr008.w.7,237)"/>
   </dialogueact>
   <dialogueact nite:id="Bmr008.F.dialogueact700" starttime="1458.51" endtime="1459.64" type="s^e" original-type="s^e" channel="c8" participant="fe008">
      <nite:child href="Bmr008.F.words.xml#id(Bmr008.w.7,260)..id(Bmr008.w.7,264)"/>
   </dialogueact>
   <dialogueact nite:id="Bmr008.F.dialogueact715" starttime="1500.28" endtime="1501.02" type="s^aa" adjacency="3b-2" original-type="s^aa" channel="c8" participant="fe008">
      <nite:child href="Bmr008.F.words.xml#id(Bmr008.w.7,446)..id(Bmr008.w.7,451)"/>
   </dialogueact>
   <dialogueact nite:id="Bmr008.F.dialogueact720" starttime="1502.02" endtime="1502.28" type="s.%-" original-type="s.%-" channel="c8" participant="fe008">
      <nite:child href="Bmr008.F.words.xml#id(Bmr008.w.7,476)..id(Bmr008.disfmarker.305)"/>
   </dialogueact>
   <dialogueact nite:id="Bmr008.F.dialogueact721" starttime="1508.01" endtime="1511.72" type="s" adjacency="4b.5a" original-type="s" channel="c8" participant="fe008">
      <nite:child href="Bmr008.F.words.xml#id(Bmr008.w.7,494)..id(Bmr008.w.7,512)"/>
   </dialogueact>
   <dialogueact nite:id="Bmr008.F.dialogueact722" starttime="1511.72" endtime="1513.63" type="s" adjacency="4b+.5a+" original-type="s" channel="c8" participant="fe008">
      <nite:child href="Bmr008.F.words.xml#id(Bmr008.w.7,513)..id(Bmr008.w.7,526)"/>
   </dialogueact>
   <dialogueact nite:id="Bmr008.F.dialogueact726" starttime="1514.62" endtime="1514.96" type="s^bk^m" adjacency="6b" original-type="s^bk^m" channel="c8" participant="fe008">
      <nite:child href="Bmr008.F.words.xml#id(Bmr008.w.7,549)..id(Bmr008.w.7,551)"/>
   </dialogueact>
   <dialogueact nite:id="Bmr008.F.dialogueact727" starttime="1515.43" endtime="1515.84" type="s^aa" adjacency="6b+" original-type="s^aa" channel="c8" participant="fe008">
      <nite:child href="Bmr008.F.words.xml#id(Bmr008.w.7,552)..id(Bmr008.w.7,555)"/>
   </dialogueact>
   <dialogueact nite:id="Bmr008.F.dialogueact728" starttime="1516.63" endtime="1517.67" type="s" original-type="s" channel="c8" participant="fe008">
      <nite:child href="Bmr008.F.words.xml#id(Bmr008.w.7,556)..id(Bmr008.w.7,561)"/>
   </dialogueact>
   <dialogueact nite:id="Bmr008.F.dialogueact730" starttime="1518.44" endtime="1518.77" type="s^bk" adjacency="7b" original-type="s^bk" channel="c8" participant="fe008">
      <nite:child href="Bmr008.F.words.xml#id(Bmr008.w.7,562)..id(Bmr008.w.7,565)"/>
   </dialogueact>
   <dialogueact nite:id="Bmr008.F.dialogueact738" starttime="1548.09" endtime="1548.28" type="s.%-" original-type="s.%-" channel="c8" participant="fe008">
      <nite:child href="Bmr008.F.words.xml#id(Bmr008.w.7,698)..id(Bmr008.disfmarker.310)"/>
   </dialogueact>
   <dialogueact nite:id="Bmr008.F.dialogueact746" starttime="1557.18" endtime="1558.7" comment="start 25:56" type="s.%--" original-type="s.%--" channel="c8" participant="fe008">
      <nite:child href="Bmr008.F.words.xml#id(Bmr008.w.7,750)..id(Bmr008.w.7,764)"/>
   </dialogueact>
   <dialogueact nite:id="Bmr008.F.dialogueact747" starttime="1558.7" endtime="1559.33" type="s^ba" original-type="sj^ba" channel="c8" participant="fe008">
      <nite:child href="Bmr008.F.words.xml#id(Bmr008.w.7,765)..id(Bmr008.w.7,770)"/>
   </dialogueact>
   <dialogueact nite:id="Bmr008.F.dialogueact748" starttime="1559.33" endtime="1563.0" comment="start 25:59" type="s.%--" adjacency="11a" original-type="s.%--" channel="c8" participant="fe008">
      <nite:child href="Bmr008.F.words.xml#id(Bmr008.w.7,771)..id(Bmr008.w.7,789)"/>
   </dialogueact>
   <dialogueact nite:id="Bmr008.F.dialogueact749" starttime="1563.56" endtime="1565.25" comment="start 26:04" type="s" adjacency="11a+" original-type="s" channel="c8" participant="fe008">
      <nite:child href="Bmr008.F.words.xml#id(Bmr008.w.7,790)..id(Bmr008.w.7,798)"/>
   </dialogueact>
   <dialogueact nite:id="Bmr008.F.dialogueact750" starttime="1565.25" endtime="1569.11" comment="start 26:05" type="s.%-" adjacency="11a++" original-type="s.%-" channel="c8" participant="fe008">
      <nite:child href="Bmr008.F.words.xml#id(Bmr008.w.7,799)..id(Bmr008.disfmarker.316)"/>
   </dialogueact>
   <dialogueact nite:id="Bmr008.F.dialogueact759" starttime="1593.78" endtime="1593.99" type="b" original-type="b" channel="c8" participant="fe008">
      <nite:child href="Bmr008.F.words.xml#id(Bmr008.w.7,923)..id(Bmr008.w.7,926)"/>
   </dialogueact>
   <dialogueact nite:id="Bmr008.F.dialogueact761" starttime="1594.13" endtime="1594.48" type="s^ba^t1" original-type="sj^ba^t1" channel="c8" participant="fe008">
      <nite:child href="Bmr008.F.words.xml#id(Bmr008.w.7,927)..id(Bmr008.w.7,928)"/>
   </dialogueact>
   <dialogueact nite:id="Bmr008.F.dialogueact766" starttime="1603.46" endtime="1603.77" type="b" original-type="b" channel="c8" participant="fe008">
      <nite:child href="Bmr008.F.words.xml#id(Bmr008.w.7,975)..id(Bmr008.w.7,978)"/>
   </dialogueact>
   <dialogueact nite:id="Bmr008.F.dialogueact768" starttime="1608.0" endtime="1611.24" type="s" adjacency="14b" original-type="s" channel="c8" participant="fe008">
      <nite:child href="Bmr008.F.words.xml#id(Bmr008.w.7,984)..id(Bmr008.w.8,028)"/>
   </dialogueact>
   <dialogueact nite:id="Bmr008.F.dialogueact772" starttime="1614.7" endtime="1615.07" comment="It sort of seems like Jane uses &quot;interesting&quot; as a continuer/backchannel." type="b" original-type="b" channel="c8" participant="fe008">
      <nite:child href="Bmr008.F.words.xml#id(Bmr008.w.8,031)..id(Bmr008.w.8,032)"/>
   </dialogueact>
   <dialogueact nite:id="Bmr008.F.dialogueact793" starttime="1667.85" endtime="1668.25" type="b" original-type="b" channel="c8" participant="fe008">
      <nite:child href="Bmr008.F.words.xml#id(Bmr008.w.8,259)..id(Bmr008.w.8,262)"/>
   </dialogueact>
   <dialogueact nite:id="Bmr008.F.dialogueact810" starttime="1690.12" endtime="1690.29" type="fg" original-type="fg" channel="c8" participant="fe008">
      <nite:child href="Bmr008.F.words.xml#id(Bmr008.w.8,390)..id(Bmr008.disfmarker.334)"/>
   </dialogueact>
   <dialogueact nite:id="Bmr008.F.dialogueact811" starttime="1690.78" endtime="1691.12" type="b" original-type="b" channel="c8" participant="fe008">
      <nite:child href="Bmr008.F.words.xml#id(Bmr008.w.8,391)..id(Bmr008.w.8,394)"/>
   </dialogueact>
   <dialogueact nite:id="Bmr008.F.dialogueact815" starttime="1696.47" endtime="1699.94" type="s^df" adjacency="7b.8a" original-type="s^df" channel="c8" participant="fe008">
      <nite:child href="Bmr008.F.words.xml#id(Bmr008.w.8,416)..id(Bmr008.w.8,444)"/>
   </dialogueact>
   <dialogueact nite:id="Bmr008.F.dialogueact816" starttime="1700.03" endtime="1703.72" type="s^df^e" adjacency="8b.9a" original-type="s^df^e" channel="c8" participant="fe008">
      <nite:child href="Bmr008.F.words.xml#id(Bmr008.w.8,445)..id(Bmr008.w.8,460)"/>
   </dialogueact>
   <dialogueact nite:id="Bmr008.F.dialogueact817" starttime="1704.29" endtime="1704.43" type="s^f" original-type="s^f" channel="c8" participant="fe008">
      <nite:child href="Bmr008.F.words.xml#id(Bmr008.w.8,461)..id(Bmr008.w.8,463)"/>
   </dialogueact>
   <dialogueact nite:id="Bmr008.F.dialogueact818" starttime="1704.43" endtime="1710.17" type="s^e" original-type="s^e" channel="c8" participant="fe008">
      <nite:child href="Bmr008.F.words.xml#id(Bmr008.w.8,464)..id(Bmr008.w.8,494)"/>
   </dialogueact>
   <dialogueact nite:id="Bmr008.F.dialogueact821" starttime="1710.17" endtime="1716.83" type="s" original-type="s" channel="c8" participant="fe008">
      <nite:child href="Bmr008.F.words.xml#id(Bmr008.w.8,495)..id(Bmr008.w.8,525)"/>
   </dialogueact>
   <dialogueact nite:id="Bmr008.F.dialogueact823" starttime="1716.83" endtime="1722.3" comment="quotes: &quot;american&quot; &quot;british&quot;" type="s^rt" original-type="s^rt" channel="c8" participant="fe008">
      <nite:child href="Bmr008.F.words.xml#id(Bmr008.w.8,526)..id(Bmr008.w.8,542)"/>
   </dialogueact>
   <dialogueact nite:id="Bmr008.F.dialogueact824" starttime="1722.74" endtime="1725.57" type="s" original-type="s" channel="c8" participant="fe008">
      <nite:child href="Bmr008.F.words.xml#id(Bmr008.w.8,543)..id(Bmr008.w.8,557)"/>
   </dialogueact>
   <dialogueact nite:id="Bmr008.F.dialogueact825" starttime="1725.57" endtime="1737.13" type="s.%--" original-type="s.%--" channel="c8" participant="fe008">
      <nite:child href="Bmr008.F.words.xml#id(Bmr008.w.8,558)..id(Bmr008.disfmarker.341)"/>
   </dialogueact>
   <dialogueact nite:id="Bmr008.F.dialogueact826" starttime="1740.11" endtime="1741.19" type="s.%--" original-type="s.%--" channel="c8" participant="fe008">
      <nite:child href="Bmr008.F.words.xml#id(Bmr008.w.8,596)..id(Bmr008.disfmarker.343)"/>
   </dialogueact>
   <dialogueact nite:id="Bmr008.F.dialogueact828" starttime="1741.19" endtime="1741.54" type="s^f" original-type="s^f" channel="c8" participant="fe008">
      <nite:child href="Bmr008.F.words.xml#id(Bmr008.w.8,603)..id(Bmr008.w.8,605)"/>
   </dialogueact>
   <dialogueact nite:id="Bmr008.F.dialogueact829" starttime="1741.62" endtime="1743.96" comment="quotes: region with respect to time frame" type="s^cs" original-type="s^cs" channel="c8" participant="fe008">
      <nite:child href="Bmr008.F.words.xml#id(Bmr008.w.8,606)..id(Bmr008.w.8,620)"/>
   </dialogueact>
   <dialogueact nite:id="Bmr008.F.dialogueact830" starttime="1746.59" endtime="1747.2" comment="quotes: whole utt" type="s^cs:qw" adjacency="10a" original-type="s^cs:qw" channel="c8" participant="fe008">
      <nite:child href="Bmr008.F.words.xml#id(Bmr008.w.8,624)..id(Bmr008.w.8,630)"/>
   </dialogueact>
   <dialogueact nite:id="Bmr008.F.dialogueact831" starttime="1747.2" endtime="1747.71" type="s" original-type="s" channel="c8" participant="fe008">
      <nite:child href="Bmr008.F.words.xml#id(Bmr008.w.8,631)..id(Bmr008.w.8,637)"/>
   </dialogueact>
   <dialogueact nite:id="Bmr008.F.dialogueact832" starttime="1748.0" endtime="1749.52" comment="quote: where did you live" type="s^cs^r:qw" adjacency="10b" original-type="s^cs^r:qw" channel="c8" participant="fe008">
      <nite:child href="Bmr008.F.words.xml#id(Bmr008.w.8,638)..id(Bmr008.w.8,651)"/>
   </dialogueact>
   <dialogueact nite:id="Bmr008.F.dialogueact833" starttime="1749.52" endtime="1751.8" comment="quotes: languages in the home" type="s^cs" original-type="s^cs" channel="c8" participant="fe008">
      <nite:child href="Bmr008.F.words.xml#id(Bmr008.w.8,652)..id(Bmr008.w.8,666)"/>
   </dialogueact>
   <dialogueact nite:id="Bmr008.F.dialogueact834" starttime="1751.8" endtime="1754.44" type="s" original-type="sj" channel="c8" participant="fe008">
      <nite:child href="Bmr008.F.words.xml#id(Bmr008.w.8,667)..id(Bmr008.w.8,680)"/>
   </dialogueact>
   <dialogueact nite:id="Bmr008.F.dialogueact835" starttime="1754.44" endtime="1757.19" comment="I'm not sure if &quot;say&quot; is meant to mean &quot;for example.&quot;  If  this is the case then I think there should be a period after &quot;say.&quot;  If &quot;say&quot; is meant to introduce a suggestion then I think this utterance should not be split and I think there should be quotes around &quot;unbounded&quot;" type="s^cs" original-type="s^cs" channel="c8" participant="fe008">
      <nite:child href="Bmr008.F.words.xml#id(Bmr008.w.8,681)..id(Bmr008.w.8,696)"/>
   </dialogueact>
   <dialogueact nite:id="Bmr008.F.dialogueact837" starttime="1763.15" endtime="1769.73" type="s" adjacency="1b.2a" original-type="s" channel="c8" participant="fe008">
      <nite:child href="Bmr008.F.words.xml#id(Bmr008.w.8,712)..id(Bmr008.w.8,738)"/>
   </dialogueact>
   <dialogueact nite:id="Bmr008.F.dialogueact839" starttime="1769.82" endtime="1785.87" comment="start 29:44" type="s^ba" adjacency="3b" original-type="sj^ba" channel="c8" participant="fe008">
      <nite:child href="Bmr008.F.words.xml#id(Bmr008.w.8,783)..id(Bmr008.w.8,795)"/>
   </dialogueact>
   <dialogueact nite:id="Bmr008.F.dialogueact848" starttime="1795.15" endtime="1795.83" type="s^ba" adjacency="4b" original-type="sj^ba" channel="c8" participant="fe008">
      <nite:child href="Bmr008.F.words.xml#id(Bmr008.w.8,843)..id(Bmr008.w.8,847)"/>
   </dialogueact>
   <dialogueact nite:id="Bmr008.F.dialogueact849" starttime="1796.16" endtime="1798.2" type="s.%-" adjacency="4b+" original-type="s.%-" channel="c8" participant="fe008">
      <nite:child href="Bmr008.F.words.xml#id(Bmr008.w.8,848)..id(Bmr008.disfmarker.350)"/>
   </dialogueact>
   <dialogueact nite:id="Bmr008.F.dialogueact855" starttime="1815.08" endtime="1815.46" type="b" original-type="b" channel="c8" participant="fe008">
      <nite:child href="Bmr008.F.words.xml#id(Bmr008.w.8,914)..id(Bmr008.w.8,917)"/>
   </dialogueact>
   <dialogueact nite:id="Bmr008.F.dialogueact864" starttime="1837.49" endtime="1837.8" type="b^rt" original-type="b^rt" channel="c8" participant="fe008">
      <nite:child href="Bmr008.F.words.xml#id(Bmr008.w.9,024)..id(Bmr008.w.9,027)"/>
   </dialogueact>
   <dialogueact nite:id="Bmr008.F.dialogueact874" starttime="1860.04" endtime="1860.28" type="fg" original-type="fg" channel="c8" participant="fe008">
      <nite:child href="Bmr008.F.words.xml#id(Bmr008.w.9,129)..id(Bmr008.w.9,130)"/>
   </dialogueact>
   <dialogueact nite:id="Bmr008.F.dialogueact875" starttime="1860.62" endtime="1861.16" type="fg|s.%-" original-type="fg|s.%-" channel="c8" participant="fe008">
      <nite:child href="Bmr008.F.words.xml#id(Bmr008.w.9,131)..id(Bmr008.w.9,134)"/>
   </dialogueact>
   <dialogueact nite:id="Bmr008.F.dialogueact876" starttime="1862.01" endtime="1862.17" type="fg" original-type="fg" channel="c8" participant="fe008">
      <nite:child href="Bmr008.F.words.xml#id(Bmr008.w.9,135)..id(Bmr008.w.9,136)"/>
   </dialogueact>
   <dialogueact nite:id="Bmr008.F.dialogueact878" starttime="1862.61" endtime="1865.5" type="s^no" adjacency="8b.9a" original-type="s^no" channel="c8" participant="fe008">
      <nite:child href="Bmr008.F.words.xml#id(Bmr008.w.9,137)..id(Bmr008.w.9,151)"/>
   </dialogueact>
   <dialogueact nite:id="Bmr008.F.dialogueact879" starttime="1865.54" endtime="1865.88" type="s^df.%--" adjacency="8b+.9a+" original-type="s^df.%--" channel="c8" participant="fe008">
      <nite:child href="Bmr008.F.words.xml#id(Bmr008.w.9,152)"/>
   </dialogueact>
   <dialogueact nite:id="Bmr008.F.dialogueact882" starttime="1869.83" endtime="1871.33" type="s" original-type="s" channel="c8" participant="fe008">
      <nite:child href="Bmr008.F.words.xml#id(Bmr008.w.9,177)..id(Bmr008.w.9,185)"/>
   </dialogueact>
   <dialogueact nite:id="Bmr008.F.dialogueact884" starttime="1873.19" endtime="1873.5" type="b" original-type="b" channel="c8" participant="fe008">
      <nite:child href="Bmr008.F.words.xml#id(Bmr008.w.9,200)..id(Bmr008.w.9,203)"/>
   </dialogueact>
   <dialogueact nite:id="Bmr008.F.dialogueact888" starttime="1875.22" endtime="1875.43" type="b" original-type="b" channel="c8" participant="fe008">
      <nite:child href="Bmr008.F.words.xml#id(Bmr008.w.9,226)..id(Bmr008.w.9,227)"/>
   </dialogueact>
   <dialogueact nite:id="Bmr008.F.dialogueact902" starttime="1894.79" endtime="1896.86" type="s" original-type="s" channel="c8" participant="fe008">
      <nite:child href="Bmr008.F.words.xml#id(Bmr008.w.9,324)..id(Bmr008.w.9,335)"/>
   </dialogueact>
   <dialogueact nite:id="Bmr008.F.dialogueact904" starttime="1896.97" endtime="1897.15" type="b" original-type="b" channel="c8" participant="fe008">
      <nite:child href="Bmr008.F.words.xml#id(Bmr008.w.9,336)..id(Bmr008.w.9,337)"/>
   </dialogueact>
   <dialogueact nite:id="Bmr008.F.dialogueact911" starttime="1917.23" endtime="1917.98" type="s^ba" adjacency="4b-1" original-type="sj^ba" channel="c8" participant="fe008">
      <nite:child href="Bmr008.F.words.xml#id(Bmr008.w.9,420)..id(Bmr008.w.9,424)"/>
   </dialogueact>
   <dialogueact nite:id="Bmr008.F.dialogueact918" starttime="1928.99" endtime="1929.2" type="%-" original-type="%-" channel="c8" participant="fe008">
      <nite:child href="Bmr008.F.words.xml#id(Bmr008.w.9,460)..id(Bmr008.disfmarker.365)"/>
   </dialogueact>
   <dialogueact nite:id="Bmr008.F.dialogueact919" starttime="1929.39" endtime="1929.77" type="b" original-type="b" channel="c8" participant="fe008">
      <nite:child href="Bmr008.F.words.xml#id(Bmr008.w.9,472)..id(Bmr008.w.9,475)"/>
   </dialogueact>
   <dialogueact nite:id="Bmr008.F.dialogueact923" starttime="1936.01" endtime="1938.66" type="s" adjacency="9a" original-type="s" channel="c8" participant="fe008">
      <nite:child href="Bmr008.F.words.xml#id(Bmr008.w.9,508)..id(Bmr008.w.9,522)"/>
   </dialogueact>
   <dialogueact nite:id="Bmr008.F.dialogueact928" starttime="1948.18" endtime="1957.01" type="s" original-type="s" channel="c8" participant="fe008">
      <nite:child href="Bmr008.F.words.xml#id(Bmr008.w.9,560)..id(Bmr008.w.9,607)"/>
   </dialogueact>
   <dialogueact nite:id="Bmr008.F.dialogueact934" starttime="1958.44" endtime="1960.86" type="s.%--" adjacency="10b-3" original-type="s.%--" channel="c8" participant="fe008">
      <nite:child href="Bmr008.F.words.xml#id(Bmr008.w.9,618)..id(Bmr008.disfmarker.369)"/>
   </dialogueact>
   <dialogueact nite:id="Bmr008.F.dialogueact949" starttime="1979.03" endtime="1979.42" type="s^aa" adjacency="3b" original-type="s^aa" channel="c8" participant="fe008">
      <nite:child href="Bmr008.F.words.xml#id(Bmr008.w.9,728)..id(Bmr008.w.9,730)"/>
   </dialogueact>
   <dialogueact nite:id="Bmr008.F.dialogueact960" starttime="1992.65" endtime="1994.75" type="s.%-" original-type="s.%-" channel="c8" participant="fe008">
      <nite:child href="Bmr008.F.words.xml#id(Bmr008.w.9,816)..id(Bmr008.disfmarker.383)"/>
   </dialogueact>
   <dialogueact nite:id="Bmr008.F.dialogueact961" starttime="1994.75" endtime="1997.75" type="s^cs" original-type="sj^cs" channel="c8" participant="fe008">
      <nite:child href="Bmr008.F.words.xml#id(Bmr008.w.9,829)..id(Bmr008.w.9,842)"/>
   </dialogueact>
   <dialogueact nite:id="Bmr008.F.dialogueact964" starttime="1997.75" endtime="1999.43" comment="quotes: whole utt" type="s^cs:qw" original-type="s^cs:qw" channel="c8" participant="fe008">
      <nite:child href="Bmr008.F.words.xml#id(Bmr008.w.9,843)..id(Bmr008.w.9,852)"/>
   </dialogueact>
   <dialogueact nite:id="Bmr008.F.dialogueact965" starttime="1999.43" endtime="2004.09" type="s^cs:qrr" original-type="s^cs:qrr" channel="c8" participant="fe008">
      <nite:child href="Bmr008.F.words.xml#id(Bmr008.w.9,853)..id(Bmr008.w.9,877)"/>
   </dialogueact>
   <dialogueact nite:id="Bmr008.F.dialogueact966" starttime="2004.42" endtime="2005.98" type="s.%--" original-type="sj.%--" channel="c8" participant="fe008">
      <nite:child href="Bmr008.F.words.xml#id(Bmr008.w.9,878)..id(Bmr008.disfmarker.387)"/>
   </dialogueact>
   <dialogueact nite:id="Bmr008.F.dialogueact967" starttime="2006.71" endtime="2009.21" type="s.%-" original-type="sj.%-" channel="c8" participant="fe008">
      <nite:child href="Bmr008.F.words.xml#id(Bmr008.w.9,885)..id(Bmr008.disfmarker.388)"/>
   </dialogueact>
   <dialogueact nite:id="Bmr008.F.dialogueact974" starttime="2023.89" endtime="2024.42" type="s^ba" adjacency="9b-2" original-type="sj^ba" channel="c8" participant="fe008">
      <nite:child href="Bmr008.F.words.xml#id(Bmr008.w.9,963)..id(Bmr008.w.9,967)"/>
   </dialogueact>
   <dialogueact nite:id="Bmr008.F.dialogueact987" starttime="2032.53" endtime="2033.01" type="s^ba" original-type="sj^ba" channel="c8" participant="fe008">
      <nite:child href="Bmr008.F.words.xml#id(Bmr008.w.10,011)..id(Bmr008.w.10,016)"/>
   </dialogueact>
   <dialogueact nite:id="Bmr008.F.dialogueact988" starttime="2034.0" endtime="2034.35" type="s^ba^r" original-type="sj^ba^r" channel="c8" participant="fe008">
      <nite:child href="Bmr008.F.words.xml#id(Bmr008.w.10,017)..id(Bmr008.w.10,020)"/>
   </dialogueact>
   <dialogueact nite:id="Bmr008.F.dialogueact989" starttime="2036.39" endtime="2039.4" type="s^ba" adjacency="3a" original-type="sj^ba" channel="c8" participant="fe008">
      <nite:child href="Bmr008.F.words.xml#id(Bmr008.w.10,021)..id(Bmr008.w.10,039)"/>
   </dialogueact>
   <dialogueact nite:id="Bmr008.F.dialogueact991" starttime="2039.4" endtime="2042.99" type="s^arp^rt" original-type="s^arp^rt" channel="c8" participant="fe008">
      <nite:child href="Bmr008.F.words.xml#id(Bmr008.w.10,040)..id(Bmr008.w.10,057)"/>
   </dialogueact>
   <dialogueact nite:id="Bmr008.F.dialogueact992" starttime="2042.99" endtime="2047.63" type="s^aap^ba" original-type="sj^aap^ba" channel="c8" participant="fe008">
      <nite:child href="Bmr008.F.words.xml#id(Bmr008.w.10,058)..id(Bmr008.w.10,101)"/>
   </dialogueact>
   <dialogueact nite:id="Bmr008.F.dialogueact995" starttime="2050.43" endtime="2051.14" type="s^aa^rt" adjacency="4b" original-type="s^aa^rt" channel="c8" participant="fe008">
      <nite:child href="Bmr008.F.words.xml#id(Bmr008.w.10,102)..id(Bmr008.w.10,106)"/>
   </dialogueact>
   <dialogueact nite:id="Bmr008.F.dialogueact996" starttime="2051.3" endtime="2053.83" type="fg|s.%--" original-type="fg|s.%--" channel="c8" participant="fe008">
      <nite:child href="Bmr008.F.words.xml#id(Bmr008.w.10,107)..id(Bmr008.disfmarker.398)"/>
   </dialogueact>
   <dialogueact nite:id="Bmr008.F.dialogueact1008" starttime="2068.93" endtime="2071.49" type="s^arp" adjacency="6b.7a" original-type="s^arp" channel="c8" participant="fe008">
      <nite:child href="Bmr008.F.words.xml#id(Bmr008.w.10,217)..id(Bmr008.w.10,225)"/>
   </dialogueact>
   <dialogueact nite:id="Bmr008.F.dialogueact1010" starttime="2071.49" endtime="2075.97" type="s^rt" adjacency="8a" original-type="s^rt" channel="c8" participant="fe008">
      <nite:child href="Bmr008.F.words.xml#id(Bmr008.w.10,226)..id(Bmr008.w.10,245)"/>
   </dialogueact>
   <dialogueact nite:id="Bmr008.F.dialogueact1011" starttime="2075.97" endtime="2079.88" type="s.%--" original-type="s.%--" channel="c8" participant="fe008">
      <nite:child href="Bmr008.F.words.xml#id(Bmr008.w.10,246)..id(Bmr008.disfmarker.403)"/>
   </dialogueact>
   <dialogueact nite:id="Bmr008.F.dialogueact1013" starttime="2079.88" endtime="2081.11" type="s.%--" original-type="s.%--" channel="c8" participant="fe008">
      <nite:child href="Bmr008.F.words.xml#id(Bmr008.w.10,265)..id(Bmr008.disfmarker.405)"/>
   </dialogueact>
   <dialogueact nite:id="Bmr008.F.dialogueact1014" starttime="2081.52" endtime="2083.95" type="s" original-type="s" channel="c8" participant="fe008">
      <nite:child href="Bmr008.F.words.xml#id(Bmr008.w.10,273)..id(Bmr008.w.10,284)"/>
   </dialogueact>
   <dialogueact nite:id="Bmr008.F.dialogueact1027" starttime="2112.88" endtime="2114.53" type="qw" adjacency="3b.4a" original-type="qw" channel="c8" participant="fe008">
      <nite:child href="Bmr008.F.words.xml#id(Bmr008.w.10,406)..id(Bmr008.w.10,413)"/>
   </dialogueact>
   <dialogueact nite:id="Bmr008.F.dialogueact1028" starttime="2114.53" endtime="2116.17" type="qw^e" adjacency="3b+.4a+" original-type="qw^e" channel="c8" participant="fe008">
      <nite:child href="Bmr008.F.words.xml#id(Bmr008.w.10,414)..id(Bmr008.w.10,424)"/>
   </dialogueact>
   <dialogueact nite:id="Bmr008.F.dialogueact1030" starttime="2118.1" endtime="2118.89" type="s^bk" adjacency="5b-1" original-type="s^bk" channel="c8" participant="fe008">
      <nite:child href="Bmr008.F.words.xml#id(Bmr008.w.10,435)..id(Bmr008.w.10,439)"/>
   </dialogueact>
   <dialogueact nite:id="Bmr008.F.dialogueact1031" starttime="2119.69" endtime="2120.67" type="qw" original-type="qw" channel="c8" participant="fe008">
      <nite:child href="Bmr008.F.words.xml#id(Bmr008.w.10,440)..id(Bmr008.w.10,445)"/>
   </dialogueact>
   <dialogueact nite:id="Bmr008.F.dialogueact1037" starttime="2131.07" endtime="2131.41" type="s^bk" adjacency="8b" original-type="s^bk" channel="c8" participant="fe008">
      <nite:child href="Bmr008.F.words.xml#id(Bmr008.w.10,493)..id(Bmr008.w.10,495)"/>
   </dialogueact>
   <dialogueact nite:id="Bmr008.F.dialogueact1039" starttime="2133.2" endtime="2134.64" type="%-" original-type="%-" channel="c8" participant="fe008">
      <nite:child href="Bmr008.F.words.xml#id(Bmr008.w.10,497)..id(Bmr008.disfmarker.413)"/>
   </dialogueact>
   <dialogueact nite:id="Bmr008.F.dialogueact1042" starttime="2136.41" endtime="2140.79" type="s^ba^nd" adjacency="9b.10a" original-type="sj^ba^nd" channel="c8" participant="fe008">
      <nite:child href="Bmr008.F.words.xml#id(Bmr008.w.10,519)..id(Bmr008.w.10,542)"/>
   </dialogueact>
   <dialogueact nite:id="Bmr008.F.dialogueact1043" starttime="2140.92" endtime="2147.01" type="s^aa^rt" adjacency="1b-2" original-type="s^aa^rt" channel="c8" participant="fe008">
      <nite:child href="Bmr008.F.words.xml#id(Bmr008.w.10,566)..id(Bmr008.w.10,573)"/>
   </dialogueact>
   <dialogueact nite:id="Bmr008.F.dialogueact1047" starttime="2147.45" endtime="2147.62" type="b.%" original-type="b.%" channel="c8" participant="fe008">
      <nite:child href="Bmr008.F.words.xml#id(Bmr008.w.10,589)..id(Bmr008.w.10,590)"/>
   </dialogueact>
   <dialogueact nite:id="Bmr008.F.dialogueact1054" starttime="2161.99" endtime="2162.52" type="s^ba" original-type="sj^ba" channel="c8" participant="fe008">
      <nite:child href="Bmr008.F.words.xml#id(Bmr008.w.10,653)..id(Bmr008.w.10,656)"/>
   </dialogueact>
   <dialogueact nite:id="Bmr008.F.dialogueact1056" starttime="2163.64" endtime="2164.01" type="s^ba" adjacency="3b-1" original-type="sj^ba" channel="c8" participant="fe008">
      <nite:child href="Bmr008.F.words.xml#id(Bmr008.w.10,666)..id(Bmr008.w.10,668)"/>
   </dialogueact>
   <dialogueact nite:id="Bmr008.F.dialogueact1059" starttime="2165.17" endtime="2166.56" type="s^ng" adjacency="3b-2" original-type="s^ng" channel="c8" participant="fe008">
      <nite:child href="Bmr008.F.words.xml#id(Bmr008.w.10,687)..id(Bmr008.w.10,693)"/>
   </dialogueact>
   <dialogueact nite:id="Bmr008.F.dialogueact1069" starttime="2172.41" endtime="2172.99" type="s^aa^j" adjacency="4b" original-type="s^aa^j" channel="c8" participant="fe008">
      <nite:child href="Bmr008.F.words.xml#id(Bmr008.w.10,742)..id(Bmr008.w.10,747)"/>
   </dialogueact>
   <dialogueact nite:id="Bmr008.F.dialogueact1070" starttime="2172.99" endtime="2174.31" type="s^cs.%--" adjacency="5a" original-type="s^cs.%--" channel="c8" participant="fe008">
      <nite:child href="Bmr008.F.words.xml#id(Bmr008.w.10,748)..id(Bmr008.w.10,754)"/>
   </dialogueact>
   <dialogueact nite:id="Bmr008.F.dialogueact1071" starttime="2174.86" endtime="2175.1" type="b" original-type="b" channel="c8" participant="fe008">
      <nite:child href="Bmr008.F.words.xml#id(Bmr008.w.10,755)..id(Bmr008.w.10,756)"/>
   </dialogueact>
   <dialogueact nite:id="Bmr008.F.dialogueact1077" starttime="2178.13" endtime="2178.26" type="b.%" original-type="b.%" channel="c8" participant="fe008">
      <nite:child href="Bmr008.F.words.xml#id(Bmr008.w.10,797)..id(Bmr008.w.10,798)"/>
   </dialogueact>
   <dialogueact nite:id="Bmr008.F.dialogueact1079" starttime="2181.77" endtime="2182.42" type="s^ba" adjacency="7b" original-type="sj^ba" channel="c8" participant="fe008">
      <nite:child href="Bmr008.F.words.xml#id(Bmr008.w.10,799)..id(Bmr008.w.10,802)"/>
   </dialogueact>
   <dialogueact nite:id="Bmr008.F.dialogueact1080" starttime="2182.77" endtime="2184.13" type="s^ba" adjacency="7b+" original-type="sj^ba" channel="c8" participant="fe008">
      <nite:child href="Bmr008.F.words.xml#id(Bmr008.w.10,803)..id(Bmr008.w.10,811)"/>
   </dialogueact>
   <dialogueact nite:id="Bmr008.F.dialogueact1081" starttime="2184.33" endtime="2184.91" type="s^ba" adjacency="7b++" original-type="sj^ba" channel="c8" participant="fe008">
      <nite:child href="Bmr008.F.words.xml#id(Bmr008.w.10,812)..id(Bmr008.w.10,815)"/>
   </dialogueact>
   <dialogueact nite:id="Bmr008.F.dialogueact1084" starttime="2195.54" endtime="2195.7" type="b" original-type="b" channel="c8" participant="fe008">
      <nite:child href="Bmr008.F.words.xml#id(Bmr008.w.10,850)..id(Bmr008.w.10,851)"/>
   </dialogueact>
   <dialogueact nite:id="Bmr008.F.dialogueact1086" starttime="2199.33" endtime="2202.87" type="s^cs" adjacency="8b" original-type="s^cs" channel="c8" participant="fe008">
      <nite:child href="Bmr008.F.words.xml#id(Bmr008.w.10,871)..id(Bmr008.w.10,887)"/>
   </dialogueact>
   <dialogueact nite:id="Bmr008.F.dialogueact1087" starttime="2203.15" endtime="2205.12" type="s" original-type="s" channel="c8" participant="fe008">
      <nite:child href="Bmr008.F.words.xml#id(Bmr008.w.10,888)..id(Bmr008.w.10,896)"/>
   </dialogueact>
   <dialogueact nite:id="Bmr008.F.dialogueact1088" starttime="2205.12" endtime="2207.07" type="s" original-type="s" channel="c8" participant="fe008">
      <nite:child href="Bmr008.F.words.xml#id(Bmr008.w.10,897)..id(Bmr008.w.10,905)"/>
   </dialogueact>
   <dialogueact nite:id="Bmr008.F.dialogueact1089" starttime="2207.07" endtime="2209.16" type="qh" original-type="qh" channel="c8" participant="fe008">
      <nite:child href="Bmr008.F.words.xml#id(Bmr008.w.10,906)..id(Bmr008.w.10,918)"/>
   </dialogueact>
   <dialogueact nite:id="Bmr008.F.dialogueact1090" starttime="2209.16" endtime="2216.95" comment="quotes: oh by the way the guy giving the presentation today is the student of the professor who you know ==&quot;" type="s^cs^e.%--" original-type="s^cs^e.%--" channel="c8" participant="fe008">
      <nite:child href="Bmr008.F.words.xml#id(Bmr008.w.10,919)..id(Bmr008.w.10,949)"/>
   </dialogueact>
   <dialogueact nite:id="Bmr008.F.dialogueact1091" starttime="2216.95" endtime="2217.34" type="s" original-type="s" channel="c8" participant="fe008">
      <nite:child href="Bmr008.F.words.xml#id(Bmr008.w.10,950)..id(Bmr008.w.10,952)"/>
   </dialogueact>
   <dialogueact nite:id="Bmr008.F.dialogueact1092" starttime="2217.51" endtime="2222.68" type="s^e" original-type="s^e" channel="c8" participant="fe008">
      <nite:child href="Bmr008.F.words.xml#id(Bmr008.w.10,953)..id(Bmr008.w.10,975)"/>
   </dialogueact>
   <dialogueact nite:id="Bmr008.F.dialogueact1093" starttime="2223.34" endtime="2225.42" comment="FBH quotes: so and so and so and so are married" type="s^e" original-type="s^e" channel="c8" participant="fe008">
      <nite:child href="Bmr008.F.words.xml#id(Bmr008.w.10,976)..id(Bmr008.w.10,998)"/>
   </dialogueact>
   <dialogueact nite:id="Bmr008.F.dialogueact1097" starttime="2229.66" endtime="2231.23" type="s" original-type="s" channel="c8" participant="fe008">
      <nite:child href="Bmr008.F.words.xml#id(Bmr008.w.11,017)..id(Bmr008.w.11,024)"/>
   </dialogueact>
   <dialogueact nite:id="Bmr008.F.dialogueact1098" starttime="2231.23" endtime="2243.24" comment="quotes: oh by the way they're married or ==&quot;" type="s.%--" original-type="s.%--" channel="c8" participant="fe008">
      <nite:child href="Bmr008.F.words.xml#id(Bmr008.w.11,025)..id(Bmr008.disfmarker.434)"/>
   </dialogueact>
   <dialogueact nite:id="Bmr008.F.dialogueact1099" starttime="2244.08" endtime="2245.44" type="s^no" original-type="s^no" channel="c8" participant="fe008">
      <nite:child href="Bmr008.F.words.xml#id(Bmr008.w.11,076)..id(Bmr008.w.11,085)"/>
   </dialogueact>
   <dialogueact nite:id="Bmr008.F.dialogueact1103" starttime="2255.47" endtime="2257.43" type="s" adjacency="9b" original-type="s" channel="c8" participant="fe008">
      <nite:child href="Bmr008.F.words.xml#id(Bmr008.w.11,131)..id(Bmr008.w.11,139)"/>
   </dialogueact>
   <dialogueact nite:id="Bmr008.F.dialogueact1104" starttime="2257.43" endtime="2269.78" type="s" original-type="sj" channel="c8" participant="fe008">
      <nite:child href="Bmr008.F.words.xml#id(Bmr008.w.11,140)..id(Bmr008.w.11,190)"/>
   </dialogueact>
   <dialogueact nite:id="Bmr008.F.dialogueact1107" starttime="2269.78" endtime="2273.68" type="s" adjacency="10a" original-type="sj" channel="c8" participant="fe008">
      <nite:child href="Bmr008.F.words.xml#id(Bmr008.w.11,191)..id(Bmr008.w.11,209)"/>
   </dialogueact>
   <dialogueact nite:id="Bmr008.F.dialogueact1109" starttime="2275.24" endtime="2275.52" type="b" original-type="b" channel="c8" participant="fe008">
      <nite:child href="Bmr008.F.words.xml#id(Bmr008.w.11,220)..id(Bmr008.w.11,221)"/>
   </dialogueact>
   <dialogueact nite:id="Bmr008.F.dialogueact1111" starttime="2281.71" endtime="2282.13" type="b" original-type="b" channel="c8" participant="fe008">
      <nite:child href="Bmr008.F.words.xml#id(Bmr008.w.11,244)..id(Bmr008.w.11,247)"/>
   </dialogueact>
   <dialogueact nite:id="Bmr008.F.dialogueact1114" starttime="2289.51" endtime="2295.84" type="s.%--" adjacency="1b" original-type="s.%--" channel="c8" participant="fe008">
      <nite:child href="Bmr008.F.words.xml#id(Bmr008.w.11,271)..id(Bmr008.disfmarker.441)"/>
   </dialogueact>
   <dialogueact nite:id="Bmr008.F.dialogueact1115" starttime="2296.35" endtime="2297.93" type="s" original-type="s" channel="c8" participant="fe008">
      <nite:child href="Bmr008.F.words.xml#id(Bmr008.w.11,302)..id(Bmr008.w.11,309)"/>
   </dialogueact>
   <dialogueact nite:id="Bmr008.F.dialogueact1116" starttime="2297.93" endtime="2305.91" type="s^e.%--" adjacency="2a" original-type="s^e.%--" channel="c8" participant="fe008">
      <nite:child href="Bmr008.F.words.xml#id(Bmr008.w.11,310)..id(Bmr008.disfmarker.443)"/>
   </dialogueact>
   <dialogueact nite:id="Bmr008.F.dialogueact1117" starttime="2306.4" endtime="2311.11" type="s^e" adjacency="2a+" original-type="s^e" channel="c8" participant="fe008">
      <nite:child href="Bmr008.F.words.xml#id(Bmr008.w.11,350)..id(Bmr008.w.11,375)"/>
   </dialogueact>
   <dialogueact nite:id="Bmr008.F.dialogueact1118" starttime="2311.11" endtime="2316.52" type="s^e" adjacency="2a++" original-type="s^e" channel="c8" participant="fe008">
      <nite:child href="Bmr008.F.words.xml#id(Bmr008.w.11,376)..id(Bmr008.w.11,407)"/>
   </dialogueact>
   <dialogueact nite:id="Bmr008.F.dialogueact1121" starttime="2317.43" endtime="2318.66" type="s^r" adjacency="2a++" original-type="s^r" channel="c8" participant="fe008">
      <nite:child href="Bmr008.F.words.xml#id(Bmr008.w.11,419)..id(Bmr008.w.11,425)"/>
   </dialogueact>
   <dialogueact nite:id="Bmr008.F.dialogueact1122" starttime="2322.49" endtime="2322.82" type="s^ba" original-type="sj^ba" channel="c8" participant="fe008">
      <nite:child href="Bmr008.F.words.xml#id(Bmr008.w.11,437)..id(Bmr008.w.11,438)"/>
   </dialogueact>
   <dialogueact nite:id="Bmr008.F.dialogueact1124" starttime="2328.63" endtime="2334.42" type="s^aa^rt|s.%-" adjacency="3b.4a" original-type="s^aa^rt|s.%-" channel="c8" participant="fe008">
      <nite:child href="Bmr008.F.words.xml#id(Bmr008.w.11,452)..id(Bmr008.disfmarker.448)"/>
   </dialogueact>
   <dialogueact nite:id="Bmr008.F.dialogueact1137" starttime="2369.74" endtime="2370.08" type="b" original-type="b" channel="c8" participant="fe008">
      <nite:child href="Bmr008.F.words.xml#id(Bmr008.w.11,630)..id(Bmr008.w.11,633)"/>
   </dialogueact>
   <dialogueact nite:id="Bmr008.F.dialogueact1151" starttime="2411.95" endtime="2415.2" type="s" adjacency="1b.2a" original-type="s" channel="c8" participant="fe008">
      <nite:child href="Bmr008.F.words.xml#id(Bmr008.w.11,777)..id(Bmr008.w.11,793)"/>
   </dialogueact>
   <dialogueact nite:id="Bmr008.F.dialogueact1152" starttime="2416.16" endtime="2419.19" type="s" adjacency="2a+" original-type="s" channel="c8" participant="fe008">
      <nite:child href="Bmr008.F.words.xml#id(Bmr008.w.11,794)..id(Bmr008.w.11,817)"/>
   </dialogueact>
   <dialogueact nite:id="Bmr008.F.dialogueact1155" starttime="2422.55" endtime="2423.62" type="s^aa" adjacency="3b-2" original-type="s^aa" channel="c8" participant="fe008">
      <nite:child href="Bmr008.F.words.xml#id(Bmr008.w.11,839)..id(Bmr008.w.11,857)"/>
   </dialogueact>
   <dialogueact nite:id="Bmr008.F.dialogueact1182" starttime="2498.56" endtime="2500.34" type="s.%" original-type="s.%" channel="c8" participant="fe008">
      <nite:child href="Bmr008.F.words.xml#id(Bmr008.w.12,204)..id(Bmr008.w.12,213)"/>
   </dialogueact>
   <dialogueact nite:id="Bmr008.F.dialogueact1183" starttime="2500.8" endtime="2502.88" type="s" adjacency="8b.9a" original-type="s" channel="c8" participant="fe008">
      <nite:child href="Bmr008.F.words.xml#id(Bmr008.w.12,214)..id(Bmr008.w.12,224)"/>
   </dialogueact>
   <dialogueact nite:id="Bmr008.F.dialogueact1185" starttime="2503.35" endtime="2503.44" type="%-" original-type="%-" channel="c8" participant="fe008">
      <nite:child href="Bmr008.F.words.xml#id(Bmr008.w.12,236)..id(Bmr008.disfmarker.484)"/>
   </dialogueact>
   <dialogueact nite:id="Bmr008.F.dialogueact1186" starttime="2505.58" endtime="2505.76" type="b" original-type="b" channel="c8" participant="fe008">
      <nite:child href="Bmr008.F.words.xml#id(Bmr008.w.12,239)..id(Bmr008.w.12,240)"/>
   </dialogueact>
   <dialogueact nite:id="Bmr008.F.dialogueact1208" starttime="2553.05" endtime="2553.25" type="%-" original-type="%-" channel="c8" participant="fe008">
      <nite:child href="Bmr008.F.words.xml#id(Bmr008.w.12,498)..id(Bmr008.disfmarker.497)"/>
   </dialogueact>
   <dialogueact nite:id="Bmr008.F.dialogueact1212" starttime="2566.42" endtime="2570.64" type="s" original-type="s" channel="c8" participant="fe008">
      <nite:child href="Bmr008.F.words.xml#id(Bmr008.w.12,551)..id(Bmr008.w.12,570)"/>
   </dialogueact>
   <dialogueact nite:id="Bmr008.F.dialogueact1214" starttime="2570.71" endtime="2576.65" type="s.%-" adjacency="3a" original-type="s.%-" channel="c8" participant="fe008">
      <nite:child href="Bmr008.F.words.xml#id(Bmr008.w.12,571)..id(Bmr008.disfmarker.502)"/>
   </dialogueact>
   <dialogueact nite:id="Bmr008.F.dialogueact1218" starttime="2576.79" endtime="2578.68" type="s" original-type="s" channel="c8" participant="fe008">
      <nite:child href="Bmr008.F.words.xml#id(Bmr008.w.12,609)..id(Bmr008.w.12,620)"/>
   </dialogueact>
   <dialogueact nite:id="Bmr008.F.dialogueact1219" starttime="2579.12" endtime="2586.37" type="s" original-type="s" channel="c8" participant="fe008">
      <nite:child href="Bmr008.F.words.xml#id(Bmr008.w.12,621)..id(Bmr008.w.12,654)"/>
   </dialogueact>
   <dialogueact nite:id="Bmr008.F.dialogueact1220" starttime="2587.05" endtime="2591.94" type="s^cs" original-type="s^cs" channel="c8" participant="fe008">
      <nite:child href="Bmr008.F.words.xml#id(Bmr008.w.12,655)..id(Bmr008.w.12,681)"/>
   </dialogueact>
   <dialogueact nite:id="Bmr008.F.dialogueact1223" starttime="2591.94" endtime="2595.77" type="s^cs" original-type="s^cs" channel="c8" participant="fe008">
      <nite:child href="Bmr008.F.words.xml#id(Bmr008.w.12,682)..id(Bmr008.w.12,700)"/>
   </dialogueact>
   <dialogueact nite:id="Bmr008.F.dialogueact1224" starttime="2595.77" endtime="2610.41" type="s" adjacency="4a" original-type="s" channel="c8" participant="fe008">
      <nite:child href="Bmr008.F.words.xml#id(Bmr008.w.12,701)..id(Bmr008.w.12,759)"/>
   </dialogueact>
   <dialogueact nite:id="Bmr008.F.dialogueact1231" starttime="2620.23" endtime="2620.42" type="%-" original-type="%-" channel="c8" participant="fe008">
      <nite:child href="Bmr008.F.words.xml#id(Bmr008.w.12,813)..id(Bmr008.disfmarker.510)"/>
   </dialogueact>
   <dialogueact nite:id="Bmr008.F.dialogueact1233" starttime="2621.61" endtime="2622.23" type="fg" original-type="fg" channel="c8" participant="fe008">
      <nite:child href="Bmr008.F.words.xml#id(Bmr008.w.12,816)..id(Bmr008.w.12,819)"/>
   </dialogueact>
   <dialogueact nite:id="Bmr008.F.dialogueact1234" starttime="2622.34" endtime="2626.87" type="s" adjacency="7a" original-type="s" channel="c8" participant="fe008">
      <nite:child href="Bmr008.F.words.xml#id(Bmr008.w.12,820)..id(Bmr008.w.12,841)"/>
   </dialogueact>
   <dialogueact nite:id="Bmr008.F.dialogueact1239" starttime="2630.77" endtime="2636.36" comment="FBH" type="s^nd" adjacency="8b.9a" original-type="s^nd" channel="c8" participant="fe008">
      <nite:child href="Bmr008.F.words.xml#id(Bmr008.w.12,867)..id(Bmr008.w.12,908)"/>
   </dialogueact>
   <dialogueact nite:id="Bmr008.F.dialogueact1315" starttime="2790.4" endtime="2790.76" type="b" original-type="b" channel="c8" participant="fe008">
      <nite:child href="Bmr008.F.words.xml#id(Bmr008.w.13,534)..id(Bmr008.w.13,537)"/>
   </dialogueact>
   <dialogueact nite:id="Bmr008.F.dialogueact1390" starttime="3017.16" endtime="3017.79" type="b" original-type="b" channel="c8" participant="fe008">
      <nite:child href="Bmr008.F.words.xml#id(Bmr008.w.14,357)..id(Bmr008.w.14,358)"/>
   </dialogueact>
   <dialogueact nite:id="Bmr008.F.dialogueact1442" starttime="3114.27" endtime="3116.02" type="qw" adjacency="14a" original-type="qw" channel="c8" participant="fe008">
      <nite:child href="Bmr008.F.words.xml#id(Bmr008.w.14,716)..id(Bmr008.w.14,725)"/>
   </dialogueact>
   <dialogueact nite:id="Bmr008.F.dialogueact1444" starttime="3117.91" endtime="3118.37" type="qw.%--" adjacency="15b" original-type="qw.%--" channel="c8" participant="fe008">
      <nite:child href="Bmr008.F.words.xml#id(Bmr008.w.14,728)..id(Bmr008.w.14,730)"/>
   </dialogueact>
   <dialogueact nite:id="Bmr008.F.dialogueact1445" starttime="3118.77" endtime="3119.11" type="fh" original-type="fh" channel="c8" participant="fe008">
      <nite:child href="Bmr008.F.words.xml#id(Bmr008.w.14,731)"/>
   </dialogueact>
   <dialogueact nite:id="Bmr008.F.dialogueact1447" starttime="3121.57" endtime="3128.4" type="s.%-" adjacency="16a" original-type="s.%-" channel="c8" participant="fe008">
      <nite:child href="Bmr008.F.words.xml#id(Bmr008.w.14,736)..id(Bmr008.disfmarker.603)"/>
   </dialogueact>
   <dialogueact nite:id="Bmr008.F.dialogueact1451" starttime="3131.36" endtime="3131.95" type="s.%-" adjacency="17b-1" original-type="s.%-" channel="c8" participant="fe008">
      <nite:child href="Bmr008.F.words.xml#id(Bmr008.w.14,790)..id(Bmr008.w.14,793)"/>
   </dialogueact>
   <dialogueact nite:id="Bmr008.F.dialogueact1453" starttime="3133.1" endtime="3133.6" type="s^aa" adjacency="18b" original-type="s^aa" channel="c8" participant="fe008">
      <nite:child href="Bmr008.F.words.xml#id(Bmr008.w.14,794)..id(Bmr008.w.14,795)"/>
   </dialogueact>
   <dialogueact nite:id="Bmr008.F.dialogueact1454" starttime="3133.64" endtime="3138.75" type="s" adjacency="19a" original-type="s" channel="c8" participant="fe008">
      <nite:child href="Bmr008.F.words.xml#id(Bmr008.w.14,796)..id(Bmr008.w.14,816)"/>
   </dialogueact>
   <dialogueact nite:id="Bmr008.F.dialogueact1492" starttime="3191.7" endtime="3192.11" type="s^ba" original-type="s^ba" channel="c8" participant="fe008">
      <nite:child href="Bmr008.F.words.xml#id(Bmr008.w.15,054)..id(Bmr008.w.15,055)"/>
   </dialogueact>
   <dialogueact nite:id="Bmr008.F.dialogueact1529" starttime="3263.34" endtime="3265.1" type="s" original-type="s" channel="c8" participant="fe008">
      <nite:child href="Bmr008.F.words.xml#id(Bmr008.w.15,387)..id(Bmr008.w.15,394)"/>
   </dialogueact>
   <dialogueact nite:id="Bmr008.F.dialogueact1542" starttime="3284.19" endtime="3284.64" type="qy^d^rt" adjacency="37b-2" original-type="qy^d^rt" channel="c8" participant="fe008">
      <nite:child href="Bmr008.F.words.xml#id(Bmr008.w.15,474)..id(Bmr008.w.15,475)"/>
   </dialogueact>
   <dialogueact nite:id="Bmr008.F.dialogueact1639" starttime="3524.06" endtime="3526.2" type="s.%--" original-type="s.%--" channel="c8" participant="fe008">
      <nite:child href="Bmr008.F.words.xml#id(Bmr008.w.16,353)..id(Bmr008.disfmarker.684)"/>
   </dialogueact>
   <dialogueact nite:id="Bmr008.F.dialogueact1640" starttime="3526.2" endtime="3529.35" type="s" original-type="s" channel="c8" participant="fe008">
      <nite:child href="Bmr008.F.words.xml#id(Bmr008.w.16,360)..id(Bmr008.w.16,372)"/>
   </dialogueact>
   <dialogueact nite:id="Bmr008.F.dialogueact1641" starttime="3529.35" endtime="3529.54" type="qy^d^g" original-type="qy^d^g" channel="c8" participant="fe008">
      <nite:child href="Bmr008.F.words.xml#id(Bmr008.w.16,373)..id(Bmr008.w.16,374)"/>
   </dialogueact>
   <dialogueact nite:id="Bmr008.F.dialogueact1642" starttime="3529.54" endtime="3530.22" type="qy^bu^rt" original-type="qy^bu^rt" channel="c8" participant="fe008">
      <nite:child href="Bmr008.F.words.xml#id(Bmr008.w.16,375)..id(Bmr008.w.16,378)"/>
   </dialogueact>
   <dialogueact nite:id="Bmr008.F.dialogueact1644" starttime="3531.09" endtime="3548.07" type="s" adjacency="52a" original-type="s" channel="c8" participant="fe008">
      <nite:child href="Bmr008.F.words.xml#id(Bmr008.w.16,381)..id(Bmr008.w.16,437)"/>
   </dialogueact>
   <dialogueact nite:id="Bmr008.F.dialogueact1646" starttime="3548.07" endtime="3550.46" type="s^cs.%--" original-type="s^cs.%--" channel="c8" participant="fe008">
      <nite:child href="Bmr008.F.words.xml#id(Bmr008.w.16,438)..id(Bmr008.w.16,447)"/>
   </dialogueact>
   <dialogueact nite:id="Bmr008.F.dialogueact1648" starttime="3551.15" endtime="3552.86" type="s^cs" original-type="s^cs" channel="c8" participant="fe008">
      <nite:child href="Bmr008.F.words.xml#id(Bmr008.w.16,451)..id(Bmr008.disfmarker.688)"/>
   </dialogueact>
   <dialogueact nite:id="Bmr008.F.dialogueact1649" starttime="3553.62" endtime="3554.47" type="s" original-type="s" channel="c8" participant="fe008">
      <nite:child href="Bmr008.F.words.xml#id(Bmr008.w.16,464)..id(Bmr008.w.16,466)"/>
   </dialogueact>
   <dialogueact nite:id="Bmr008.F.dialogueact1650" starttime="3554.47" endtime="3557.02" type="s^cs" adjacency="53a" original-type="s^cs" channel="c8" participant="fe008">
      <nite:child href="Bmr008.F.words.xml#id(Bmr008.w.16,467)..id(Bmr008.w.16,478)"/>
   </dialogueact>
   <dialogueact nite:id="Bmr008.F.dialogueact1654" starttime="3560.35" endtime="3560.7" type="s^ba.%" original-type="s^ba.%" channel="c8" participant="fe008">
      <nite:child href="Bmr008.F.words.xml#id(Bmr008.w.16,500)..id(Bmr008.w.16,503)"/>
   </dialogueact>
   <dialogueact nite:id="Bmr008.F.dialogueact1658" starttime="3571.64" endtime="3571.88" type="b" original-type="b" channel="c8" participant="fe008">
      <nite:child href="Bmr008.F.words.xml#id(Bmr008.w.16,551)..id(Bmr008.w.16,552)"/>
   </dialogueact>
   <dialogueact nite:id="Bmr008.F.dialogueact1732" starttime="3716.4" endtime="3716.87" type="s^aa" original-type="s^aa" channel="c8" participant="fe008">
      <nite:child href="Bmr008.F.words.xml#id(Bmr008.w.17,152)..id(Bmr008.w.17,155)"/>
   </dialogueact>
   <dialogueact nite:id="Bmr008.F.dialogueact1733" starttime="3717.1" endtime="3717.9" type="s^ba" original-type="s^ba" channel="c8" participant="fe008">
      <nite:child href="Bmr008.F.words.xml#id(Bmr008.w.17,156)..id(Bmr008.w.17,159)"/>
   </dialogueact>
   <dialogueact nite:id="Bmr008.F.dialogueact1749" starttime="3753.94" endtime="3754.66" type="s^ba" adjacency="15b" original-type="s^ba" channel="c8" participant="fe008">
      <nite:child href="Bmr008.F.words.xml#id(Bmr008.w.17,294)..id(Bmr008.w.17,299)"/>
   </dialogueact>
   <dialogueact nite:id="Bmr008.F.dialogueact1750" starttime="3754.66" endtime="3756.26" type="s" adjacency="15b+" original-type="s" channel="c8" participant="fe008">
      <nite:child href="Bmr008.F.words.xml#id(Bmr008.w.17,300)..id(Bmr008.w.17,308)"/>
   </dialogueact>
   <dialogueact nite:id="Bmr008.F.dialogueact1752" starttime="3757.39" endtime="3757.66" type="b" original-type="b" channel="c8" participant="fe008">
      <nite:child href="Bmr008.F.words.xml#id(Bmr008.w.17,319)..id(Bmr008.w.17,320)"/>
   </dialogueact>
   <dialogueact nite:id="Bmr008.F.dialogueact1795" starttime="3844.32" endtime="3844.81" type="s^bk" original-type="s^bk" channel="c8" participant="fe008">
      <nite:child href="Bmr008.F.words.xml#id(Bmr008.w.17,664)..id(Bmr008.w.17,667)"/>
   </dialogueact>
   <dialogueact nite:id="Bmr008.F.dialogueact1797" starttime="3846.52" endtime="3846.83" type="s^bk" original-type="s^bk" channel="c8" participant="fe008">
      <nite:child href="Bmr008.F.words.xml#id(Bmr008.w.17,668)..id(Bmr008.w.17,669)"/>
   </dialogueact>
</nite:root>