<?xml version="1.0" encoding="ISO-8859-1" standalone="yes"?>
<nite:root nite:id="Bsr001.C.dialogue-acts" xmlns:nite="http://nite.sourceforge.net/">
   <dialogueact nite:id="Bsr001.C.dialogueact7" starttime="21.652" endtime="23.162" type="z" original-type="z" channel="c2" participant="mn057">
      <nite:child href="Bsr001.C.words.xml#id(Bsr001.w.99)..id(Bsr001.w.108)"/>
   </dialogueact>
   <dialogueact nite:id="Bsr001.C.dialogueact9" starttime="23.162" endtime="24.162" type="z" original-type="z" channel="c2" participant="mn057">
      <nite:child href="Bsr001.C.words.xml#id(Bsr001.w.109)..id(Bsr001.w.114)"/>
   </dialogueact>
   <dialogueact nite:id="Bsr001.C.dialogueact18" starttime="30.251" endtime="33.611" type="z" original-type="z" channel="c2" participant="mn057">
      <nite:child href="Bsr001.C.words.xml#id(Bsr001.w.139)..id(Bsr001.w.187)"/>
   </dialogueact>
   <dialogueact nite:id="Bsr001.C.dialogueact27" starttime="42.49" endtime="43.01" type="z" original-type="z" channel="c2" participant="mn057">
      <nite:child href="Bsr001.C.words.xml#id(Bsr001.w.218)..id(Bsr001.w.221)"/>
   </dialogueact>
   <dialogueact nite:id="Bsr001.C.dialogueact28" starttime="44.39" endtime="44.86" type="z" original-type="z" channel="c2" participant="mn057">
      <nite:child href="Bsr001.C.words.xml#id(Bsr001.w.222)..id(Bsr001.w.225)"/>
   </dialogueact>
   <dialogueact nite:id="Bsr001.C.dialogueact30" starttime="45.19" endtime="45.7" type="z" original-type="z" channel="c2" participant="mn057">
      <nite:child href="Bsr001.C.words.xml#id(Bsr001.w.233)..id(Bsr001.w.235)"/>
   </dialogueact>
   <dialogueact nite:id="Bsr001.C.dialogueact34" starttime="47.66" endtime="48.32" type="z" original-type="z" channel="c2" participant="mn057">
      <nite:child href="Bsr001.C.words.xml#id(Bsr001.w.251)..id(Bsr001.w.253)"/>
   </dialogueact>
   <dialogueact nite:id="Bsr001.C.dialogueact42" starttime="52.27" endtime="52.74" type="z" original-type="z" channel="c2" participant="mn057">
      <nite:child href="Bsr001.C.words.xml#id(Bsr001.w.271)..id(Bsr001.disfmarker.5)"/>
   </dialogueact>
   <dialogueact nite:id="Bsr001.C.dialogueact43" starttime="53.07" endtime="53.74" type="z" original-type="z" channel="c2" participant="mn057">
      <nite:child href="Bsr001.C.words.xml#id(Bsr001.w.272)..id(Bsr001.w.278)"/>
   </dialogueact>
   <dialogueact nite:id="Bsr001.C.dialogueact44" starttime="54.06" endtime="54.19" type="z" original-type="z" channel="c2" participant="mn057">
      <nite:child href="Bsr001.C.words.xml#id(Bsr001.w.279)..id(Bsr001.w.280)"/>
   </dialogueact>
   <dialogueact nite:id="Bsr001.C.dialogueact49" starttime="56.84" endtime="57.54" type="z" original-type="z" channel="c2" participant="mn057">
      <nite:child href="Bsr001.C.words.xml#id(Bsr001.w.305)..id(Bsr001.w.309)"/>
   </dialogueact>
   <dialogueact nite:id="Bsr001.C.dialogueact57" starttime="61.43" endtime="62.36" type="z" original-type="z" channel="c2" participant="mn057">
      <nite:child href="Bsr001.C.words.xml#id(Bsr001.w.339)..id(Bsr001.w.345)"/>
   </dialogueact>
   <dialogueact nite:id="Bsr001.C.dialogueact60" starttime="63.8" endtime="64.05" type="z" original-type="z" channel="c2" participant="mn057">
      <nite:child href="Bsr001.C.words.xml#id(Bsr001.w.354)..id(Bsr001.w.355)"/>
   </dialogueact>
   <dialogueact nite:id="Bsr001.C.dialogueact61" starttime="64.18" endtime="64.91" type="z" original-type="z" channel="c2" participant="mn057">
      <nite:child href="Bsr001.C.words.xml#id(Bsr001.w.356)..id(Bsr001.w.362)"/>
   </dialogueact>
   <dialogueact nite:id="Bsr001.C.dialogueact62" starttime="65.16" endtime="65.58" type="z" original-type="z" channel="c2" participant="mn057">
      <nite:child href="Bsr001.C.words.xml#id(Bsr001.w.363)..id(Bsr001.w.364)"/>
   </dialogueact>
   <dialogueact nite:id="Bsr001.C.dialogueact65" starttime="65.84" endtime="66.28" type="z" original-type="z" channel="c2" participant="mn057">
      <nite:child href="Bsr001.C.words.xml#id(Bsr001.w.365)..id(Bsr001.disfmarker.8)"/>
   </dialogueact>
   <dialogueact nite:id="Bsr001.C.dialogueact67" starttime="66.8" endtime="69.51" type="z" original-type="z" channel="c2" participant="mn057">
      <nite:child href="Bsr001.C.words.xml#id(Bsr001.w.386)..id(Bsr001.w.400)"/>
   </dialogueact>
   <dialogueact nite:id="Bsr001.C.dialogueact70" starttime="69.51" endtime="69.82" type="z" original-type="z" channel="c2" participant="mn057">
      <nite:child href="Bsr001.C.words.xml#id(Bsr001.w.401)..id(Bsr001.w.402)"/>
   </dialogueact>
   <dialogueact nite:id="Bsr001.C.dialogueact77" starttime="71.91" endtime="72.15" type="z" original-type="z" channel="c2" participant="mn057">
      <nite:child href="Bsr001.C.words.xml#id(Bsr001.w.451)..id(Bsr001.w.452)"/>
   </dialogueact>
   <dialogueact nite:id="Bsr001.C.dialogueact91" starttime="79.037" endtime="79.397" type="z" original-type="z" channel="c2" participant="mn057">
      <nite:child href="Bsr001.C.words.xml#id(Bsr001.w.546)..id(Bsr001.w.547)"/>
   </dialogueact>
   <dialogueact nite:id="Bsr001.C.dialogueact109" starttime="95.26" endtime="96.46" type="z" original-type="z" channel="c2" participant="mn057">
      <nite:child href="Bsr001.C.words.xml#id(Bsr001.w.616)..id(Bsr001.w.619)"/>
   </dialogueact>
   <dialogueact nite:id="Bsr001.C.dialogueact117" starttime="107.53" endtime="108.03" type="z" original-type="z" channel="c2" participant="mn057">
      <nite:child href="Bsr001.C.words.xml#id(Bsr001.w.672)..id(Bsr001.w.673)"/>
   </dialogueact>
   <dialogueact nite:id="Bsr001.C.dialogueact120" starttime="108.821" endtime="109.331" type="z" original-type="z" channel="c2" participant="mn057">
      <nite:child href="Bsr001.C.words.xml#id(Bsr001.w.688)..id(Bsr001.disfmarker.14)"/>
   </dialogueact>
   <dialogueact nite:id="Bsr001.C.dialogueact145" starttime="133.23" endtime="135.79" type="z" original-type="z" channel="c2" participant="mn057">
      <nite:child href="Bsr001.C.words.xml#id(Bsr001.w.836)..id(Bsr001.w.852)"/>
   </dialogueact>
   <dialogueact nite:id="Bsr001.C.dialogueact198" starttime="188.92" endtime="190.98" type="s" adjacency="7a" original-type="s" channel="c2" participant="mn057">
      <nite:child href="Bsr001.C.words.xml#id(Bsr001.w.1,176)..id(Bsr001.w.1,187)"/>
   </dialogueact>
   <dialogueact nite:id="Bsr001.C.dialogueact201" starttime="190.98" endtime="191.72" type="s" adjacency="7a+" original-type="s" channel="c2" participant="mn057">
      <nite:child href="Bsr001.C.words.xml#id(Bsr001.w.1,188)..id(Bsr001.w.1,193)"/>
   </dialogueact>
   <dialogueact nite:id="Bsr001.C.dialogueact204" starttime="194.256" endtime="195.856" type="s" original-type="s" channel="c2" participant="mn057">
      <nite:child href="Bsr001.C.words.xml#id(Bsr001.w.1,223)..id(Bsr001.w.1,229)"/>
   </dialogueact>
   <dialogueact nite:id="Bsr001.C.dialogueact210" starttime="204.8" endtime="205.71" type="s" original-type="s" channel="c2" participant="mn057">
      <nite:child href="Bsr001.C.words.xml#id(Bsr001.w.1,275)..id(Bsr001.w.1,281)"/>
   </dialogueact>
   <dialogueact nite:id="Bsr001.C.dialogueact214" starttime="207.02" endtime="207.37" type="s^fe" original-type="s^fe" channel="c2" participant="mn057">
      <nite:child href="Bsr001.C.words.xml#id(Bsr001.w.1,291)..id(Bsr001.w.1,292)"/>
   </dialogueact>
   <dialogueact nite:id="Bsr001.C.dialogueact261" starttime="251.65" endtime="254.49" type="s^aa|s" adjacency="18b-1.19a" original-type="s^aa|s" channel="c2" participant="mn057">
      <nite:child href="Bsr001.C.words.xml#id(Bsr001.w.1,576)..id(Bsr001.disfmarker.69)"/>
   </dialogueact>
   <dialogueact nite:id="Bsr001.C.dialogueact273" starttime="265.24" endtime="265.68" type="s^fe" adjacency="20a" original-type="s^fe" channel="c2" participant="mn057">
      <nite:child href="Bsr001.C.words.xml#id(Bsr001.w.1,657)..id(Bsr001.w.1,658)"/>
   </dialogueact>
   <dialogueact nite:id="Bsr001.C.dialogueact289" starttime="278.828" endtime="279.008" type="s^aa" original-type="s^aa" channel="c2" participant="mn057">
      <nite:child href="Bsr001.C.words.xml#id(Bsr001.w.1,750)..id(Bsr001.w.1,751)"/>
   </dialogueact>
   <dialogueact nite:id="Bsr001.C.dialogueact290" starttime="279.008" endtime="279.708" type="s^co" original-type="s^co" channel="c2" participant="mn057">
      <nite:child href="Bsr001.C.words.xml#id(Bsr001.w.1,752)..id(Bsr001.w.1,755)"/>
   </dialogueact>
   <dialogueact nite:id="Bsr001.C.dialogueact323" starttime="316.27" endtime="316.85" type="qw^t3" original-type="qw^t3" channel="c2" participant="mn057">
      <nite:child href="Bsr001.C.words.xml#id(Bsr001.w.2,015)..id(Bsr001.w.2,019)"/>
   </dialogueact>
   <dialogueact nite:id="Bsr001.C.dialogueact349" starttime="340.2" endtime="344.68" type="s" adjacency="30b.31a" original-type="s" channel="c2" participant="mn057">
      <nite:child href="Bsr001.C.words.xml#id(Bsr001.w.2,208)..id(Bsr001.w.2,224)"/>
   </dialogueact>
   <dialogueact nite:id="Bsr001.C.dialogueact413" starttime="377.6" endtime="378.61" type="s^na" adjacency="37b" original-type="s^na" channel="c2" participant="mn057">
      <nite:child href="Bsr001.C.words.xml#id(Bsr001.w.2,610)..id(Bsr001.w.2,616)"/>
   </dialogueact>
   <dialogueact nite:id="Bsr001.C.dialogueact414" starttime="378.61" endtime="378.85" type="s^aa" adjacency="37b+" original-type="s^aa" channel="c2" participant="mn057">
      <nite:child href="Bsr001.C.words.xml#id(Bsr001.w.2,617)..id(Bsr001.w.2,618)"/>
   </dialogueact>
   <dialogueact nite:id="Bsr001.C.dialogueact415" starttime="378.85" endtime="381.79" type="s.%-" adjacency="37b++" original-type="s.%-" channel="c2" participant="mn057">
      <nite:child href="Bsr001.C.words.xml#id(Bsr001.w.2,619)..id(Bsr001.disfmarker.114)"/>
   </dialogueact>
   <dialogueact nite:id="Bsr001.C.dialogueact475" starttime="419.4" endtime="421.64" type="s^bk|s" adjacency="48b" original-type="s^bk|s" channel="c2" participant="mn057">
      <nite:child href="Bsr001.C.words.xml#id(Bsr001.w.2,965)..id(Bsr001.w.2,981)"/>
   </dialogueact>
   <dialogueact nite:id="Bsr001.C.dialogueact477" starttime="421.64" endtime="421.73" type="fh" original-type="fh" channel="c2" participant="mn057">
      <nite:child href="Bsr001.C.words.xml#id(Bsr001.w.2,982)..id(Bsr001.w.2,983)"/>
   </dialogueact>
   <dialogueact nite:id="Bsr001.C.dialogueact518" starttime="459.12" endtime="460.31" type="s^j" adjacency="53b-2.54a" original-type="s^j" channel="c2" participant="mn057">
      <nite:child href="Bsr001.C.words.xml#id(Bsr001.w.3,256)..id(Bsr001.w.3,264)"/>
   </dialogueact>
   <dialogueact nite:id="Bsr001.C.dialogueact519" starttime="460.48" endtime="460.78" type="%-" original-type="%-" channel="c2" participant="mn057">
      <nite:child href="Bsr001.C.words.xml#id(Bsr001.w.3,265)..id(Bsr001.disfmarker.149)"/>
   </dialogueact>
   <dialogueact nite:id="Bsr001.C.dialogueact527" starttime="467.737" endtime="468.487" type="b" original-type="b" channel="c2" participant="mn057">
      <nite:child href="Bsr001.C.words.xml#id(Bsr001.w.3,316)..id(Bsr001.w.3,317)"/>
   </dialogueact>
   <dialogueact nite:id="Bsr001.C.dialogueact576" starttime="518.95" endtime="519.22" type="qy^bh" adjacency="63b" original-type="qy^bh" channel="c2" participant="mn057">
      <nite:child href="Bsr001.C.words.xml#id(Bsr001.w.3,631)..id(Bsr001.w.3,632)"/>
   </dialogueact>
   <dialogueact nite:id="Bsr001.C.dialogueact577" starttime="519.22" endtime="521.35" type="qy^d" adjacency="63b+.65a" original-type="qy^d" channel="c2" participant="mn057">
      <nite:child href="Bsr001.C.words.xml#id(Bsr001.w.3,633)..id(Bsr001.w.3,639)"/>
   </dialogueact>
   <dialogueact nite:id="Bsr001.C.dialogueact580" starttime="521.35" endtime="521.74" type="qrr.%--" adjacency="63b++" original-type="qrr.%--" channel="c2" participant="mn057">
      <nite:child href="Bsr001.C.words.xml#id(Bsr001.w.3,640)..id(Bsr001.w.3,641)"/>
   </dialogueact>
   <dialogueact nite:id="Bsr001.C.dialogueact582" starttime="522.86" endtime="523.01" type="qy^bh" adjacency="66b" original-type="qy^bh" channel="c2" participant="mn057">
      <nite:child href="Bsr001.C.words.xml#id(Bsr001.w.3,655)..id(Bsr001.w.3,656)"/>
   </dialogueact>
   <dialogueact nite:id="Bsr001.C.dialogueact588" starttime="525.991" endtime="526.251" type="s^ba^fe" adjacency="69b" original-type="s^ba^fe" channel="c2" participant="mn057">
      <nite:child href="Bsr001.C.words.xml#id(Bsr001.w.3,685)..id(Bsr001.w.3,686)"/>
   </dialogueact>
   <dialogueact nite:id="Bsr001.C.dialogueact591" starttime="527.048" endtime="527.398" type="%" original-type="%" channel="c2" participant="mn057">
      <nite:child href="Bsr001.C.words.xml#id(Bsr001.w.3,697)..id(Bsr001.w.3,698)"/>
   </dialogueact>
   <dialogueact nite:id="Bsr001.C.dialogueact594" starttime="528.58" endtime="529.16" type="b" original-type="b" channel="c2" participant="mn057">
      <nite:child href="Bsr001.C.words.xml#id(Bsr001.w.3,700)..id(Bsr001.w.3,701)"/>
   </dialogueact>
   <dialogueact nite:id="Bsr001.C.dialogueact659" starttime="664.041" endtime="664.971" type="b" original-type="b" channel="c2" participant="mn057">
      <nite:child href="Bsr001.C.words.xml#id(Bsr001.w.4,224)..id(Bsr001.w.4,225)"/>
   </dialogueact>
   <dialogueact nite:id="Bsr001.C.dialogueact660" starttime="664.971" endtime="665.161" type="b" original-type="b" channel="c2" participant="mn057">
      <nite:child href="Bsr001.C.words.xml#id(Bsr001.w.4,226)..id(Bsr001.w.4,227)"/>
   </dialogueact>
   <dialogueact nite:id="Bsr001.C.dialogueact808" starttime="912.005" endtime="912.785" type="b" original-type="b" channel="c2" participant="mn057">
      <nite:child href="Bsr001.C.words.xml#id(Bsr001.w.5,501)..id(Bsr001.w.5,504)"/>
   </dialogueact>
   <dialogueact nite:id="Bsr001.C.dialogueact833" starttime="939.9" endtime="946.74" type="s^bk|s" adjacency="29b.30a" original-type="s^bk|s" channel="c2" participant="mn057">
      <nite:child href="Bsr001.C.words.xml#id(Bsr001.w.5,663)..id(Bsr001.w.5,697)"/>
   </dialogueact>
   <dialogueact nite:id="Bsr001.C.dialogueact836" starttime="946.74" endtime="947.07" type="fh" original-type="fh" channel="c2" participant="mn057">
      <nite:child href="Bsr001.C.words.xml#id(Bsr001.w.5,698)..id(Bsr001.w.5,699)"/>
   </dialogueact>
   <dialogueact nite:id="Bsr001.C.dialogueact839" starttime="949.32" endtime="953.79" type="s^e" adjacency="31a" original-type="s^e" channel="c2" participant="mn057">
      <nite:child href="Bsr001.C.words.xml#id(Bsr001.w.5,712)..id(Bsr001.w.5,732)"/>
   </dialogueact>
   <dialogueact nite:id="Bsr001.C.dialogueact841" starttime="953.94" endtime="954.08" type="%" original-type="%" channel="c2" participant="mn057">
      <nite:child href="Bsr001.C.words.xml#id(Bsr001.w.5,733)..id(Bsr001.w.5,734)"/>
   </dialogueact>
   <dialogueact nite:id="Bsr001.C.dialogueact844" starttime="954.56" endtime="956.23" type="s^e" original-type="s^e" channel="c2" participant="mn057">
      <nite:child href="Bsr001.C.words.xml#id(Bsr001.w.5,748)..id(Bsr001.w.5,756)"/>
   </dialogueact>
   <dialogueact nite:id="Bsr001.C.dialogueact846" starttime="957.135" endtime="957.365" type="s^aa" adjacency="32b" original-type="s^aa" channel="c2" participant="mn057">
      <nite:child href="Bsr001.C.words.xml#id(Bsr001.w.5,761)..id(Bsr001.w.5,762)"/>
   </dialogueact>
   <dialogueact nite:id="Bsr001.C.dialogueact847" starttime="957.695" endtime="960.515" type="s" adjacency="32b+" original-type="s" channel="c2" participant="mn057">
      <nite:child href="Bsr001.C.words.xml#id(Bsr001.w.5,763)..id(Bsr001.w.5,777)"/>
   </dialogueact>
   <dialogueact nite:id="Bsr001.C.dialogueact851" starttime="961.728" endtime="963.008" type="s^rt" adjacency="33b.34a" original-type="s^rt" channel="c2" participant="mn057">
      <nite:child href="Bsr001.C.words.xml#id(Bsr001.w.5,791)..id(Bsr001.w.5,796)"/>
   </dialogueact>
   <dialogueact nite:id="Bsr001.C.dialogueact852" starttime="963.008" endtime="963.798" type="fh" original-type="fh" channel="c2" participant="mn057">
      <nite:child href="Bsr001.C.words.xml#id(Bsr001.w.5,797)..id(Bsr001.w.5,798)"/>
   </dialogueact>
   <dialogueact nite:id="Bsr001.C.dialogueact855" starttime="964.188" endtime="965.978" type="s^aa|s^na" adjacency="35b.36a" original-type="s^aa|s^na" channel="c2" participant="mn057">
      <nite:child href="Bsr001.C.words.xml#id(Bsr001.w.5,808)..id(Bsr001.w.5,814)"/>
   </dialogueact>
   <dialogueact nite:id="Bsr001.C.dialogueact859" starttime="969.59" endtime="970.19" type="s" adjacency="37b.38a" original-type="s" channel="c2" participant="mn057">
      <nite:child href="Bsr001.C.words.xml#id(Bsr001.w.5,839)..id(Bsr001.w.5,842)"/>
   </dialogueact>
   <dialogueact nite:id="Bsr001.C.dialogueact861" starttime="971.46" endtime="972.67" type="s.%--" adjacency="37b+" original-type="s.%--" channel="c2" participant="mn057">
      <nite:child href="Bsr001.C.words.xml#id(Bsr001.w.5,847)..id(Bsr001.disfmarker.226)"/>
   </dialogueact>
   <dialogueact nite:id="Bsr001.C.dialogueact862" starttime="972.67" endtime="973.55" type="%--" adjacency="37b++" original-type="%--" channel="c2" participant="mn057">
      <nite:child href="Bsr001.C.words.xml#id(Bsr001.w.5,851)..id(Bsr001.disfmarker.228)"/>
   </dialogueact>
   <dialogueact nite:id="Bsr001.C.dialogueact863" starttime="974.44" endtime="974.87" type="%--" adjacency="37b+++" original-type="%--" channel="c2" participant="mn057">
      <nite:child href="Bsr001.C.words.xml#id(Bsr001.w.5,853)..id(Bsr001.disfmarker.229)"/>
   </dialogueact>
   <dialogueact nite:id="Bsr001.C.dialogueact864" starttime="974.87" endtime="975.52" type="%--" adjacency="37b++++" original-type="%--" channel="c2" participant="mn057">
      <nite:child href="Bsr001.C.words.xml#id(Bsr001.w.5,854)..id(Bsr001.disfmarker.230)"/>
   </dialogueact>
   <dialogueact nite:id="Bsr001.C.dialogueact865" starttime="976.882" endtime="979.952" type="s^df" adjacency="37b+++++" original-type="s^df" channel="c2" participant="mn057">
      <nite:child href="Bsr001.C.words.xml#id(Bsr001.w.5,858)..id(Bsr001.w.5,871)"/>
   </dialogueact>
   <dialogueact nite:id="Bsr001.C.dialogueact866" starttime="979.952" endtime="982.082" type="s^df" adjacency="37b++++++" original-type="s^df" channel="c2" participant="mn057">
      <nite:child href="Bsr001.C.words.xml#id(Bsr001.w.5,872)..id(Bsr001.w.5,878)"/>
   </dialogueact>
   <dialogueact nite:id="Bsr001.C.dialogueact867" starttime="982.692" endtime="986.032" type="s^no" adjacency="37b+++++++" original-type="s^no" channel="c2" participant="mn057">
      <nite:child href="Bsr001.C.words.xml#id(Bsr001.w.5,879)..id(Bsr001.w.5,892)"/>
   </dialogueact>
   <dialogueact nite:id="Bsr001.C.dialogueact868" starttime="986.032" endtime="990.072" type="s^df" adjacency="37b++++++++.39a" original-type="s^df" channel="c2" participant="mn057">
      <nite:child href="Bsr001.C.words.xml#id(Bsr001.w.5,893)..id(Bsr001.w.5,917)"/>
   </dialogueact>
   <dialogueact nite:id="Bsr001.C.dialogueact870" starttime="990.552" endtime="994.802" type="fh|s^no" adjacency="37b+++++++++" original-type="fh|s^no" channel="c2" participant="mn057">
      <nite:child href="Bsr001.C.words.xml#id(Bsr001.w.5,920)..id(Bsr001.w.5,935)"/>
   </dialogueact>
   <dialogueact nite:id="Bsr001.C.dialogueact871" starttime="994.922" endtime="995.522" type="fh" original-type="fh" channel="c2" participant="mn057">
      <nite:child href="Bsr001.C.words.xml#id(Bsr001.w.5,936)..id(Bsr001.w.5,937)"/>
   </dialogueact>
   <dialogueact nite:id="Bsr001.C.dialogueact872" starttime="995.522" endtime="999.182" type="s^df.%--" adjacency="37b++++++++++" original-type="s^df.%--" channel="c2" participant="mn057">
      <nite:child href="Bsr001.C.words.xml#id(Bsr001.w.5,938)..id(Bsr001.disfmarker.235)"/>
   </dialogueact>
   <dialogueact nite:id="Bsr001.C.dialogueact873" starttime="1000.22" endtime="1001.99" type="s^am" adjacency="37b+++++++++++.40a" original-type="s^am" channel="c2" participant="mn057">
      <nite:child href="Bsr001.C.words.xml#id(Bsr001.w.5,952)..id(Bsr001.w.5,959)"/>
   </dialogueact>
   <dialogueact nite:id="Bsr001.C.dialogueact875" starttime="1001.99" endtime="1002.54" type="s^aa" adjacency="37b++++++++++++" original-type="s^aa" channel="c2" participant="mn057">
      <nite:child href="Bsr001.C.words.xml#id(Bsr001.w.5,960)..id(Bsr001.w.5,963)"/>
   </dialogueact>
   <dialogueact nite:id="Bsr001.C.dialogueact877" starttime="1005.22" endtime="1006.65" type="s^aa" adjacency="41b" original-type="s^aa" channel="c2" participant="mn057">
      <nite:child href="Bsr001.C.words.xml#id(Bsr001.w.5,984)..id(Bsr001.w.5,987)"/>
   </dialogueact>
   <dialogueact nite:id="Bsr001.C.dialogueact879" starttime="1007.28" endtime="1007.57" type="b" original-type="b" channel="c2" participant="mn057">
      <nite:child href="Bsr001.C.words.xml#id(Bsr001.w.5,990)..id(Bsr001.w.5,991)"/>
   </dialogueact>
   <dialogueact nite:id="Bsr001.C.dialogueact881" starttime="1009.18" endtime="1009.75" type="b" original-type="b" channel="c2" participant="mn057">
      <nite:child href="Bsr001.C.words.xml#id(Bsr001.w.6,010)..id(Bsr001.w.6,011)"/>
   </dialogueact>
   <dialogueact nite:id="Bsr001.C.dialogueact886" starttime="1023.28" endtime="1023.38" type="fg" original-type="fg" channel="c2" participant="mn057">
      <nite:child href="Bsr001.C.words.xml#id(Bsr001.w.6,051)..id(Bsr001.w.6,052)"/>
   </dialogueact>
   <dialogueact nite:id="Bsr001.C.dialogueact887" starttime="1023.38" endtime="1026.83" type="s.%--" adjacency="42b" original-type="s.%--" channel="c2" participant="mn057">
      <nite:child href="Bsr001.C.words.xml#id(Bsr001.w.6,053)..id(Bsr001.w.6,069)"/>
   </dialogueact>
   <dialogueact nite:id="Bsr001.C.dialogueact889" starttime="1027.71" endtime="1037.35" type="fh|s" adjacency="42b+" original-type="fh|s" channel="c2" participant="mn057">
      <nite:child href="Bsr001.C.words.xml#id(Bsr001.w.6,072)..id(Bsr001.w.6,110)"/>
   </dialogueact>
   <dialogueact nite:id="Bsr001.C.dialogueact892" starttime="1037.83" endtime="1041.44" type="s^df" adjacency="42b++" original-type="s^df" channel="c2" participant="mn057">
      <nite:child href="Bsr001.C.words.xml#id(Bsr001.w.6,119)..id(Bsr001.w.6,134)"/>
   </dialogueact>
   <dialogueact nite:id="Bsr001.C.dialogueact894" starttime="1042.13" endtime="1043.88" type="fh" original-type="fh" channel="c2" participant="mn057">
      <nite:child href="Bsr001.C.words.xml#id(Bsr001.w.6,139)..id(Bsr001.w.6,144)"/>
   </dialogueact>
   <dialogueact nite:id="Bsr001.C.dialogueact895" starttime="1044.34" endtime="1047.35" type="s^bk|s" adjacency="42b+++.43a" original-type="s^bk|s" channel="c2" participant="mn057">
      <nite:child href="Bsr001.C.words.xml#id(Bsr001.w.6,145)..id(Bsr001.w.6,158)"/>
   </dialogueact>
   <dialogueact nite:id="Bsr001.C.dialogueact896" starttime="1047.35" endtime="1048.06" type="%--" original-type="%--" channel="c2" participant="mn057">
      <nite:child href="Bsr001.C.words.xml#id(Bsr001.w.6,159)..id(Bsr001.w.6,163)"/>
   </dialogueact>
   <dialogueact nite:id="Bsr001.C.dialogueact898" starttime="1048.43" endtime="1052.15" type="s^df" adjacency="42b++++.44a" original-type="s^df" channel="c2" participant="mn057">
      <nite:child href="Bsr001.C.words.xml#id(Bsr001.w.6,174)..id(Bsr001.w.6,188)"/>
   </dialogueact>
   <dialogueact nite:id="Bsr001.C.dialogueact900" starttime="1052.15" endtime="1052.41" type="fh" original-type="fh" channel="c2" participant="mn057">
      <nite:child href="Bsr001.C.words.xml#id(Bsr001.w.6,189)..id(Bsr001.disfmarker.244)"/>
   </dialogueact>
   <dialogueact nite:id="Bsr001.C.dialogueact1540" starttime="1988.98" endtime="1995.53" type="s" adjacency="27b.28a" original-type="s" channel="c2" participant="mn057">
      <nite:child href="Bsr001.C.words.xml#id(Bsr001.w.11,150)..id(Bsr001.w.11,176)"/>
   </dialogueact>
   <dialogueact nite:id="Bsr001.C.dialogueact1567" starttime="2019.72" endtime="2020.95" type="s^j^nd" adjacency="32b" original-type="s^j^nd" channel="c2" participant="mn057">
      <nite:child href="Bsr001.C.words.xml#id(Bsr001.w.11,342)..id(Bsr001.w.11,346)"/>
   </dialogueact>
   <dialogueact nite:id="Bsr001.C.dialogueact2312" starttime="3114.77" endtime="3118.9" type="s" adjacency="4b" original-type="s" channel="c2" participant="mn057">
      <nite:child href="Bsr001.C.words.xml#id(Bsr001.w.17,292)..id(Bsr001.w.17,309)"/>
   </dialogueact>
   <dialogueact nite:id="Bsr001.C.dialogueact2389" starttime="3220.72" endtime="3220.86" type="b" original-type="b" channel="c2" participant="mn057">
      <nite:child href="Bsr001.C.words.xml#id(Bsr001.w.17,980)..id(Bsr001.w.17,981)"/>
   </dialogueact>
   <dialogueact nite:id="Bsr001.C.dialogueact2459" starttime="3295.05" endtime="3296.35" type="s" original-type="s" channel="c2" participant="mn057">
      <nite:child href="Bsr001.C.words.xml#id(Bsr001.w.18,460)..id(Bsr001.w.18,464)"/>
   </dialogueact>
</nite:root>